Workbook

Sheet 📊 DASHBOARD
A1: 🕉 SRI PONNIAMMAN TEMPLE — ANNUAL ACCOUNTS 🕉
A2: Multi-Year Dashboard — Select Year to View Annual Summary
A4: 📅 SELECT YEAR
A5: Select Year ▼ | D5: 2026
A7: 📊 FINANCIAL SUMMARY
A8: ANNUAL BUDGET (₹) | D8: {=IFERROR(INDIRECT($D$5&"!D9"),0)} -> 177000
A9: DONATIONS PLEDGED (₹) | D9: {=IFERROR(INDIRECT($D$5&"!D10"),0)} -> 307803
A10: RECEIVED (₹) | D10: {=IFERROR(INDIRECT($D$5&"!D11"),0)} -> 247803
A11: PENDING (₹) | D11: {=IFERROR(INDIRECT($D$5&"!D12"),0)} -> 60000
A12: IN-KIND DONATIONS (₹) | D12: {=IFERROR(INDIRECT($D$5&"!D13"),0)} -> 8400
A13: TOTAL EXPENSES (₹) | D13: {=IFERROR(INDIRECT($D$5&"!D14"),0)} -> 147622
A14: NET SURPLUS / (DEFICIT) (₹) | D14: {=IFERROR(INDIRECT($D$5&"!D15"),0)} -> 29378
A15: TOTAL DONORS | D15: {=IFERROR(INDIRECT($D$5&"!D16"),0)} -> 47
A17: 💰 EXPENSE CATEGORY BREAKDOWN
A18: # | B18: Category | D18: Budget (₹) | E18: Actual (₹) | F18: Balance (₹)
A19: 1 | B19: Puja & Rituals | D19: {=IFERROR(INDIRECT($D$5&"!D20"),0)} -> 52000 | E19: {=IFERROR(INDIRECT($D$5&"!E20"),0)} -> 16502 | F19: =D19-E19 -> 35498
A20: 2 | B20: Decorations & Flowers | D20: {=IFERROR(INDIRECT($D$5&"!D21"),0)} -> 32500 | E20: {=IFERROR(INDIRECT($D$5&"!E21"),0)} -> 7002 | F20: =D20-E20 -> 25498
A21: 3 | B21: Food & Catering | D21: {=IFERROR(INDIRECT($D$5&"!D22"),0)} -> 45000 | E21: {=IFERROR(INDIRECT($D$5&"!E22"),0)} -> 40000 | F21: =D21-E21 -> 5000
A22: 4 | B22: Infrastructure & Logistics | D22: {=IFERROR(INDIRECT($D$5&"!D23"),0)} -> 28500 | E22: {=IFERROR(INDIRECT($D$5&"!E23"),0)} -> 4787 | F22: =D22-E22 -> 23713
A23: 5 | B23: Miscellaneous | D23: {=IFERROR(INDIRECT($D$5&"!D24"),0)} -> 19000 | E23: {=IFERROR(INDIRECT($D$5&"!E24"),0)} -> 2961 | F23: =D23-E23 -> 16039
A24: 6 | B24: Materials | D24: {=IFERROR(INDIRECT($D$5&"!D25"),0)} -> 0 | E24: {=IFERROR(INDIRECT($D$5&"!E25"),0)} -> 63850 | F24: =D24-E24 -> -63850
A25: 7 | B25: Labour | D25: {=IFERROR(INDIRECT($D$5&"!D26"),0)} -> 0 | E25: {=IFERROR(INDIRECT($D$5&"!E26"),0)} -> 10000 | F25: =D25-E25 -> -10000
A26: 8 | B26: Transport | D26: {=IFERROR(INDIRECT($D$5&"!D27"),0)} -> 0 | E26: {=IFERROR(INDIRECT($D$5&"!E27"),0)} -> 1600 | F26: =D26-E26 -> -1600
A27: 9 | B27: Food | D27: {=IFERROR(INDIRECT($D$5&"!D28"),0)} -> 0 | E27: {=IFERROR(INDIRECT($D$5&"!E28"),0)} -> 920 | F27: =D27-E27 -> -920
A28: TOTAL | D28: =SUM(D19:D27) -> 177000 | E28: =SUM(E19:E27) -> 147622 | F28: =D28-E28 -> 29378
A30: 🗂️ EXPENSE TYPE SUMMARY
A31: Expense Type | D31: Total Amount (₹)
A32: Aadi Festival | D32: {=IFERROR(INDIRECT($D$5&"!D33"),0)} -> 70852
A33: Temple Development | D33: {=IFERROR(INDIRECT($D$5&"!D34"),0)} -> 76770
A34: Temple Operations | D34: {=IFERROR(INDIRECT($D$5&"!D35"),0)} -> 0
A35: Others | D35: {=IFERROR(INDIRECT($D$5&"!D36"),0)} -> 0
A36: TOTAL | D36: =SUM(D32:D35) -> 147622
A38: 💝 DONATION TYPE SUMMARY
A39: Donation Type | D39: Pledged (₹) | E39: Received (₹) | F39: Pending (₹)
A40: Aadi Festival | D40: {=IFERROR(INDIRECT($D$5&"!D75"),0)} -> 204603 | E40: {=IFERROR(INDIRECT($D$5&"!E75"),0)} -> 149603 | F40: =D40-E40 -> 55000
A41: Temple Development | D41: {=IFERROR(INDIRECT($D$5&"!D76"),0)} -> 88500 | E41: {=IFERROR(INDIRECT($D$5&"!E76"),0)} -> 83500 | F41: =D41-E41 -> 5000
A42: Birthday Pooja | D42: {=IFERROR(INDIRECT($D$5&"!D77"),0)} -> 800 | E42: {=IFERROR(INDIRECT($D$5&"!E77"),0)} -> 800 | F42: =D42-E42 -> 0
A43: Anniversary Pooja | D43: {=IFERROR(INDIRECT($D$5&"!D78"),0)} -> 0 | E43: {=IFERROR(INDIRECT($D$5&"!E78"),0)} -> 0 | F43: =D43-E43 -> 0
A44: Pournami Pooja | D44: {=IFERROR(INDIRECT($D$5&"!D79"),0)} -> 0 | E44: {=IFERROR(INDIRECT($D$5&"!E79"),0)} -> 0 | F44: =D44-E44 -> 0
A45: Amavasai Pooja | D45: {=IFERROR(INDIRECT($D$5&"!D80"),0)} -> 0 | E45: {=IFERROR(INDIRECT($D$5&"!E80"),0)} -> 0 | F45: =D45-E45 -> 0
A46: Weekly Pooja | D46: {=IFERROR(INDIRECT($D$5&"!D81"),0)} -> 500 | E46: {=IFERROR(INDIRECT($D$5&"!E81"),0)} -> 500 | F46: =D46-E46 -> 0
A47: Others | D47: {=IFERROR(INDIRECT($D$5&"!D82"),0)} -> 13400 | E47: {=IFERROR(INDIRECT($D$5&"!E82"),0)} -> 13400 | F47: =D47-E47 -> 0
A48: TOTAL | D48: =SUM(D40:D47) -> 307803 | E48: =SUM(E40:E47) -> 247803 | F48: =D48-E48 -> 60000
A50: 🙏 DONATION PAYMENT STATUS
A51: Status | C51: Count | D51: Amount (₹) | E51: % of Total
A52: Received | C52: {=IFERROR(COUNTIF(INDIRECT($D$5&"!G87:G136"),"Received"),0)} -> 38 | D52: {=IFERROR(SUMIF(INDIRECT($D$5&"!G87:G136"),"Received",INDIRECT($D$5&"!E87:E136")),0)} -> 247803 | E52: =IFERROR(D52/INDIRECT($D$5&"!E137"),0) -> 1
A53: Pending | C53: {=IFERROR(COUNTIF(INDIRECT($D$5&"!G87:G136"),"Pending"),0)} -> 9 | D53: {=IFERROR(SUMIF(INDIRECT($D$5&"!G87:G136"),"Pending",INDIRECT($D$5&"!E87:E136")),0)} -> 0 | E53: =IFERROR(D53/INDIRECT($D$5&"!E137"),0) -> 0
A54: Partially Received | C54: {=IFERROR(COUNTIF(INDIRECT($D$5&"!G87:G136"),"Partially Received"),0)} -> 0 | D54: {=IFERROR(SUMIF(INDIRECT($D$5&"!G87:G136"),"Partially Received",INDIRECT($D$5&"!E87:E136")),0)} -> 0 | E54: =IFERROR(D54/INDIRECT($D$5&"!E137"),0) -> 0
A56: 📎 SOURCE DATA LINKS
A57: Year | B57: Source | D57: Type | E57: Link
A58: 2026 | B58: Aadi Festival 2026 | D58: Google Sheets | E58: 🔗 Open Live Sheet
A59: 2027 | B59: Aadi Festival 2027 | D59: Google Sheets | E59: 🔗 Open Live Sheet

Sheet 📈 CUMULATIVE
A1: 🕉 SRI PONNIAMMAN TEMPLE — ANNUAL ACCOUNTS SUMMARY 🕉
A2: Year-on-year financial overview across all festivals
A4: 📈 YEAR-WISE COLLECTION SUMMARY
B5: Year | C5: Festival Date | D5: Budget (₹) | E5: Pledged (₹) | F5: Received (₹) | G5: Pending (₹) | H5: Expenses (₹) | I5: Net Surplus/(Deficit) (₹)
B6: 2026 | C6: 16-Aug-2026 | D6: =IFERROR('2026'!D9,0) -> 177000 | E6: =IFERROR('2026'!D10,0) -> 307803 | F6: =IFERROR('2026'!D11,0) -> 247803 | G6: =IFERROR('2026'!D12,0) -> 60000 | H6: =IFERROR('2026'!D14,0) -> 147622 | I6: =IFERROR('2026'!D15,0) -> 29378
B7: 2027 | C7: — | D7: =IFERROR('2027'!D9,0) -> 0 | E7: =IFERROR('2027'!D10,0) -> 0 | F7: =IFERROR('2027'!D11,0) -> 0 | G7: =IFERROR('2027'!D12,0) -> 0 | H7: =IFERROR('2027'!D14,0) -> 0 | I7: =IFERROR('2027'!D15,0) -> 0
A8: CUMULATIVE TOTAL | D8: =SUM(D6:D7) -> 177000 | E8: =SUM(E6:E7) -> 307803 | F8: =SUM(F6:F7) -> 247803 | G8: =SUM(G6:G7) -> 60000 | H8: =SUM(H6:H7) -> 147622 | I8: =SUM(I6:I7) -> 29378
A10: 🗂️ EXPENSE TYPE — YEAR COMPARISON
A11: Expense Type | B11: 2026 | C11: 2027
A12: Aadi Festival | B12: =IFERROR('2026'!D33,0) -> 70852 | C12: =IFERROR('2027'!D33,0) -> 0
A13: Temple Development | B13: =IFERROR('2026'!D34,0) -> 76770 | C13: =IFERROR('2027'!D34,0) -> 0
A14: Temple Operations | B14: =IFERROR('2026'!D35,0) -> 0 | C14: =IFERROR('2027'!D35,0) -> 0
A15: Others | B15: =IFERROR('2026'!D36,0) -> 0 | C15: =IFERROR('2027'!D36,0) -> 0
A16: TOTAL | B16: =SUM(B12:B15) -> 147622 | C16: =SUM(C12:C15) -> 0

Sheet 2026
A1: 🕉 SRI PONNIAMMAN TEMPLE — ANNUAL ACCOUNTS 2026 🕉
A2: Financial Year: 2026 | Live data via Google Sheets IMPORTRANGE
A4: 🎪 FESTIVALS / EVENTS IN THIS YEAR
A5: # | B5: Festival / Event | D5: Date | E5: Notes / Description
A6: 1
A8: 📊 ANNUAL SUMMARY
A9: Annual Budget (₹) | D9: =SUM(D20:D28) -> 177000
A10: Total Donations Pledged (₹) | D10: =IFERROR(__xludf.DUMMYFUNCTION("IFERROR(INDEX(QUERY(IMPORTRANGE(""12PgU-zwv8gBrFfxvJpoPIPcxUHWup-vsxMH3HWUigZ8"",""💰 Donations!A4:D200""),""SELECT SUM(Col3) WHERE Col1 LIKE '2026/D/%' LABEL SUM(Col3) ''""),1),0)"),307803.0) -> 307803
A11: Donations Received (₹) | D11: =IFERROR(__xludf.DUMMYFUNCTION("IFERROR(INDEX(QUERY(IMPORTRANGE(""12PgU-zwv8gBrFfxvJpoPIPcxUHWup-vsxMH3HWUigZ8"",""💰 Donations!A4:D200""),""SELECT SUM(Col4) WHERE Col1 LIKE '2026/D/%' LABEL SUM(Col4) ''""),1),0)"),247803.0) -> 247803
A12: Donations Pending (₹) | D12: =D10-D11 -> 60000
A13: In-Kind Donations (₹) | D13: =IFERROR(__xludf.DUMMYFUNCTION("IFERROR(INDEX(QUERY(IMPORTRANGE(""12PgU-zwv8gBrFfxvJpoPIPcxUHWup-vsxMH3HWUigZ8"",""🌿 In-Kind!A4:E200""),""SELECT SUM(Col5) WHERE Col1 LIKE '2026/IK/%' LABEL SUM(Col5) ''""),1),0)"),8400.0) -> 8400
A14: Total Expenses (₹) | D14: =IFERROR(__xludf.DUMMYFUNCTION("IFERROR(INDEX(QUERY(IMPORTRANGE(""12PgU-zwv8gBrFfxvJpoPIPcxUHWup-vsxMH3HWUigZ8"",""💸 Expenses!A5:F200""),""SELECT SUM(Col6) WHERE Col1 LIKE '2026/EX/%' LABEL SUM(Col6) ''""),1),0)"),147622.0) -> 147622
A15: Net Surplus / (Deficit) (₹) | D15: =D9-D14 -> 29378
A16: Total Donors | D16: =IFERROR(__xludf.DUMMYFUNCTION("IFERROR(INDEX(QUERY(IMPORTRANGE(""12PgU-zwv8gBrFfxvJpoPIPcxUHWup-vsxMH3HWUigZ8"",""💰 Donations!A4:D200""),""SELECT COUNT(Col1) WHERE Col1 LIKE '2026/D/%' LABEL COUNT(Col1) ''""),1),0)"),47.0) -> 47
A18: 💰 EXPENSE CATEGORY BREAKDOWN (Budget vs Actual)
A19: # | B19: Category | C19: Group | D19: Budget (₹) | E19: Actual (₹) | F19: Balance (₹)
A20: 1 | B20: Puja & Rituals | C20: Aadi Festival | D20: =IFERROR(__xludf.DUMMYFUNCTION("IFERROR(INDEX(QUERY(IMPORTRANGE(""12PgU-zwv8gBrFfxvJpoPIPcxUHWup-vsxMH3HWUigZ8"",""💰 Budget!C5:E200""),""SELECT SUM(Col3) WHERE Col1='Puja & Rituals' LABEL SUM(Col3) ''""),1),0)"),52000.0) -> 52000 | E20: =IFERROR(__xludf.DUMMYFUNCTION("IFERROR(INDEX(QUERY(IMPORTRANGE(""12PgU-zwv8gBrFfxvJpoPIPcxUHWup-vsxMH3HWUigZ8"",""💸 Expenses!E5:F200""),""SELECT SUM(Col2) WHERE Col1='Puja & Rituals' LABEL SUM(Col2) ''""),1),0)"),16502.0) -> 16502 | F20: =D20-E20 -> 35498
A21: 2 | B21: Decorations & Flowers | C21: Aadi Festival | D21: =IFERROR(__xludf.DUMMYFUNCTION("IFERROR(INDEX(QUERY(IMPORTRANGE(""12PgU-zwv8gBrFfxvJpoPIPcxUHWup-vsxMH3HWUigZ8"",""💰 Budget!C5:E200""),""SELECT SUM(Col3) WHERE Col1='Decorations & Flowers' LABEL SUM(Col3) ''""),1),0)"),32500.0) -> 32500 | E21: =IFERROR(__xludf.DUMMYFUNCTION("IFERROR(INDEX(QUERY(IMPORTRANGE(""12PgU-zwv8gBrFfxvJpoPIPcxUHWup-vsxMH3HWUigZ8"",""💸 Expenses!E5:F200""),""SELECT SUM(Col2) WHERE Col1='Decorations & Flowers' LABEL SUM(Col2) ''""),1),0)"),7002.0) -> 7002 | F21: =D21-E21 -> 25498
A22: 3 | B22: Food & Catering | C22: Aadi Festival | D22: =IFERROR(__xludf.DUMMYFUNCTION("IFERROR(INDEX(QUERY(IMPORTRANGE(""12PgU-zwv8gBrFfxvJpoPIPcxUHWup-vsxMH3HWUigZ8"",""💰 Budget!C5:E200""),""SELECT SUM(Col3) WHERE Col1='Food & Catering' LABEL SUM(Col3) ''""),1),0)"),45000.0) -> 45000 | E22: =IFERROR(__xludf.DUMMYFUNCTION("IFERROR(INDEX(QUERY(IMPORTRANGE(""12PgU-zwv8gBrFfxvJpoPIPcxUHWup-vsxMH3HWUigZ8"",""💸 Expenses!E5:F200""),""SELECT SUM(Col2) WHERE Col1='Food & Catering' LABEL SUM(Col2) ''""),1),0)"),40000.0) -> 40000 | F22: =D22-E22 -> 5000
A23: 4 | B23: Infrastructure & Logistics | C23: Aadi Festival | D23: =IFERROR(__xludf.DUMMYFUNCTION("IFERROR(INDEX(QUERY(IMPORTRANGE(""12PgU-zwv8gBrFfxvJpoPIPcxUHWup-vsxMH3HWUigZ8"",""💰 Budget!C5:E200""),""SELECT SUM(Col3) WHERE Col1='Infrastructure & Logistics' LABEL SUM(Col3) ''""),1),0)"),28500.0) -> 28500 | E23: =IFERROR(__xludf.DUMMYFUNCTION("IFERROR(INDEX(QUERY(IMPORTRANGE(""12PgU-zwv8gBrFfxvJpoPIPcxUHWup-vsxMH3HWUigZ8"",""💸 Expenses!E5:F200""),""SELECT SUM(Col2) WHERE Col1='Infrastructure & Logistics' LABEL SUM(Col2) ''""),1),0)"),4787.0) -> 4787 | F23: =D23-E23 -> 23713
A24: 5 | B24: Miscellaneous | C24: Aadi Festival | D24: =IFERROR(__xludf.DUMMYFUNCTION("IFERROR(INDEX(QUERY(IMPORTRANGE(""12PgU-zwv8gBrFfxvJpoPIPcxUHWup-vsxMH3HWUigZ8"",""💰 Budget!C5:E200""),""SELECT SUM(Col3) WHERE Col1='Miscellaneous' LABEL SUM(Col3) ''""),1),0)"),19000.0) -> 19000 | E24: =IFERROR(__xludf.DUMMYFUNCTION("IFERROR(INDEX(QUERY(IMPORTRANGE(""12PgU-zwv8gBrFfxvJpoPIPcxUHWup-vsxMH3HWUigZ8"",""💸 Expenses!E5:F200""),""SELECT SUM(Col2) WHERE Col1='Miscellaneous' LABEL SUM(Col2) ''""),1),0)"),2961.0) -> 2961 | F24: =D24-E24 -> 16039
A25: 6 | B25: Materials | C25: Temple Development | D25: =IFERROR(__xludf.DUMMYFUNCTION("IFERROR(INDEX(QUERY(IMPORTRANGE(""12PgU-zwv8gBrFfxvJpoPIPcxUHWup-vsxMH3HWUigZ8"",""💰 Budget!C5:E200""),""SELECT SUM(Col3) WHERE Col1='Materials' LABEL SUM(Col3) ''""),1),0)"),0.0) -> 0 | E25: =IFERROR(__xludf.DUMMYFUNCTION("IFERROR(INDEX(QUERY(IMPORTRANGE(""12PgU-zwv8gBrFfxvJpoPIPcxUHWup-vsxMH3HWUigZ8"",""💸 Expenses!E5:F200""),""SELECT SUM(Col2) WHERE Col1='Materials' LABEL SUM(Col2) ''""),1),0)"),63850.0) -> 63850 | F25: =D25-E25 -> -63850
A26: 7 | B26: Labour | C26: Temple Development | D26: =IFERROR(__xludf.DUMMYFUNCTION("IFERROR(INDEX(QUERY(IMPORTRANGE(""12PgU-zwv8gBrFfxvJpoPIPcxUHWup-vsxMH3HWUigZ8"",""💰 Budget!C5:E200""),""SELECT SUM(Col3) WHERE Col1='Labour' LABEL SUM(Col3) ''""),1),0)"),0.0) -> 0 | E26: =IFERROR(__xludf.DUMMYFUNCTION("IFERROR(INDEX(QUERY(IMPORTRANGE(""12PgU-zwv8gBrFfxvJpoPIPcxUHWup-vsxMH3HWUigZ8"",""💸 Expenses!E5:F200""),""SELECT SUM(Col2) WHERE Col1='Labour' LABEL SUM(Col2) ''""),1),0)"),10000.0) -> 10000 | F26: =D26-E26 -> -10000
A27: 8 | B27: Transport | C27: Temple Development | D27: =IFERROR(__xludf.DUMMYFUNCTION("IFERROR(INDEX(QUERY(IMPORTRANGE(""12PgU-zwv8gBrFfxvJpoPIPcxUHWup-vsxMH3HWUigZ8"",""💰 Budget!C5:E200""),""SELECT SUM(Col3) WHERE Col1='Transport' LABEL SUM(Col3) ''""),1),0)"),0.0) -> 0 | E27: =IFERROR(__xludf.DUMMYFUNCTION("IFERROR(INDEX(QUERY(IMPORTRANGE(""12PgU-zwv8gBrFfxvJpoPIPcxUHWup-vsxMH3HWUigZ8"",""💸 Expenses!E5:F200""),""SELECT SUM(Col2) WHERE Col1='Transport' LABEL SUM(Col2) ''""),1),0)"),1600.0) -> 1600 | F27: =D27-E27 -> -1600
A28: 9 | B28: Food | C28: Temple Development | D28: =IFERROR(__xludf.DUMMYFUNCTION("IFERROR(INDEX(QUERY(IMPORTRANGE(""12PgU-zwv8gBrFfxvJpoPIPcxUHWup-vsxMH3HWUigZ8"",""💰 Budget!C5:E200""),""SELECT SUM(Col3) WHERE Col1='Food' LABEL SUM(Col3) ''""),1),0)"),0.0) -> 0 | E28: =IFERROR(__xludf.DUMMYFUNCTION("IFERROR(INDEX(QUERY(IMPORTRANGE(""12PgU-zwv8gBrFfxvJpoPIPcxUHWup-vsxMH3HWUigZ8"",""💸 Expenses!E5:F200""),""SELECT SUM(Col2) WHERE Col1='Food' LABEL SUM(Col2) ''""),1),0)"),920.0) -> 920 | F28: =D28-E28 -> -920
A29: TOTAL ALL CATEGORIES | D29: =SUM(D20:D28) -> 177000 | E29: =SUM(E20:E28) -> 147622 | F29: =D29-E29 -> 29378
A31: 🗂️ EXPENSE TYPE SUMMARY
A32: # | B32: Expense Type | D32: Total Amount (₹)
A33: 1 | B33: Aadi Festival | D33: =IFERROR(__xludf.DUMMYFUNCTION("IFERROR(INDEX(QUERY(IMPORTRANGE(""12PgU-zwv8gBrFfxvJpoPIPcxUHWup-vsxMH3HWUigZ8"",""💸 Expenses!F5:J200""),""SELECT SUM(Col1) WHERE Col5='Aadi Festival' LABEL SUM(Col1) ''""),1),0)"),70852.0) -> 70852
A34: 2 | B34: Temple Development | D34: =IFERROR(__xludf.DUMMYFUNCTION("IFERROR(INDEX(QUERY(IMPORTRANGE(""12PgU-zwv8gBrFfxvJpoPIPcxUHWup-vsxMH3HWUigZ8"",""💸 Expenses!F5:J200""),""SELECT SUM(Col1) WHERE Col5='Temple Development' LABEL SUM(Col1) ''""),1),0)"),76770.0) -> 76770
A35: 3 | B35: Temple Operations | D35: =IFERROR(__xludf.DUMMYFUNCTION("IFERROR(INDEX(QUERY(IMPORTRANGE(""12PgU-zwv8gBrFfxvJpoPIPcxUHWup-vsxMH3HWUigZ8"",""💸 Expenses!F5:J200""),""SELECT SUM(Col1) WHERE Col5='Temple Operations' LABEL SUM(Col1) ''""),1),0)"),0.0) -> 0
A36: 4 | B36: Others | D36: =IFERROR(__xludf.DUMMYFUNCTION("IFERROR(INDEX(QUERY(IMPORTRANGE(""12PgU-zwv8gBrFfxvJpoPIPcxUHWup-vsxMH3HWUigZ8"",""💸 Expenses!F5:J200""),""SELECT SUM(Col1) WHERE Col5='Others' LABEL SUM(Col1) ''""),1),0)"),0.0) -> 0
A37: TOTAL | D37: =SUM(D33:D36) -> 147622
A39: 💸 EXPENSE LOG
A40: # | B40: Date | C40: Vendor / Payee | D40: Description | E40: Category | F40: Amount (₹) | G40: Mode | H40: Paid By | I40: Remarks | J40: Type
A41: =IFERROR(__xludf.DUMMYFUNCTION("IFERROR(INDEX(IMPORTRANGE(""12PgU-zwv8gBrFfxvJpoPIPcxUHWup-vsxMH3HWUigZ8"",""💸 Expenses!A5:J200""),1,1),"""")"),"2026/EX/1") -> 2026/EX/1 | B41: =IFERROR(__xludf.DUMMYFUNCTION("IFERROR(IF(INDEX(IMPORTRANGE(""12PgU-zwv8gBrFfxvJpoPIPcxUHWup-vsxMH3HWUigZ8"",""💸 Expenses!A5:J200""),1,2)="""","""",TEXT(INDEX(IMPORTRANGE(""12PgU-zwv8gBrFfxvJpoPIPcxUHWup-vsxMH3HWUigZ8"",""💸 Expenses!A5:J200""),1,2),""DD-MM-YYYY"")),"""")"),"25-05-26") -> 25-05-26 | C41: =IFERROR(__xludf.DUMMYFUNCTION("IFERROR(INDEX(IMPORTRANGE(""12PgU-zwv8gBrFfxvJpoPIPcxUHWup-vsxMH3HWUigZ8"",""💸 Expenses!A5:J200""),1,3),"""")"),"Thimiri Press") -> Thimiri Press | D41: =IFERROR(__xludf.DUMMYFUNCTION("IFERROR(INDEX(IMPORTRANGE(""12PgU-zwv8gBrFfxvJpoPIPcxUHWup-vsxMH3HWUigZ8"",""💸 Expenses!A5:J200""),1,4),"""")"),"Card Printing") -> Card Printing | E41: =IFERROR(__xludf.DUMMYFUNCTION("IFERROR(INDEX(IMPORTRANGE(""12PgU-zwv8gBrFfxvJpoPIPcxUHWup-vsxMH3HWUigZ8"",""💸 Expenses!A5:J200""),1,5),"""")"),"Miscellaneous") -> Miscellaneous | F41: =IFERROR(__xludf.DUMMYFUNCTION("IFERROR(IFERROR(INDEX(IMPORTRANGE(""12PgU-zwv8gBrFfxvJpoPIPcxUHWup-vsxMH3HWUigZ8"",""💸 Expenses!A5:J200""),1,6)*1,0),0)"),500.0) -> 500 | G41: =IFERROR(__xludf.DUMMYFUNCTION("IFERROR(INDEX(IMPORTRANGE(""12PgU-zwv8gBrFfxvJpoPIPcxUHWup-vsxMH3HWUigZ8"",""💸 Expenses!A5:J200""),1,7),"""")"),"UPI") -> UPI | H41: =IFERROR(__xludf.DUMMYFUNCTION("IFERROR(INDEX(IMPORTRANGE(""12PgU-zwv8gBrFfxvJpoPIPcxUHWup-vsxMH3HWUigZ8"",""💸 Expenses!A5:J200""),1,8),"""")"),"Sunil Kumar") -> Sunil Kumar | I41: =IFERROR(__xludf.DUMMYFUNCTION("IFERROR(INDEX(IMPORTRANGE(""12PgU-zwv8gBrFfxvJpoPIPcxUHWup-vsxMH3HWUigZ8"",""💸 Expenses!A5:J200""),1,9),"""")"),"") | J41: =IFERROR(__xludf.DUMMYFUNCTION("IFERROR(INDEX(IMPORTRANGE(""12PgU-zwv8gBrFfxvJpoPIPcxUHWup-vsxMH3HWUigZ8"",""💸 Expenses!A5:J200""),1,10),"""")"),"Aadi Festival") -> Aadi Festival
A42: =IFERROR(__xludf.DUMMYFUNCTION("IFERROR(INDEX(IMPORTRANGE(""12PgU-zwv8gBrFfxvJpoPIPcxUHWup-vsxMH3HWUigZ8"",""💸 Expenses!A5:J200""),2,1),"""")"),"2026/EX/2") -> 2026/EX/2 | B42: =IFERROR(__xludf.DUMMYFUNCTION("IFERROR(IF(INDEX(IMPORTRANGE(""12PgU-zwv8gBrFfxvJpoPIPcxUHWup-vsxMH3HWUigZ8"",""💸 Expenses!A5:J200""),2,2)="""","""",TEXT(INDEX(IMPORTRANGE(""12PgU-zwv8gBrFfxvJpoPIPcxUHWup-vsxMH3HWUigZ8"",""💸 Expenses!A5:J200""),2,2),""DD-MM-YYYY"")),"""")"),"25-05-26") -> 25-05-26 | C42: =IFERROR(__xludf.DUMMYFUNCTION("IFERROR(INDEX(IMPORTRANGE(""12PgU-zwv8gBrFfxvJpoPIPcxUHWup-vsxMH3HWUigZ8"",""💸 Expenses!A5:J200""),2,3),"""")"),"Vadivelu / Saravana") -> Vadivelu / Saravana | D42: =IFERROR(__xludf.DUMMYFUNCTION("IFERROR(INDEX(IMPORTRANGE(""12PgU-zwv8gBrFfxvJpoPIPcxUHWup-vsxMH3HWUigZ8"",""💸 Expenses!A5:J200""),2,4),"""")"),"Iyer Booking") -> Iyer Booking | E42: =IFERROR(__xludf.DUMMYFUNCTION("IFERROR(INDEX(IMPORTRANGE(""12PgU-zwv8gBrFfxvJpoPIPcxUHWup-vsxMH3HWUigZ8"",""💸 Expenses!A5:J200""),2,5),"""")"),"Puja & Rituals") -> Puja & Rituals | F42: =IFERROR(__xludf.DUMMYFUNCTION("IFERROR(IFERROR(INDEX(IMPORTRANGE(""12PgU-zwv8gBrFfxvJpoPIPcxUHWup-vsxMH3HWUigZ8"",""💸 Expenses!A5:J200""),2,6)*1,0),0)"),5000.0) -> 5000 | G42: =IFERROR(__xludf.DUMMYFUNCTION("IFERROR(INDEX(IMPORTRANGE(""12PgU-zwv8gBrFfxvJpoPIPcxUHWup-vsxMH3HWUigZ8"",""💸 Expenses!A5:J200""),2,7),"""")"),"UPI") -> UPI | H42: =IFERROR(__xludf.DUMMYFUNCTION("IFERROR(INDEX(IMPORTRANGE(""12PgU-zwv8gBrFfxvJpoPIPcxUHWup-vsxMH3HWUigZ8"",""💸 Expenses!A5:J200""),2,8),"""")"),"Sunil Kumar") -> Sunil Kumar | I42: =IFERROR(__xludf.DUMMYFUNCTION("IFERROR(INDEX(IMPORTRANGE(""12PgU-zwv8gBrFfxvJpoPIPcxUHWup-vsxMH3HWUigZ8"",""💸 Expenses!A5:J200""),2,9),"""")"),"") | J42: =IFERROR(__xludf.DUMMYFUNCTION("IFERROR(INDEX(IMPORTRANGE(""12PgU-zwv8gBrFfxvJpoPIPcxUHWup-vsxMH3HWUigZ8"",""💸 Expenses!A5:J200""),2,10),"""")"),"Aadi Festival") -> Aadi Festival
A43: =IFERROR(__xludf.DUMMYFUNCTION("IFERROR(INDEX(IMPORTRANGE(""12PgU-zwv8gBrFfxvJpoPIPcxUHWup-vsxMH3HWUigZ8"",""💸 Expenses!A5:J200""),3,1),"""")"),"2026/EX/3") -> 2026/EX/3 | B43: =IFERROR(__xludf.DUMMYFUNCTION("IFERROR(IF(INDEX(IMPORTRANGE(""12PgU-zwv8gBrFfxvJpoPIPcxUHWup-vsxMH3HWUigZ8"",""💸 Expenses!A5:J200""),3,2)="""","""",TEXT(INDEX(IMPORTRANGE(""12PgU-zwv8gBrFfxvJpoPIPcxUHWup-vsxMH3HWUigZ8"",""💸 Expenses!A5:J200""),3,2),""DD-MM-YYYY"")),"""")"),"26-05-26") -> 26-05-26 | C43: =IFERROR(__xludf.DUMMYFUNCTION("IFERROR(INDEX(IMPORTRANGE(""12PgU-zwv8gBrFfxvJpoPIPcxUHWup-vsxMH3HWUigZ8"",""💸 Expenses!A5:J200""),3,3),"""")"),"Sathish B") -> Sathish B | D43: =IFERROR(__xludf.DUMMYFUNCTION("IFERROR(INDEX(IMPORTRANGE(""12PgU-zwv8gBrFfxvJpoPIPcxUHWup-vsxMH3HWUigZ8"",""💸 Expenses!A5:J200""),3,4),"""")"),"Vessels & Utensils") -> Vessels & Utensils | E43: =IFERROR(__xludf.DUMMYFUNCTION("IFERROR(INDEX(IMPORTRANGE(""12PgU-zwv8gBrFfxvJpoPIPcxUHWup-vsxMH3HWUigZ8"",""💸 Expenses!A5:J200""),3,5),"""")"),"Infrastructure & Logistics") -> Infrastructure & Logistics | F43: =IFERROR(__xludf.DUMMYFUNCTION("IFERROR(IFERROR(INDEX(IMPORTRANGE(""12PgU-zwv8gBrFfxvJpoPIPcxUHWup-vsxMH3HWUigZ8"",""💸 Expenses!A5:J200""),3,6)*1,0),0)"),2001.0) -> 2001 | G43: =IFERROR(__xludf.DUMMYFUNCTION("IFERROR(INDEX(IMPORTRANGE(""12PgU-zwv8gBrFfxvJpoPIPcxUHWup-vsxMH3HWUigZ8"",""💸 Expenses!A5:J200""),3,7),"""")"),"UPI") -> UPI | H43: =IFERROR(__xludf.DUMMYFUNCTION("IFERROR(INDEX(IMPORTRANGE(""12PgU-zwv8gBrFfxvJpoPIPcxUHWup-vsxMH3HWUigZ8"",""💸 Expenses!A5:J200""),3,8),"""")"),"Sunil Kumar") -> Sunil Kumar | I43: =IFERROR(__xludf.DUMMYFUNCTION("IFERROR(INDEX(IMPORTRANGE(""12PgU-zwv8gBrFfxvJpoPIPcxUHWup-vsxMH3HWUigZ8"",""💸 Expenses!A5:J200""),3,9),"""")"),"") | J43: =IFERROR(__xludf.DUMMYFUNCTION("IFERROR(INDEX(IMPORTRANGE(""12PgU-zwv8gBrFfxvJpoPIPcxUHWup-vsxMH3HWUigZ8"",""💸 Expenses!A5:J200""),3,10),"""")"),"Aadi Festival") -> Aadi Festival
A44: =IFERROR(__xludf.DUMMYFUNCTION("IFERROR(INDEX(IMPORTRANGE(""12PgU-zwv8gBrFfxvJpoPIPcxUHWup-vsxMH3HWUigZ8"",""💸 Expenses!A5:J200""),4,1),"""")"),"2026/EX/4") -> 2026/EX/4 | B44: =IFERROR(__xludf.DUMMYFUNCTION("IFERROR(IF(INDEX(IMPORTRANGE(""12PgU-zwv8gBrFfxvJpoPIPcxUHWup-vsxMH3HWUigZ8"",""💸 Expenses!A5:J200""),4,2)="""","""",TEXT(INDEX(IMPORTRANGE(""12PgU-zwv8gBrFfxvJpoPIPcxUHWup-vsxMH3HWUigZ8"",""💸 Expenses!A5:J200""),4,2),""DD-MM-YYYY"")),"""")"),"26-05-26") -> 26-05-26 | C44: =IFERROR(__xludf.DUMMYFUNCTION("IFERROR(INDEX(IMPORTRANGE(""12PgU-zwv8gBrFfxvJpoPIPcxUHWup-vsxMH3HWUigZ8"",""💸 Expenses!A5:J200""),4,3),"""")"),"Karthik") -> Karthik | D44: =IFERROR(__xludf.DUMMYFUNCTION("IFERROR(INDEX(IMPORTRANGE(""12PgU-zwv8gBrFfxvJpoPIPcxUHWup-vsxMH3HWUigZ8"",""💸 Expenses!A5:J200""),4,4),"""")"),"Electrical Lighting & Generator Mic & Sound system") -> Electrical Lighting & Generator Mic & Sound system | E44: =IFERROR(__xludf.DUMMYFUNCTION("IFERROR(INDEX(IMPORTRANGE(""12PgU-zwv8gBrFfxvJpoPIPcxUHWup-vsxMH3HWUigZ8"",""💸 Expenses!A5:J200""),4,5),"""")"),"Infrastructure & Logistics") -> Infrastructure & Logistics | F44: =IFERROR(__xludf.DUMMYFUNCTION("IFERROR(IFERROR(INDEX(IMPORTRANGE(""12PgU-zwv8gBrFfxvJpoPIPcxUHWup-vsxMH3HWUigZ8"",""💸 Expenses!A5:J200""),4,6)*1,0),0)"),2001.0) -> 2001 | G44: =IFERROR(__xludf.DUMMYFUNCTION("IFERROR(INDEX(IMPORTRANGE(""12PgU-zwv8gBrFfxvJpoPIPcxUHWup-vsxMH3HWUigZ8"",""💸 Expenses!A5:J200""),4,7),"""")"),"UPI") -> UPI | H44: =IFERROR(__xludf.DUMMYFUNCTION("IFERROR(INDEX(IMPORTRANGE(""12PgU-zwv8gBrFfxvJpoPIPcxUHWup-vsxMH3HWUigZ8"",""💸 Expenses!A5:J200""),4,8),"""")"),"Sunil Kumar") -> Sunil Kumar | I44: =IFERROR(__xludf.DUMMYFUNCTION("IFERROR(INDEX(IMPORTRANGE(""12PgU-zwv8gBrFfxvJpoPIPcxUHWup-vsxMH3HWUigZ8"",""💸 Expenses!A5:J200""),4,9),"""")"),"") | J44: =IFERROR(__xludf.DUMMYFUNCTION("IFERROR(INDEX(IMPORTRANGE(""12PgU-zwv8gBrFfxvJpoPIPcxUHWup-vsxMH3HWUigZ8"",""💸 Expenses!A5:J200""),4,10),"""")"),"Aadi Festival") -> Aadi Festival
A45: =IFERROR(__xludf.DUMMYFUNCTION("IFERROR(INDEX(IMPORTRANGE(""12PgU-zwv8gBrFfxvJpoPIPcxUHWup-vsxMH3HWUigZ8"",""💸 Expenses!A5:J200""),5,1),"""")"),"2026/EX/5") -> 2026/EX/5 | B45: =IFERROR(__xludf.DUMMYFUNCTION("IFERROR(IF(INDEX(IMPORTRANGE(""12PgU-zwv8gBrFfxvJpoPIPcxUHWup-vsxMH3HWUigZ8"",""💸 Expenses!A5:J200""),5,2)="""","""",TEXT(INDEX(IMPORTRANGE(""12PgU-zwv8gBrFfxvJpoPIPcxUHWup-vsxMH3HWUigZ8"",""💸 Expenses!A5:J200""),5,2),""DD-MM-YYYY"")),"""")"),"26-05-26") -> 26-05-26 | C45: =IFERROR(__xludf.DUMMYFUNCTION("IFERROR(INDEX(IMPORTRANGE(""12PgU-zwv8gBrFfxvJpoPIPcxUHWup-vsxMH3HWUigZ8"",""💸 Expenses!A5:J200""),5,3),"""")"),"Elagovan") -> Elagovan | D45: =IFERROR(__xludf.DUMMYFUNCTION("IFERROR(INDEX(IMPORTRANGE(""12PgU-zwv8gBrFfxvJpoPIPcxUHWup-vsxMH3HWUigZ8"",""💸 Expenses!A5:J200""),5,4),"""")"),"Flowers & Flower decoration for Chariot") -> Flowers & Flower decoration for Chariot | E45: =IFERROR(__xludf.DUMMYFUNCTION("IFERROR(INDEX(IMPORTRANGE(""12PgU-zwv8gBrFfxvJpoPIPcxUHWup-vsxMH3HWUigZ8"",""💸 Expenses!A5:J200""),5,5),"""")"),"Decorations & Flowers") -> Decorations & Flowers | F45: =IFERROR(__xludf.DUMMYFUNCTION("IFERROR(IFERROR(INDEX(IMPORTRANGE(""12PgU-zwv8gBrFfxvJpoPIPcxUHWup-vsxMH3HWUigZ8"",""💸 Expenses!A5:J200""),5,6)*1,0),0)"),5001.0) -> 5001 | G45: =IFERROR(__xludf.DUMMYFUNCTION("IFERROR(INDEX(IMPORTRANGE(""12PgU-zwv8gBrFfxvJpoPIPcxUHWup-vsxMH3HWUigZ8"",""💸 Expenses!A5:J200""),5,7),"""")"),"UPI") -> UPI | H45: =IFERROR(__xludf.DUMMYFUNCTION("IFERROR(INDEX(IMPORTRANGE(""12PgU-zwv8gBrFfxvJpoPIPcxUHWup-vsxMH3HWUigZ8"",""💸 Expenses!A5:J200""),5,8),"""")"),"Sunil Kumar") -> Sunil Kumar | I45: =IFERROR(__xludf.DUMMYFUNCTION("IFERROR(INDEX(IMPORTRANGE(""12PgU-zwv8gBrFfxvJpoPIPcxUHWup-vsxMH3HWUigZ8"",""💸 Expenses!A5:J200""),5,9),"""")"),"") | J45: =IFERROR(__xludf.DUMMYFUNCTION("IFERROR(INDEX(IMPORTRANGE(""12PgU-zwv8gBrFfxvJpoPIPcxUHWup-vsxMH3HWUigZ8"",""💸 Expenses!A5:J200""),5,10),"""")"),"Aadi Festival") -> Aadi Festival
A46: =IFERROR(__xludf.DUMMYFUNCTION("IFERROR(INDEX(IMPORTRANGE(""12PgU-zwv8gBrFfxvJpoPIPcxUHWup-vsxMH3HWUigZ8"",""💸 Expenses!A5:J200""),6,1),"""")"),"2026/EX/6") -> 2026/EX/6 | B46: =IFERROR(__xludf.DUMMYFUNCTION("IFERROR(IF(INDEX(IMPORTRANGE(""12PgU-zwv8gBrFfxvJpoPIPcxUHWup-vsxMH3HWUigZ8"",""💸 Expenses!A5:J200""),6,2)="""","""",TEXT(INDEX(IMPORTRANGE(""12PgU-zwv8gBrFfxvJpoPIPcxUHWup-vsxMH3HWUigZ8"",""💸 Expenses!A5:J200""),6,2),""DD-MM-YYYY"")),"""")"),"26-05-26") -> 26-05-26 | C46: =IFERROR(__xludf.DUMMYFUNCTION("IFERROR(INDEX(IMPORTRANGE(""12PgU-zwv8gBrFfxvJpoPIPcxUHWup-vsxMH3HWUigZ8"",""💸 Expenses!A5:J200""),6,3),"""")"),"Suresh") -> Suresh | D46: =IFERROR(__xludf.DUMMYFUNCTION("IFERROR(INDEX(IMPORTRANGE(""12PgU-zwv8gBrFfxvJpoPIPcxUHWup-vsxMH3HWUigZ8"",""💸 Expenses!A5:J200""),6,4),"""")")," Decoration of Ponniamman & tempo charges for Procession") -> Decoration of Ponniamman & tempo charges for Procession | E46: =IFERROR(__xludf.DUMMYFUNCTION("IFERROR(INDEX(IMPORTRANGE(""12PgU-zwv8gBrFfxvJpoPIPcxUHWup-vsxMH3HWUigZ8"",""💸 Expenses!A5:J200""),6,5),"""")"),"Decorations & Flowers") -> Decorations & Flowers | F46: =IFERROR(__xludf.DUMMYFUNCTION("IFERROR(IFERROR(INDEX(IMPORTRANGE(""12PgU-zwv8gBrFfxvJpoPIPcxUHWup-vsxMH3HWUigZ8"",""💸 Expenses!A5:J200""),6,6)*1,0),0)"),2001.0) -> 2001 | G46: =IFERROR(__xludf.DUMMYFUNCTION("IFERROR(INDEX(IMPORTRANGE(""12PgU-zwv8gBrFfxvJpoPIPcxUHWup-vsxMH3HWUigZ8"",""💸 Expenses!A5:J200""),6,7),"""")"),"UPI") -> UPI | H46: =IFERROR(__xludf.DUMMYFUNCTION("IFERROR(INDEX(IMPORTRANGE(""12PgU-zwv8gBrFfxvJpoPIPcxUHWup-vsxMH3HWUigZ8"",""💸 Expenses!A5:J200""),6,8),"""")"),"Sunil Kumar") -> Sunil Kumar | I46: =IFERROR(__xludf.DUMMYFUNCTION("IFERROR(INDEX(IMPORTRANGE(""12PgU-zwv8gBrFfxvJpoPIPcxUHWup-vsxMH3HWUigZ8"",""💸 Expenses!A5:J200""),6,9),"""")"),"") | J46: =IFERROR(__xludf.DUMMYFUNCTION("IFERROR(INDEX(IMPORTRANGE(""12PgU-zwv8gBrFfxvJpoPIPcxUHWup-vsxMH3HWUigZ8"",""💸 Expenses!A5:J200""),6,10),"""")"),"Aadi Festival") -> Aadi Festival
A47: =IFERROR(__xludf.DUMMYFUNCTION("IFERROR(INDEX(IMPORTRANGE(""12PgU-zwv8gBrFfxvJpoPIPcxUHWup-vsxMH3HWUigZ8"",""💸 Expenses!A5:J200""),7,1),"""")"),"2026/EX/7") -> 2026/EX/7 | B47: =IFERROR(__xludf.DUMMYFUNCTION("IFERROR(IF(INDEX(IMPORTRANGE(""12PgU-zwv8gBrFfxvJpoPIPcxUHWup-vsxMH3HWUigZ8"",""💸 Expenses!A5:J200""),7,2)="""","""",TEXT(INDEX(IMPORTRANGE(""12PgU-zwv8gBrFfxvJpoPIPcxUHWup-vsxMH3HWUigZ8"",""💸 Expenses!A5:J200""),7,2),""DD-MM-YYYY"")),"""")"),"30-05-2026") -> 30-05-2026 | C47: =IFERROR(__xludf.DUMMYFUNCTION("IFERROR(INDEX(IMPORTRANGE(""12PgU-zwv8gBrFfxvJpoPIPcxUHWup-vsxMH3HWUigZ8"",""💸 Expenses!A5:J200""),7,3),"""")"),"Chennai Studios") -> Chennai Studios | D47: =IFERROR(__xludf.DUMMYFUNCTION("IFERROR(INDEX(IMPORTRANGE(""12PgU-zwv8gBrFfxvJpoPIPcxUHWup-vsxMH3HWUigZ8"",""💸 Expenses!A5:J200""),7,4),"""")"),"Photography Booking") -> Photography Booking | E47: =IFERROR(__xludf.DUMMYFUNCTION("IFERROR(INDEX(IMPORTRANGE(""12PgU-zwv8gBrFfxvJpoPIPcxUHWup-vsxMH3HWUigZ8"",""💸 Expenses!A5:J200""),7,5),"""")"),"Miscellaneous") -> Miscellaneous | F47: =IFERROR(__xludf.DUMMYFUNCTION("IFERROR(IFERROR(INDEX(IMPORTRANGE(""12PgU-zwv8gBrFfxvJpoPIPcxUHWup-vsxMH3HWUigZ8"",""💸 Expenses!A5:J200""),7,6)*1,0),0)"),1001.0) -> 1001 | G47: =IFERROR(__xludf.DUMMYFUNCTION("IFERROR(INDEX(IMPORTRANGE(""12PgU-zwv8gBrFfxvJpoPIPcxUHWup-vsxMH3HWUigZ8"",""💸 Expenses!A5:J200""),7,7),"""")"),"UPI") -> UPI | H47: =IFERROR(__xludf.DUMMYFUNCTION("IFERROR(INDEX(IMPORTRANGE(""12PgU-zwv8gBrFfxvJpoPIPcxUHWup-vsxMH3HWUigZ8"",""💸 Expenses!A5:J200""),7,8),"""")"),"Sunil Kumar") -> Sunil Kumar | I47: =IFERROR(__xludf.DUMMYFUNCTION("IFERROR(INDEX(IMPORTRANGE(""12PgU-zwv8gBrFfxvJpoPIPcxUHWup-vsxMH3HWUigZ8"",""💸 Expenses!A5:J200""),7,9),"""")"),"") | J47: =IFERROR(__xludf.DUMMYFUNCTION("IFERROR(INDEX(IMPORTRANGE(""12PgU-zwv8gBrFfxvJpoPIPcxUHWup-vsxMH3HWUigZ8"",""💸 Expenses!A5:J200""),7,10),"""")"),"Aadi Festival") -> Aadi Festival
A48: =IFERROR(__xludf.DUMMYFUNCTION("IFERROR(INDEX(IMPORTRANGE(""12PgU-zwv8gBrFfxvJpoPIPcxUHWup-vsxMH3HWUigZ8"",""💸 Expenses!A5:J200""),8,1),"""")"),"2026/EX/8") -> 2026/EX/8 | B48: =IFERROR(__xludf.DUMMYFUNCTION("IFERROR(IF(INDEX(IMPORTRANGE(""12PgU-zwv8gBrFfxvJpoPIPcxUHWup-vsxMH3HWUigZ8"",""💸 Expenses!A5:J200""),8,2)="""","""",TEXT(INDEX(IMPORTRANGE(""12PgU-zwv8gBrFfxvJpoPIPcxUHWup-vsxMH3HWUigZ8"",""💸 Expenses!A5:J200""),8,2),""DD-MM-YYYY"")),"""")"),"30-05-2026") -> 30-05-2026 | C48: =IFERROR(__xludf.DUMMYFUNCTION("IFERROR(INDEX(IMPORTRANGE(""12PgU-zwv8gBrFfxvJpoPIPcxUHWup-vsxMH3HWUigZ8"",""💸 Expenses!A5:J200""),8,3),"""")"),"Narasimhan") -> Narasimhan | D48: =IFERROR(__xludf.DUMMYFUNCTION("IFERROR(INDEX(IMPORTRANGE(""12PgU-zwv8gBrFfxvJpoPIPcxUHWup-vsxMH3HWUigZ8"",""💸 Expenses!A5:J200""),8,4),"""")"),"Nadeswaram Booking") -> Nadeswaram Booking | E48: =IFERROR(__xludf.DUMMYFUNCTION("IFERROR(INDEX(IMPORTRANGE(""12PgU-zwv8gBrFfxvJpoPIPcxUHWup-vsxMH3HWUigZ8"",""💸 Expenses!A5:J200""),8,5),"""")"),"Puja & Rituals") -> Puja & Rituals | F48: =IFERROR(__xludf.DUMMYFUNCTION("IFERROR(IFERROR(INDEX(IMPORTRANGE(""12PgU-zwv8gBrFfxvJpoPIPcxUHWup-vsxMH3HWUigZ8"",""💸 Expenses!A5:J200""),8,6)*1,0),0)"),1001.0) -> 1001 | G48: =IFERROR(__xludf.DUMMYFUNCTION("IFERROR(INDEX(IMPORTRANGE(""12PgU-zwv8gBrFfxvJpoPIPcxUHWup-vsxMH3HWUigZ8"",""💸 Expenses!A5:J200""),8,7),"""")"),"UPI") -> UPI | H48: =IFERROR(__xludf.DUMMYFUNCTION("IFERROR(INDEX(IMPORTRANGE(""12PgU-zwv8gBrFfxvJpoPIPcxUHWup-vsxMH3HWUigZ8"",""💸 Expenses!A5:J200""),8,8),"""")"),"Sunil Kumar") -> Sunil Kumar | I48: =IFERROR(__xludf.DUMMYFUNCTION("IFERROR(INDEX(IMPORTRANGE(""12PgU-zwv8gBrFfxvJpoPIPcxUHWup-vsxMH3HWUigZ8"",""💸 Expenses!A5:J200""),8,9),"""")"),"") | J48: =IFERROR(__xludf.DUMMYFUNCTION("IFERROR(INDEX(IMPORTRANGE(""12PgU-zwv8gBrFfxvJpoPIPcxUHWup-vsxMH3HWUigZ8"",""💸 Expenses!A5:J200""),8,10),"""")"),"Aadi Festival") -> Aadi Festival
A49: =IFERROR(__xludf.DUMMYFUNCTION("IFERROR(INDEX(IMPORTRANGE(""12PgU-zwv8gBrFfxvJpoPIPcxUHWup-vsxMH3HWUigZ8"",""💸 Expenses!A5:J200""),9,1),"""")"),"2026/EX/9") -> 2026/EX/9 | B49: =IFERROR(__xludf.DUMMYFUNCTION("IFERROR(IF(INDEX(IMPORTRANGE(""12PgU-zwv8gBrFfxvJpoPIPcxUHWup-vsxMH3HWUigZ8"",""💸 Expenses!A5:J200""),9,2)="""","""",TEXT(INDEX(IMPORTRANGE(""12PgU-zwv8gBrFfxvJpoPIPcxUHWup-vsxMH3HWUigZ8"",""💸 Expenses!A5:J200""),9,2),""DD-MM-YYYY"")),"""")"),"30-05-2026") -> 30-05-2026 | C49: =IFERROR(__xludf.DUMMYFUNCTION("IFERROR(INDEX(IMPORTRANGE(""12PgU-zwv8gBrFfxvJpoPIPcxUHWup-vsxMH3HWUigZ8"",""💸 Expenses!A5:J200""),9,3),"""")"),"Pradhap") -> Pradhap | D49: =IFERROR(__xludf.DUMMYFUNCTION("IFERROR(INDEX(IMPORTRANGE(""12PgU-zwv8gBrFfxvJpoPIPcxUHWup-vsxMH3HWUigZ8"",""💸 Expenses!A5:J200""),9,4),"""")"),"Tamte Booking") -> Tamte Booking | E49: =IFERROR(__xludf.DUMMYFUNCTION("IFERROR(INDEX(IMPORTRANGE(""12PgU-zwv8gBrFfxvJpoPIPcxUHWup-vsxMH3HWUigZ8"",""💸 Expenses!A5:J200""),9,5),"""")"),"Puja & Rituals") -> Puja & Rituals | F49: =IFERROR(__xludf.DUMMYFUNCTION("IFERROR(IFERROR(INDEX(IMPORTRANGE(""12PgU-zwv8gBrFfxvJpoPIPcxUHWup-vsxMH3HWUigZ8"",""💸 Expenses!A5:J200""),9,6)*1,0),0)"),1001.0) -> 1001 | G49: =IFERROR(__xludf.DUMMYFUNCTION("IFERROR(INDEX(IMPORTRANGE(""12PgU-zwv8gBrFfxvJpoPIPcxUHWup-vsxMH3HWUigZ8"",""💸 Expenses!A5:J200""),9,7),"""")"),"UPI") -> UPI | H49: =IFERROR(__xludf.DUMMYFUNCTION("IFERROR(INDEX(IMPORTRANGE(""12PgU-zwv8gBrFfxvJpoPIPcxUHWup-vsxMH3HWUigZ8"",""💸 Expenses!A5:J200""),9,8),"""")"),"Sunil Kumar") -> Sunil Kumar | I49: =IFERROR(__xludf.DUMMYFUNCTION("IFERROR(INDEX(IMPORTRANGE(""12PgU-zwv8gBrFfxvJpoPIPcxUHWup-vsxMH3HWUigZ8"",""💸 Expenses!A5:J200""),9,9),"""")"),"") | J49: =IFERROR(__xludf.DUMMYFUNCTION("IFERROR(INDEX(IMPORTRANGE(""12PgU-zwv8gBrFfxvJpoPIPcxUHWup-vsxMH3HWUigZ8"",""💸 Expenses!A5:J200""),9,10),"""")"),"Aadi Festival") -> Aadi Festival
A50: =IFERROR(__xludf.DUMMYFUNCTION("IFERROR(INDEX(IMPORTRANGE(""12PgU-zwv8gBrFfxvJpoPIPcxUHWup-vsxMH3HWUigZ8"",""💸 Expenses!A5:J200""),10,1),"""")"),"2026/EX/10") -> 2026/EX/10 | B50: =IFERROR(__xludf.DUMMYFUNCTION("IFERROR(IF(INDEX(IMPORTRANGE(""12PgU-zwv8gBrFfxvJpoPIPcxUHWup-vsxMH3HWUigZ8"",""💸 Expenses!A5:J200""),10,2)="""","""",TEXT(INDEX(IMPORTRANGE(""12PgU-zwv8gBrFfxvJpoPIPcxUHWup-vsxMH3HWUigZ8"",""💸 Expenses!A5:J200""),10,2),""DD-MM-YYYY"")),"""")"),"30-05-2026") -> 30-05-2026 | C50: =IFERROR(__xludf.DUMMYFUNCTION("IFERROR(INDEX(IMPORTRANGE(""12PgU-zwv8gBrFfxvJpoPIPcxUHWup-vsxMH3HWUigZ8"",""💸 Expenses!A5:J200""),10,3),"""")"),"Damodharan") -> Damodharan | D50: =IFERROR(__xludf.DUMMYFUNCTION("IFERROR(INDEX(IMPORTRANGE(""12PgU-zwv8gBrFfxvJpoPIPcxUHWup-vsxMH3HWUigZ8"",""💸 Expenses!A5:J200""),10,4),"""")"),"Invitation balance") -> Invitation balance | E50: =IFERROR(__xludf.DUMMYFUNCTION("IFERROR(INDEX(IMPORTRANGE(""12PgU-zwv8gBrFfxvJpoPIPcxUHWup-vsxMH3HWUigZ8"",""💸 Expenses!A5:J200""),10,5),"""")"),"Miscellaneous") -> Miscellaneous | F50: =IFERROR(__xludf.DUMMYFUNCTION("IFERROR(IFERROR(INDEX(IMPORTRANGE(""12PgU-zwv8gBrFfxvJpoPIPcxUHWup-vsxMH3HWUigZ8"",""💸 Expenses!A5:J200""),10,6)*1,0),0)"),1000.0) -> 1000 | G50: =IFERROR(__xludf.DUMMYFUNCTION("IFERROR(INDEX(IMPORTRANGE(""12PgU-zwv8gBrFfxvJpoPIPcxUHWup-vsxMH3HWUigZ8"",""💸 Expenses!A5:J200""),10,7),"""")"),"UPI") -> UPI | H50: =IFERROR(__xludf.DUMMYFUNCTION("IFERROR(INDEX(IMPORTRANGE(""12PgU-zwv8gBrFfxvJpoPIPcxUHWup-vsxMH3HWUigZ8"",""💸 Expenses!A5:J200""),10,8),"""")"),"Sunil Kumar") -> Sunil Kumar | I50: =IFERROR(__xludf.DUMMYFUNCTION("IFERROR(INDEX(IMPORTRANGE(""12PgU-zwv8gBrFfxvJpoPIPcxUHWup-vsxMH3HWUigZ8"",""💸 Expenses!A5:J200""),10,9),"""")"),"") | J50: =IFERROR(__xludf.DUMMYFUNCTION("IFERROR(INDEX(IMPORTRANGE(""12PgU-zwv8gBrFfxvJpoPIPcxUHWup-vsxMH3HWUigZ8"",""💸 Expenses!A5:J200""),10,10),"""")"),"Aadi Festival") -> Aadi Festival
A51: =IFERROR(__xludf.DUMMYFUNCTION("IFERROR(INDEX(IMPORTRANGE(""12PgU-zwv8gBrFfxvJpoPIPcxUHWup-vsxMH3HWUigZ8"",""💸 Expenses!A5:J200""),11,1),"""")"),"2026/EX/11") -> 2026/EX/11 | B51: =IFERROR(__xludf.DUMMYFUNCTION("IFERROR(IF(INDEX(IMPORTRANGE(""12PgU-zwv8gBrFfxvJpoPIPcxUHWup-vsxMH3HWUigZ8"",""💸 Expenses!A5:J200""),11,2)="""","""",TEXT(INDEX(IMPORTRANGE(""12PgU-zwv8gBrFfxvJpoPIPcxUHWup-vsxMH3HWUigZ8"",""💸 Expenses!A5:J200""),11,2),""DD-MM-YYYY"")),"""")"),"31-05-2026") -> 31-05-2026 | C51: =IFERROR(__xludf.DUMMYFUNCTION("IFERROR(INDEX(IMPORTRANGE(""12PgU-zwv8gBrFfxvJpoPIPcxUHWup-vsxMH3HWUigZ8"",""💸 Expenses!A5:J200""),11,3),"""")"),"Print Out") -> Print Out | D51: =IFERROR(__xludf.DUMMYFUNCTION("IFERROR(INDEX(IMPORTRANGE(""12PgU-zwv8gBrFfxvJpoPIPcxUHWup-vsxMH3HWUigZ8"",""💸 Expenses!A5:J200""),11,4),"""")"),"Invite Print out laminate") -> Invite Print out laminate | E51: =IFERROR(__xludf.DUMMYFUNCTION("IFERROR(INDEX(IMPORTRANGE(""12PgU-zwv8gBrFfxvJpoPIPcxUHWup-vsxMH3HWUigZ8"",""💸 Expenses!A5:J200""),11,5),"""")"),"Miscellaneous") -> Miscellaneous | F51: =IFERROR(__xludf.DUMMYFUNCTION("IFERROR(IFERROR(INDEX(IMPORTRANGE(""12PgU-zwv8gBrFfxvJpoPIPcxUHWup-vsxMH3HWUigZ8"",""💸 Expenses!A5:J200""),11,6)*1,0),0)"),60.0) -> 60 | G51: =IFERROR(__xludf.DUMMYFUNCTION("IFERROR(INDEX(IMPORTRANGE(""12PgU-zwv8gBrFfxvJpoPIPcxUHWup-vsxMH3HWUigZ8"",""💸 Expenses!A5:J200""),11,7),"""")"),"UPI") -> UPI | H51: =IFERROR(__xludf.DUMMYFUNCTION("IFERROR(INDEX(IMPORTRANGE(""12PgU-zwv8gBrFfxvJpoPIPcxUHWup-vsxMH3HWUigZ8"",""💸 Expenses!A5:J200""),11,8),"""")"),"Sunil Kumar") -> Sunil Kumar | I51: =IFERROR(__xludf.DUMMYFUNCTION("IFERROR(INDEX(IMPORTRANGE(""12PgU-zwv8gBrFfxvJpoPIPcxUHWup-vsxMH3HWUigZ8"",""💸 Expenses!A5:J200""),11,9),"""")"),"") | J51: =IFERROR(__xludf.DUMMYFUNCTION("IFERROR(INDEX(IMPORTRANGE(""12PgU-zwv8gBrFfxvJpoPIPcxUHWup-vsxMH3HWUigZ8"",""💸 Expenses!A5:J200""),11,10),"""")"),"Aadi Festival") -> Aadi Festival
A52: =IFERROR(__xludf.DUMMYFUNCTION("IFERROR(INDEX(IMPORTRANGE(""12PgU-zwv8gBrFfxvJpoPIPcxUHWup-vsxMH3HWUigZ8"",""💸 Expenses!A5:J200""),12,1),"""")"),"2026/EX/12") -> 2026/EX/12 | B52: =IFERROR(__xludf.DUMMYFUNCTION("IFERROR(IF(INDEX(IMPORTRANGE(""12PgU-zwv8gBrFfxvJpoPIPcxUHWup-vsxMH3HWUigZ8"",""💸 Expenses!A5:J200""),12,2)="""","""",TEXT(INDEX(IMPORTRANGE(""12PgU-zwv8gBrFfxvJpoPIPcxUHWup-vsxMH3HWUigZ8"",""💸 Expenses!A5:J200""),12,2),""DD-MM-YYYY"")),"""")"),"31-05-2026") -> 31-05-2026 | C52: =IFERROR(__xludf.DUMMYFUNCTION("IFERROR(INDEX(IMPORTRANGE(""12PgU-zwv8gBrFfxvJpoPIPcxUHWup-vsxMH3HWUigZ8"",""💸 Expenses!A5:J200""),12,3),"""")"),"Amma Hotel") -> Amma Hotel | D52: =IFERROR(__xludf.DUMMYFUNCTION("IFERROR(INDEX(IMPORTRANGE(""12PgU-zwv8gBrFfxvJpoPIPcxUHWup-vsxMH3HWUigZ8"",""💸 Expenses!A5:J200""),12,4),"""")"),"Food Catering") -> Food Catering | E52: =IFERROR(__xludf.DUMMYFUNCTION("IFERROR(INDEX(IMPORTRANGE(""12PgU-zwv8gBrFfxvJpoPIPcxUHWup-vsxMH3HWUigZ8"",""💸 Expenses!A5:J200""),12,5),"""")"),"Food & Catering") -> Food & Catering | F52: =IFERROR(__xludf.DUMMYFUNCTION("IFERROR(IFERROR(INDEX(IMPORTRANGE(""12PgU-zwv8gBrFfxvJpoPIPcxUHWup-vsxMH3HWUigZ8"",""💸 Expenses!A5:J200""),12,6)*1,0),0)"),40000.0) -> 40000 | G52: =IFERROR(__xludf.DUMMYFUNCTION("IFERROR(INDEX(IMPORTRANGE(""12PgU-zwv8gBrFfxvJpoPIPcxUHWup-vsxMH3HWUigZ8"",""💸 Expenses!A5:J200""),12,7),"""")"),"UPI") -> UPI | H52: =IFERROR(__xludf.DUMMYFUNCTION("IFERROR(INDEX(IMPORTRANGE(""12PgU-zwv8gBrFfxvJpoPIPcxUHWup-vsxMH3HWUigZ8"",""💸 Expenses!A5:J200""),12,8),"""")"),"Sunil Kumar") -> Sunil Kumar | I52: =IFERROR(__xludf.DUMMYFUNCTION("IFERROR(INDEX(IMPORTRANGE(""12PgU-zwv8gBrFfxvJpoPIPcxUHWup-vsxMH3HWUigZ8"",""💸 Expenses!A5:J200""),12,9),"""")"),"") | J52: =IFERROR(__xludf.DUMMYFUNCTION("IFERROR(INDEX(IMPORTRANGE(""12PgU-zwv8gBrFfxvJpoPIPcxUHWup-vsxMH3HWUigZ8"",""💸 Expenses!A5:J200""),12,10),"""")"),"Aadi Festival") -> Aadi Festival
A53: =IFERROR(__xludf.DUMMYFUNCTION("IFERROR(INDEX(IMPORTRANGE(""12PgU-zwv8gBrFfxvJpoPIPcxUHWup-vsxMH3HWUigZ8"",""💸 Expenses!A5:J200""),13,1),"""")"),"2026/EX/13") -> 2026/EX/13 | B53: =IFERROR(__xludf.DUMMYFUNCTION("IFERROR(IF(INDEX(IMPORTRANGE(""12PgU-zwv8gBrFfxvJpoPIPcxUHWup-vsxMH3HWUigZ8"",""💸 Expenses!A5:J200""),13,2)="""","""",TEXT(INDEX(IMPORTRANGE(""12PgU-zwv8gBrFfxvJpoPIPcxUHWup-vsxMH3HWUigZ8"",""💸 Expenses!A5:J200""),13,2),""DD-MM-YYYY"")),"""")"),"31-05-2026") -> 31-05-2026 | C53: =IFERROR(__xludf.DUMMYFUNCTION("IFERROR(INDEX(IMPORTRANGE(""12PgU-zwv8gBrFfxvJpoPIPcxUHWup-vsxMH3HWUigZ8"",""💸 Expenses!A5:J200""),13,3),"""")"),"Bala Abhirami") -> Bala Abhirami | D53: =IFERROR(__xludf.DUMMYFUNCTION("IFERROR(INDEX(IMPORTRANGE(""12PgU-zwv8gBrFfxvJpoPIPcxUHWup-vsxMH3HWUigZ8"",""💸 Expenses!A5:J200""),13,4),"""")"),"Temple cleaning, painting, pipe repair materials") -> Temple cleaning, painting, pipe repair materials | E53: =IFERROR(__xludf.DUMMYFUNCTION("IFERROR(INDEX(IMPORTRANGE(""12PgU-zwv8gBrFfxvJpoPIPcxUHWup-vsxMH3HWUigZ8"",""💸 Expenses!A5:J200""),13,5),"""")"),"Infrastructure & Logistics") -> Infrastructure & Logistics | F53: =IFERROR(__xludf.DUMMYFUNCTION("IFERROR(IFERROR(INDEX(IMPORTRANGE(""12PgU-zwv8gBrFfxvJpoPIPcxUHWup-vsxMH3HWUigZ8"",""💸 Expenses!A5:J200""),13,6)*1,0),0)"),785.0) -> 785 | G53: =IFERROR(__xludf.DUMMYFUNCTION("IFERROR(INDEX(IMPORTRANGE(""12PgU-zwv8gBrFfxvJpoPIPcxUHWup-vsxMH3HWUigZ8"",""💸 Expenses!A5:J200""),13,7),"""")"),"UPI") -> UPI | H53: =IFERROR(__xludf.DUMMYFUNCTION("IFERROR(INDEX(IMPORTRANGE(""12PgU-zwv8gBrFfxvJpoPIPcxUHWup-vsxMH3HWUigZ8"",""💸 Expenses!A5:J200""),13,8),"""")"),"Sunil Kumar") -> Sunil Kumar | I53: =IFERROR(__xludf.DUMMYFUNCTION("IFERROR(INDEX(IMPORTRANGE(""12PgU-zwv8gBrFfxvJpoPIPcxUHWup-vsxMH3HWUigZ8"",""💸 Expenses!A5:J200""),13,9),"""")"),"") | J53: =IFERROR(__xludf.DUMMYFUNCTION("IFERROR(INDEX(IMPORTRANGE(""12PgU-zwv8gBrFfxvJpoPIPcxUHWup-vsxMH3HWUigZ8"",""💸 Expenses!A5:J200""),13,10),"""")"),"Aadi Festival") -> Aadi Festival
A54: =IFERROR(__xludf.DUMMYFUNCTION("IFERROR(INDEX(IMPORTRANGE(""12PgU-zwv8gBrFfxvJpoPIPcxUHWup-vsxMH3HWUigZ8"",""💸 Expenses!A5:J200""),14,1),"""")"),"2026/EX/14") -> 2026/EX/14 | B54: =IFERROR(__xludf.DUMMYFUNCTION("IFERROR(IF(INDEX(IMPORTRANGE(""12PgU-zwv8gBrFfxvJpoPIPcxUHWup-vsxMH3HWUigZ8"",""💸 Expenses!A5:J200""),14,2)="""","""",TEXT(INDEX(IMPORTRANGE(""12PgU-zwv8gBrFfxvJpoPIPcxUHWup-vsxMH3HWUigZ8"",""💸 Expenses!A5:J200""),14,2),""DD-MM-YYYY"")),"""")"),"30-05-2026") -> 30-05-2026 | C54: =IFERROR(__xludf.DUMMYFUNCTION("IFERROR(INDEX(IMPORTRANGE(""12PgU-zwv8gBrFfxvJpoPIPcxUHWup-vsxMH3HWUigZ8"",""💸 Expenses!A5:J200""),14,3),"""")"),"Narayana") -> Narayana | D54: =IFERROR(__xludf.DUMMYFUNCTION("IFERROR(INDEX(IMPORTRANGE(""12PgU-zwv8gBrFfxvJpoPIPcxUHWup-vsxMH3HWUigZ8"",""💸 Expenses!A5:J200""),14,4),"""")"),"Ladder rental and transport") -> Ladder rental and transport | E54: =IFERROR(__xludf.DUMMYFUNCTION("IFERROR(INDEX(IMPORTRANGE(""12PgU-zwv8gBrFfxvJpoPIPcxUHWup-vsxMH3HWUigZ8"",""💸 Expenses!A5:J200""),14,5),"""")"),"Transport") -> Transport | F54: =IFERROR(__xludf.DUMMYFUNCTION("IFERROR(IFERROR(INDEX(IMPORTRANGE(""12PgU-zwv8gBrFfxvJpoPIPcxUHWup-vsxMH3HWUigZ8"",""💸 Expenses!A5:J200""),14,6)*1,0),0)"),500.0) -> 500 | G54: =IFERROR(__xludf.DUMMYFUNCTION("IFERROR(INDEX(IMPORTRANGE(""12PgU-zwv8gBrFfxvJpoPIPcxUHWup-vsxMH3HWUigZ8"",""💸 Expenses!A5:J200""),14,7),"""")"),"UPI") -> UPI | H54: =IFERROR(__xludf.DUMMYFUNCTION("IFERROR(INDEX(IMPORTRANGE(""12PgU-zwv8gBrFfxvJpoPIPcxUHWup-vsxMH3HWUigZ8"",""💸 Expenses!A5:J200""),14,8),"""")"),"Sunil Kumar") -> Sunil Kumar | I54: =IFERROR(__xludf.DUMMYFUNCTION("IFERROR(INDEX(IMPORTRANGE(""12PgU-zwv8gBrFfxvJpoPIPcxUHWup-vsxMH3HWUigZ8"",""💸 Expenses!A5:J200""),14,9),"""")"),"Sheet Work") -> Sheet Work | J54: =IFERROR(__xludf.DUMMYFUNCTION("IFERROR(INDEX(IMPORTRANGE(""12PgU-zwv8gBrFfxvJpoPIPcxUHWup-vsxMH3HWUigZ8"",""💸 Expenses!A5:J200""),14,10),"""")"),"Temple Development") -> Temple Development
A55: =IFERROR(__xludf.DUMMYFUNCTION("IFERROR(INDEX(IMPORTRANGE(""12PgU-zwv8gBrFfxvJpoPIPcxUHWup-vsxMH3HWUigZ8"",""💸 Expenses!A5:J200""),15,1),"""")"),"2026/EX/15") -> 2026/EX/15 | B55: =IFERROR(__xludf.DUMMYFUNCTION("IFERROR(IF(INDEX(IMPORTRANGE(""12PgU-zwv8gBrFfxvJpoPIPcxUHWup-vsxMH3HWUigZ8"",""💸 Expenses!A5:J200""),15,2)="""","""",TEXT(INDEX(IMPORTRANGE(""12PgU-zwv8gBrFfxvJpoPIPcxUHWup-vsxMH3HWUigZ8"",""💸 Expenses!A5:J200""),15,2),""DD-MM-YYYY"")),"""")"),"30-05-2026") -> 30-05-2026 | C55: =IFERROR(__xludf.DUMMYFUNCTION("IFERROR(INDEX(IMPORTRANGE(""12PgU-zwv8gBrFfxvJpoPIPcxUHWup-vsxMH3HWUigZ8"",""💸 Expenses!A5:J200""),15,3),"""")"),"Narayana") -> Narayana | D55: =IFERROR(__xludf.DUMMYFUNCTION("IFERROR(INDEX(IMPORTRANGE(""12PgU-zwv8gBrFfxvJpoPIPcxUHWup-vsxMH3HWUigZ8"",""💸 Expenses!A5:J200""),15,4),"""")"),"Breakfast for labours") -> Breakfast for labours | E55: =IFERROR(__xludf.DUMMYFUNCTION("IFERROR(INDEX(IMPORTRANGE(""12PgU-zwv8gBrFfxvJpoPIPcxUHWup-vsxMH3HWUigZ8"",""💸 Expenses!A5:J200""),15,5),"""")"),"Food") -> Food | F55: =IFERROR(__xludf.DUMMYFUNCTION("IFERROR(IFERROR(INDEX(IMPORTRANGE(""12PgU-zwv8gBrFfxvJpoPIPcxUHWup-vsxMH3HWUigZ8"",""💸 Expenses!A5:J200""),15,6)*1,0),0)"),170.0) -> 170 | G55: =IFERROR(__xludf.DUMMYFUNCTION("IFERROR(INDEX(IMPORTRANGE(""12PgU-zwv8gBrFfxvJpoPIPcxUHWup-vsxMH3HWUigZ8"",""💸 Expenses!A5:J200""),15,7),"""")"),"UPI") -> UPI | H55: =IFERROR(__xludf.DUMMYFUNCTION("IFERROR(INDEX(IMPORTRANGE(""12PgU-zwv8gBrFfxvJpoPIPcxUHWup-vsxMH3HWUigZ8"",""💸 Expenses!A5:J200""),15,8),"""")"),"Suresh Velu") -> Suresh Velu | I55: =IFERROR(__xludf.DUMMYFUNCTION("IFERROR(INDEX(IMPORTRANGE(""12PgU-zwv8gBrFfxvJpoPIPcxUHWup-vsxMH3HWUigZ8"",""💸 Expenses!A5:J200""),15,9),"""")"),"Sheet Work") -> Sheet Work | J55: =IFERROR(__xludf.DUMMYFUNCTION("IFERROR(INDEX(IMPORTRANGE(""12PgU-zwv8gBrFfxvJpoPIPcxUHWup-vsxMH3HWUigZ8"",""💸 Expenses!A5:J200""),15,10),"""")"),"Temple Development") -> Temple Development
A56: =IFERROR(__xludf.DUMMYFUNCTION("IFERROR(INDEX(IMPORTRANGE(""12PgU-zwv8gBrFfxvJpoPIPcxUHWup-vsxMH3HWUigZ8"",""💸 Expenses!A5:J200""),16,1),"""")"),"2026/EX/16") -> 2026/EX/16 | B56: =IFERROR(__xludf.DUMMYFUNCTION("IFERROR(IF(INDEX(IMPORTRANGE(""12PgU-zwv8gBrFfxvJpoPIPcxUHWup-vsxMH3HWUigZ8"",""💸 Expenses!A5:J200""),16,2)="""","""",TEXT(INDEX(IMPORTRANGE(""12PgU-zwv8gBrFfxvJpoPIPcxUHWup-vsxMH3HWUigZ8"",""💸 Expenses!A5:J200""),16,2),""DD-MM-YYYY"")),"""")"),"30-05-2026") -> 30-05-2026 | C56: =IFERROR(__xludf.DUMMYFUNCTION("IFERROR(INDEX(IMPORTRANGE(""12PgU-zwv8gBrFfxvJpoPIPcxUHWup-vsxMH3HWUigZ8"",""💸 Expenses!A5:J200""),16,3),"""")"),"N.S. Bismi Traders") -> N.S. Bismi Traders | D56: =IFERROR(__xludf.DUMMYFUNCTION("IFERROR(INDEX(IMPORTRANGE(""12PgU-zwv8gBrFfxvJpoPIPcxUHWup-vsxMH3HWUigZ8"",""💸 Expenses!A5:J200""),16,4),"""")"),"Metal material") -> Metal material | E56: =IFERROR(__xludf.DUMMYFUNCTION("IFERROR(INDEX(IMPORTRANGE(""12PgU-zwv8gBrFfxvJpoPIPcxUHWup-vsxMH3HWUigZ8"",""💸 Expenses!A5:J200""),16,5),"""")"),"Materials") -> Materials | F56: =IFERROR(__xludf.DUMMYFUNCTION("IFERROR(IFERROR(INDEX(IMPORTRANGE(""12PgU-zwv8gBrFfxvJpoPIPcxUHWup-vsxMH3HWUigZ8"",""💸 Expenses!A5:J200""),16,6)*1,0),0)"),61000.0) -> 61000 | G56: =IFERROR(__xludf.DUMMYFUNCTION("IFERROR(INDEX(IMPORTRANGE(""12PgU-zwv8gBrFfxvJpoPIPcxUHWup-vsxMH3HWUigZ8"",""💸 Expenses!A5:J200""),16,7),"""")"),"UPI") -> UPI | H56: =IFERROR(__xludf.DUMMYFUNCTION("IFERROR(INDEX(IMPORTRANGE(""12PgU-zwv8gBrFfxvJpoPIPcxUHWup-vsxMH3HWUigZ8"",""💸 Expenses!A5:J200""),16,8),"""")"),"Sunil Kumar") -> Sunil Kumar | I56: =IFERROR(__xludf.DUMMYFUNCTION("IFERROR(INDEX(IMPORTRANGE(""12PgU-zwv8gBrFfxvJpoPIPcxUHWup-vsxMH3HWUigZ8"",""💸 Expenses!A5:J200""),16,9),"""")"),"Sheet Work") -> Sheet Work | J56: =IFERROR(__xludf.DUMMYFUNCTION("IFERROR(INDEX(IMPORTRANGE(""12PgU-zwv8gBrFfxvJpoPIPcxUHWup-vsxMH3HWUigZ8"",""💸 Expenses!A5:J200""),16,10),"""")"),"Temple Development") -> Temple Development
A57: =IFERROR(__xludf.DUMMYFUNCTION("IFERROR(INDEX(IMPORTRANGE(""12PgU-zwv8gBrFfxvJpoPIPcxUHWup-vsxMH3HWUigZ8"",""💸 Expenses!A5:J200""),17,1),"""")"),"2026/EX/17") -> 2026/EX/17 | B57: =IFERROR(__xludf.DUMMYFUNCTION("IFERROR(IF(INDEX(IMPORTRANGE(""12PgU-zwv8gBrFfxvJpoPIPcxUHWup-vsxMH3HWUigZ8"",""💸 Expenses!A5:J200""),17,2)="""","""",TEXT(INDEX(IMPORTRANGE(""12PgU-zwv8gBrFfxvJpoPIPcxUHWup-vsxMH3HWUigZ8"",""💸 Expenses!A5:J200""),17,2),""DD-MM-YYYY"")),"""")"),"30-05-2026") -> 30-05-2026 | C57: =IFERROR(__xludf.DUMMYFUNCTION("IFERROR(INDEX(IMPORTRANGE(""12PgU-zwv8gBrFfxvJpoPIPcxUHWup-vsxMH3HWUigZ8"",""💸 Expenses!A5:J200""),17,3),"""")"),"Narayana") -> Narayana | D57: =IFERROR(__xludf.DUMMYFUNCTION("IFERROR(INDEX(IMPORTRANGE(""12PgU-zwv8gBrFfxvJpoPIPcxUHWup-vsxMH3HWUigZ8"",""💸 Expenses!A5:J200""),17,4),"""")"),"Labour") -> Labour | E57: =IFERROR(__xludf.DUMMYFUNCTION("IFERROR(INDEX(IMPORTRANGE(""12PgU-zwv8gBrFfxvJpoPIPcxUHWup-vsxMH3HWUigZ8"",""💸 Expenses!A5:J200""),17,5),"""")"),"Labour") -> Labour | F57: =IFERROR(__xludf.DUMMYFUNCTION("IFERROR(IFERROR(INDEX(IMPORTRANGE(""12PgU-zwv8gBrFfxvJpoPIPcxUHWup-vsxMH3HWUigZ8"",""💸 Expenses!A5:J200""),17,6)*1,0),0)"),4000.0) -> 4000 | G57: =IFERROR(__xludf.DUMMYFUNCTION("IFERROR(INDEX(IMPORTRANGE(""12PgU-zwv8gBrFfxvJpoPIPcxUHWup-vsxMH3HWUigZ8"",""💸 Expenses!A5:J200""),17,7),"""")"),"Cash") -> Cash | H57: =IFERROR(__xludf.DUMMYFUNCTION("IFERROR(INDEX(IMPORTRANGE(""12PgU-zwv8gBrFfxvJpoPIPcxUHWup-vsxMH3HWUigZ8"",""💸 Expenses!A5:J200""),17,8),"""")"),"Sunil Kumar") -> Sunil Kumar | I57: =IFERROR(__xludf.DUMMYFUNCTION("IFERROR(INDEX(IMPORTRANGE(""12PgU-zwv8gBrFfxvJpoPIPcxUHWup-vsxMH3HWUigZ8"",""💸 Expenses!A5:J200""),17,9),"""")"),"Sheet Work") -> Sheet Work | J57: =IFERROR(__xludf.DUMMYFUNCTION("IFERROR(INDEX(IMPORTRANGE(""12PgU-zwv8gBrFfxvJpoPIPcxUHWup-vsxMH3HWUigZ8"",""💸 Expenses!A5:J200""),17,10),"""")"),"Temple Development") -> Temple Development
A58: =IFERROR(__xludf.DUMMYFUNCTION("IFERROR(INDEX(IMPORTRANGE(""12PgU-zwv8gBrFfxvJpoPIPcxUHWup-vsxMH3HWUigZ8"",""💸 Expenses!A5:J200""),18,1),"""")"),"2026/EX/18") -> 2026/EX/18 | B58: =IFERROR(__xludf.DUMMYFUNCTION("IFERROR(IF(INDEX(IMPORTRANGE(""12PgU-zwv8gBrFfxvJpoPIPcxUHWup-vsxMH3HWUigZ8"",""💸 Expenses!A5:J200""),18,2)="""","""",TEXT(INDEX(IMPORTRANGE(""12PgU-zwv8gBrFfxvJpoPIPcxUHWup-vsxMH3HWUigZ8"",""💸 Expenses!A5:J200""),18,2),""DD-MM-YYYY"")),"""")"),"30-05-2026") -> 30-05-2026 | C58: =IFERROR(__xludf.DUMMYFUNCTION("IFERROR(INDEX(IMPORTRANGE(""12PgU-zwv8gBrFfxvJpoPIPcxUHWup-vsxMH3HWUigZ8"",""💸 Expenses!A5:J200""),18,3),"""")"),"N.S. Bismi Traders") -> N.S. Bismi Traders | D58: =IFERROR(__xludf.DUMMYFUNCTION("IFERROR(INDEX(IMPORTRANGE(""12PgU-zwv8gBrFfxvJpoPIPcxUHWup-vsxMH3HWUigZ8"",""💸 Expenses!A5:J200""),18,4),"""")"),"Tempo for metal material") -> Tempo for metal material | E58: =IFERROR(__xludf.DUMMYFUNCTION("IFERROR(INDEX(IMPORTRANGE(""12PgU-zwv8gBrFfxvJpoPIPcxUHWup-vsxMH3HWUigZ8"",""💸 Expenses!A5:J200""),18,5),"""")"),"Transport") -> Transport | F58: =IFERROR(__xludf.DUMMYFUNCTION("IFERROR(IFERROR(INDEX(IMPORTRANGE(""12PgU-zwv8gBrFfxvJpoPIPcxUHWup-vsxMH3HWUigZ8"",""💸 Expenses!A5:J200""),18,6)*1,0),0)"),1100.0) -> 1100 | G58: =IFERROR(__xludf.DUMMYFUNCTION("IFERROR(INDEX(IMPORTRANGE(""12PgU-zwv8gBrFfxvJpoPIPcxUHWup-vsxMH3HWUigZ8"",""💸 Expenses!A5:J200""),18,7),"""")"),"Cash") -> Cash | H58: =IFERROR(__xludf.DUMMYFUNCTION("IFERROR(INDEX(IMPORTRANGE(""12PgU-zwv8gBrFfxvJpoPIPcxUHWup-vsxMH3HWUigZ8"",""💸 Expenses!A5:J200""),18,8),"""")"),"Sunil Kumar") -> Sunil Kumar | I58: =IFERROR(__xludf.DUMMYFUNCTION("IFERROR(INDEX(IMPORTRANGE(""12PgU-zwv8gBrFfxvJpoPIPcxUHWup-vsxMH3HWUigZ8"",""💸 Expenses!A5:J200""),18,9),"""")"),"Sheet Work") -> Sheet Work | J58: =IFERROR(__xludf.DUMMYFUNCTION("IFERROR(INDEX(IMPORTRANGE(""12PgU-zwv8gBrFfxvJpoPIPcxUHWup-vsxMH3HWUigZ8"",""💸 Expenses!A5:J200""),18,10),"""")"),"Temple Development") -> Temple Development
A59: =IFERROR(__xludf.DUMMYFUNCTION("IFERROR(INDEX(IMPORTRANGE(""12PgU-zwv8gBrFfxvJpoPIPcxUHWup-vsxMH3HWUigZ8"",""💸 Expenses!A5:J200""),19,1),"""")"),"2026/EX/19") -> 2026/EX/19 | B59: =IFERROR(__xludf.DUMMYFUNCTION("IFERROR(IF(INDEX(IMPORTRANGE(""12PgU-zwv8gBrFfxvJpoPIPcxUHWup-vsxMH3HWUigZ8"",""💸 Expenses!A5:J200""),19,2)="""","""",TEXT(INDEX(IMPORTRANGE(""12PgU-zwv8gBrFfxvJpoPIPcxUHWup-vsxMH3HWUigZ8"",""💸 Expenses!A5:J200""),19,2),""DD-MM-YYYY"")),"""")"),"31-05-2026") -> 31-05-2026 | C59: =IFERROR(__xludf.DUMMYFUNCTION("IFERROR(INDEX(IMPORTRANGE(""12PgU-zwv8gBrFfxvJpoPIPcxUHWup-vsxMH3HWUigZ8"",""💸 Expenses!A5:J200""),19,3),"""")"),"N.S. Bismi Traders") -> N.S. Bismi Traders | D59: =IFERROR(__xludf.DUMMYFUNCTION("IFERROR(INDEX(IMPORTRANGE(""12PgU-zwv8gBrFfxvJpoPIPcxUHWup-vsxMH3HWUigZ8"",""💸 Expenses!A5:J200""),19,4),"""")"),"Metal Material") -> Metal Material | E59: =IFERROR(__xludf.DUMMYFUNCTION("IFERROR(INDEX(IMPORTRANGE(""12PgU-zwv8gBrFfxvJpoPIPcxUHWup-vsxMH3HWUigZ8"",""💸 Expenses!A5:J200""),19,5),"""")"),"Materials") -> Materials | F59: =IFERROR(__xludf.DUMMYFUNCTION("IFERROR(IFERROR(INDEX(IMPORTRANGE(""12PgU-zwv8gBrFfxvJpoPIPcxUHWup-vsxMH3HWUigZ8"",""💸 Expenses!A5:J200""),19,6)*1,0),0)"),1300.0) -> 1300 | G59: =IFERROR(__xludf.DUMMYFUNCTION("IFERROR(INDEX(IMPORTRANGE(""12PgU-zwv8gBrFfxvJpoPIPcxUHWup-vsxMH3HWUigZ8"",""💸 Expenses!A5:J200""),19,7),"""")"),"UPI") -> UPI | H59: =IFERROR(__xludf.DUMMYFUNCTION("IFERROR(INDEX(IMPORTRANGE(""12PgU-zwv8gBrFfxvJpoPIPcxUHWup-vsxMH3HWUigZ8"",""💸 Expenses!A5:J200""),19,8),"""")"),"Sunil Kumar") -> Sunil Kumar | I59: =IFERROR(__xludf.DUMMYFUNCTION("IFERROR(INDEX(IMPORTRANGE(""12PgU-zwv8gBrFfxvJpoPIPcxUHWup-vsxMH3HWUigZ8"",""💸 Expenses!A5:J200""),19,9),"""")"),"Sheet Work") -> Sheet Work | J59: =IFERROR(__xludf.DUMMYFUNCTION("IFERROR(INDEX(IMPORTRANGE(""12PgU-zwv8gBrFfxvJpoPIPcxUHWup-vsxMH3HWUigZ8"",""💸 Expenses!A5:J200""),19,10),"""")"),"Temple Development") -> Temple Development
A60: =IFERROR(__xludf.DUMMYFUNCTION("IFERROR(INDEX(IMPORTRANGE(""12PgU-zwv8gBrFfxvJpoPIPcxUHWup-vsxMH3HWUigZ8"",""💸 Expenses!A5:J200""),20,1),"""")"),"2026/EX/20") -> 2026/EX/20 | B60: =IFERROR(__xludf.DUMMYFUNCTION("IFERROR(IF(INDEX(IMPORTRANGE(""12PgU-zwv8gBrFfxvJpoPIPcxUHWup-vsxMH3HWUigZ8"",""💸 Expenses!A5:J200""),20,2)="""","""",TEXT(INDEX(IMPORTRANGE(""12PgU-zwv8gBrFfxvJpoPIPcxUHWup-vsxMH3HWUigZ8"",""💸 Expenses!A5:J200""),20,2),""DD-MM-YYYY"")),"""")"),"31-05-2026") -> 31-05-2026 | C60: =IFERROR(__xludf.DUMMYFUNCTION("IFERROR(INDEX(IMPORTRANGE(""12PgU-zwv8gBrFfxvJpoPIPcxUHWup-vsxMH3HWUigZ8"",""💸 Expenses!A5:J200""),20,3),"""")"),"Bala Abhirami") -> Bala Abhirami | D60: =IFERROR(__xludf.DUMMYFUNCTION("IFERROR(INDEX(IMPORTRANGE(""12PgU-zwv8gBrFfxvJpoPIPcxUHWup-vsxMH3HWUigZ8"",""💸 Expenses!A5:J200""),20,4),"""")"),"Thar Tape") -> Thar Tape | E60: =IFERROR(__xludf.DUMMYFUNCTION("IFERROR(INDEX(IMPORTRANGE(""12PgU-zwv8gBrFfxvJpoPIPcxUHWup-vsxMH3HWUigZ8"",""💸 Expenses!A5:J200""),20,5),"""")"),"Materials") -> Materials | F60: =IFERROR(__xludf.DUMMYFUNCTION("IFERROR(IFERROR(INDEX(IMPORTRANGE(""12PgU-zwv8gBrFfxvJpoPIPcxUHWup-vsxMH3HWUigZ8"",""💸 Expenses!A5:J200""),20,6)*1,0),0)"),650.0) -> 650 | G60: =IFERROR(__xludf.DUMMYFUNCTION("IFERROR(INDEX(IMPORTRANGE(""12PgU-zwv8gBrFfxvJpoPIPcxUHWup-vsxMH3HWUigZ8"",""💸 Expenses!A5:J200""),20,7),"""")"),"UPI") -> UPI | H60: =IFERROR(__xludf.DUMMYFUNCTION("IFERROR(INDEX(IMPORTRANGE(""12PgU-zwv8gBrFfxvJpoPIPcxUHWup-vsxMH3HWUigZ8"",""💸 Expenses!A5:J200""),20,8),"""")"),"Sunil Kumar") -> Sunil Kumar | I60: =IFERROR(__xludf.DUMMYFUNCTION("IFERROR(INDEX(IMPORTRANGE(""12PgU-zwv8gBrFfxvJpoPIPcxUHWup-vsxMH3HWUigZ8"",""💸 Expenses!A5:J200""),20,9),"""")"),"Sheet Work") -> Sheet Work | J60: =IFERROR(__xludf.DUMMYFUNCTION("IFERROR(INDEX(IMPORTRANGE(""12PgU-zwv8gBrFfxvJpoPIPcxUHWup-vsxMH3HWUigZ8"",""💸 Expenses!A5:J200""),20,10),"""")"),"Temple Development") -> Temple Development
A61: =IFERROR(__xludf.DUMMYFUNCTION("IFERROR(INDEX(IMPORTRANGE(""12PgU-zwv8gBrFfxvJpoPIPcxUHWup-vsxMH3HWUigZ8"",""💸 Expenses!A5:J200""),21,1),"""")"),"2026/EX/21") -> 2026/EX/21 | B61: =IFERROR(__xludf.DUMMYFUNCTION("IFERROR(IF(INDEX(IMPORTRANGE(""12PgU-zwv8gBrFfxvJpoPIPcxUHWup-vsxMH3HWUigZ8"",""💸 Expenses!A5:J200""),21,2)="""","""",TEXT(INDEX(IMPORTRANGE(""12PgU-zwv8gBrFfxvJpoPIPcxUHWup-vsxMH3HWUigZ8"",""💸 Expenses!A5:J200""),21,2),""DD-MM-YYYY"")),"""")"),"31-05-2026") -> 31-05-2026 | C61: =IFERROR(__xludf.DUMMYFUNCTION("IFERROR(INDEX(IMPORTRANGE(""12PgU-zwv8gBrFfxvJpoPIPcxUHWup-vsxMH3HWUigZ8"",""💸 Expenses!A5:J200""),21,3),"""")"),"Narayana") -> Narayana | D61: =IFERROR(__xludf.DUMMYFUNCTION("IFERROR(INDEX(IMPORTRANGE(""12PgU-zwv8gBrFfxvJpoPIPcxUHWup-vsxMH3HWUigZ8"",""💸 Expenses!A5:J200""),21,4),"""")"),"Labour Lunch") -> Labour Lunch | E61: =IFERROR(__xludf.DUMMYFUNCTION("IFERROR(INDEX(IMPORTRANGE(""12PgU-zwv8gBrFfxvJpoPIPcxUHWup-vsxMH3HWUigZ8"",""💸 Expenses!A5:J200""),21,5),"""")"),"Food") -> Food | F61: =IFERROR(__xludf.DUMMYFUNCTION("IFERROR(IFERROR(INDEX(IMPORTRANGE(""12PgU-zwv8gBrFfxvJpoPIPcxUHWup-vsxMH3HWUigZ8"",""💸 Expenses!A5:J200""),21,6)*1,0),0)"),250.0) -> 250 | G61: =IFERROR(__xludf.DUMMYFUNCTION("IFERROR(INDEX(IMPORTRANGE(""12PgU-zwv8gBrFfxvJpoPIPcxUHWup-vsxMH3HWUigZ8"",""💸 Expenses!A5:J200""),21,7),"""")"),"UPI") -> UPI | H61: =IFERROR(__xludf.DUMMYFUNCTION("IFERROR(INDEX(IMPORTRANGE(""12PgU-zwv8gBrFfxvJpoPIPcxUHWup-vsxMH3HWUigZ8"",""💸 Expenses!A5:J200""),21,8),"""")"),"Suresh Velu") -> Suresh Velu | I61: =IFERROR(__xludf.DUMMYFUNCTION("IFERROR(INDEX(IMPORTRANGE(""12PgU-zwv8gBrFfxvJpoPIPcxUHWup-vsxMH3HWUigZ8"",""💸 Expenses!A5:J200""),21,9),"""")"),"Sheet Work") -> Sheet Work | J61: =IFERROR(__xludf.DUMMYFUNCTION("IFERROR(INDEX(IMPORTRANGE(""12PgU-zwv8gBrFfxvJpoPIPcxUHWup-vsxMH3HWUigZ8"",""💸 Expenses!A5:J200""),21,10),"""")"),"Temple Development") -> Temple Development
A62: =IFERROR(__xludf.DUMMYFUNCTION("IFERROR(INDEX(IMPORTRANGE(""12PgU-zwv8gBrFfxvJpoPIPcxUHWup-vsxMH3HWUigZ8"",""💸 Expenses!A5:J200""),22,1),"""")"),"2026/EX/22") -> 2026/EX/22 | B62: =IFERROR(__xludf.DUMMYFUNCTION("IFERROR(IF(INDEX(IMPORTRANGE(""12PgU-zwv8gBrFfxvJpoPIPcxUHWup-vsxMH3HWUigZ8"",""💸 Expenses!A5:J200""),22,2)="""","""",TEXT(INDEX(IMPORTRANGE(""12PgU-zwv8gBrFfxvJpoPIPcxUHWup-vsxMH3HWUigZ8"",""💸 Expenses!A5:J200""),22,2),""DD-MM-YYYY"")),"""")"),"31-05-2026") -> 31-05-2026 | C62: =IFERROR(__xludf.DUMMYFUNCTION("IFERROR(INDEX(IMPORTRANGE(""12PgU-zwv8gBrFfxvJpoPIPcxUHWup-vsxMH3HWUigZ8"",""💸 Expenses!A5:J200""),22,3),"""")"),"Narayana") -> Narayana | D62: =IFERROR(__xludf.DUMMYFUNCTION("IFERROR(INDEX(IMPORTRANGE(""12PgU-zwv8gBrFfxvJpoPIPcxUHWup-vsxMH3HWUigZ8"",""💸 Expenses!A5:J200""),22,4),"""")"),"Labour") -> Labour | E62: =IFERROR(__xludf.DUMMYFUNCTION("IFERROR(INDEX(IMPORTRANGE(""12PgU-zwv8gBrFfxvJpoPIPcxUHWup-vsxMH3HWUigZ8"",""💸 Expenses!A5:J200""),22,5),"""")"),"Labour") -> Labour | F62: =IFERROR(__xludf.DUMMYFUNCTION("IFERROR(IFERROR(INDEX(IMPORTRANGE(""12PgU-zwv8gBrFfxvJpoPIPcxUHWup-vsxMH3HWUigZ8"",""💸 Expenses!A5:J200""),22,6)*1,0),0)"),6000.0) -> 6000 | G62: =IFERROR(__xludf.DUMMYFUNCTION("IFERROR(INDEX(IMPORTRANGE(""12PgU-zwv8gBrFfxvJpoPIPcxUHWup-vsxMH3HWUigZ8"",""💸 Expenses!A5:J200""),22,7),"""")"),"Cash") -> Cash | H62: =IFERROR(__xludf.DUMMYFUNCTION("IFERROR(INDEX(IMPORTRANGE(""12PgU-zwv8gBrFfxvJpoPIPcxUHWup-vsxMH3HWUigZ8"",""💸 Expenses!A5:J200""),22,8),"""")"),"Sunil Kumar") -> Sunil Kumar | I62: =IFERROR(__xludf.DUMMYFUNCTION("IFERROR(INDEX(IMPORTRANGE(""12PgU-zwv8gBrFfxvJpoPIPcxUHWup-vsxMH3HWUigZ8"",""💸 Expenses!A5:J200""),22,9),"""")"),"Sheet Work") -> Sheet Work | J62: =IFERROR(__xludf.DUMMYFUNCTION("IFERROR(INDEX(IMPORTRANGE(""12PgU-zwv8gBrFfxvJpoPIPcxUHWup-vsxMH3HWUigZ8"",""💸 Expenses!A5:J200""),22,10),"""")"),"Temple Development") -> Temple Development
A63: =IFERROR(__xludf.DUMMYFUNCTION("IFERROR(INDEX(IMPORTRANGE(""12PgU-zwv8gBrFfxvJpoPIPcxUHWup-vsxMH3HWUigZ8"",""💸 Expenses!A5:J200""),23,1),"""")"),"2026/EX/23") -> 2026/EX/23 | B63: =IFERROR(__xludf.DUMMYFUNCTION("IFERROR(IF(INDEX(IMPORTRANGE(""12PgU-zwv8gBrFfxvJpoPIPcxUHWup-vsxMH3HWUigZ8"",""💸 Expenses!A5:J200""),23,2)="""","""",TEXT(INDEX(IMPORTRANGE(""12PgU-zwv8gBrFfxvJpoPIPcxUHWup-vsxMH3HWUigZ8"",""💸 Expenses!A5:J200""),23,2),""DD-MM-YYYY"")),"""")"),"31-05-2026") -> 31-05-2026 | C63: =IFERROR(__xludf.DUMMYFUNCTION("IFERROR(INDEX(IMPORTRANGE(""12PgU-zwv8gBrFfxvJpoPIPcxUHWup-vsxMH3HWUigZ8"",""💸 Expenses!A5:J200""),23,3),"""")"),"Kumar") -> Kumar | D63: =IFERROR(__xludf.DUMMYFUNCTION("IFERROR(INDEX(IMPORTRANGE(""12PgU-zwv8gBrFfxvJpoPIPcxUHWup-vsxMH3HWUigZ8"",""💸 Expenses!A5:J200""),23,4),"""")"),"Petrol expenses") -> Petrol expenses | E63: =IFERROR(__xludf.DUMMYFUNCTION("IFERROR(INDEX(IMPORTRANGE(""12PgU-zwv8gBrFfxvJpoPIPcxUHWup-vsxMH3HWUigZ8"",""💸 Expenses!A5:J200""),23,5),"""")"),"Miscellaneous") -> Miscellaneous | F63: =IFERROR(__xludf.DUMMYFUNCTION("IFERROR(IFERROR(INDEX(IMPORTRANGE(""12PgU-zwv8gBrFfxvJpoPIPcxUHWup-vsxMH3HWUigZ8"",""💸 Expenses!A5:J200""),23,6)*1,0),0)"),400.0) -> 400 | G63: =IFERROR(__xludf.DUMMYFUNCTION("IFERROR(INDEX(IMPORTRANGE(""12PgU-zwv8gBrFfxvJpoPIPcxUHWup-vsxMH3HWUigZ8"",""💸 Expenses!A5:J200""),23,7),"""")"),"Cash") -> Cash | H63: =IFERROR(__xludf.DUMMYFUNCTION("IFERROR(INDEX(IMPORTRANGE(""12PgU-zwv8gBrFfxvJpoPIPcxUHWup-vsxMH3HWUigZ8"",""💸 Expenses!A5:J200""),23,8),"""")"),"Sunil Kumar") -> Sunil Kumar | I63: =IFERROR(__xludf.DUMMYFUNCTION("IFERROR(INDEX(IMPORTRANGE(""12PgU-zwv8gBrFfxvJpoPIPcxUHWup-vsxMH3HWUigZ8"",""💸 Expenses!A5:J200""),23,9),"""")"),"Sheet Work") -> Sheet Work | J63: =IFERROR(__xludf.DUMMYFUNCTION("IFERROR(INDEX(IMPORTRANGE(""12PgU-zwv8gBrFfxvJpoPIPcxUHWup-vsxMH3HWUigZ8"",""💸 Expenses!A5:J200""),23,10),"""")"),"Temple Development") -> Temple Development
A64: =IFERROR(__xludf.DUMMYFUNCTION("IFERROR(INDEX(IMPORTRANGE(""12PgU-zwv8gBrFfxvJpoPIPcxUHWup-vsxMH3HWUigZ8"",""💸 Expenses!A5:J200""),24,1),"""")"),"2026/EX/24") -> 2026/EX/24 | B64: =IFERROR(__xludf.DUMMYFUNCTION("IFERROR(IF(INDEX(IMPORTRANGE(""12PgU-zwv8gBrFfxvJpoPIPcxUHWup-vsxMH3HWUigZ8"",""💸 Expenses!A5:J200""),24,2)="""","""",TEXT(INDEX(IMPORTRANGE(""12PgU-zwv8gBrFfxvJpoPIPcxUHWup-vsxMH3HWUigZ8"",""💸 Expenses!A5:J200""),24,2),""DD-MM-YYYY"")),"""")"),"02-06-2026") -> 02-06-2026 | C64: =IFERROR(__xludf.DUMMYFUNCTION("IFERROR(INDEX(IMPORTRANGE(""12PgU-zwv8gBrFfxvJpoPIPcxUHWup-vsxMH3HWUigZ8"",""💸 Expenses!A5:J200""),24,3),"""")"),"Kumar") -> Kumar | D64: =IFERROR(__xludf.DUMMYFUNCTION("IFERROR(INDEX(IMPORTRANGE(""12PgU-zwv8gBrFfxvJpoPIPcxUHWup-vsxMH3HWUigZ8"",""💸 Expenses!A5:J200""),24,4),"""")"),"Food") -> Food | E64: =IFERROR(__xludf.DUMMYFUNCTION("IFERROR(INDEX(IMPORTRANGE(""12PgU-zwv8gBrFfxvJpoPIPcxUHWup-vsxMH3HWUigZ8"",""💸 Expenses!A5:J200""),24,5),"""")"),"Food") -> Food | F64: =IFERROR(__xludf.DUMMYFUNCTION("IFERROR(IFERROR(INDEX(IMPORTRANGE(""12PgU-zwv8gBrFfxvJpoPIPcxUHWup-vsxMH3HWUigZ8"",""💸 Expenses!A5:J200""),24,6)*1,0),0)"),500.0) -> 500 | G64: =IFERROR(__xludf.DUMMYFUNCTION("IFERROR(INDEX(IMPORTRANGE(""12PgU-zwv8gBrFfxvJpoPIPcxUHWup-vsxMH3HWUigZ8"",""💸 Expenses!A5:J200""),24,7),"""")"),"UPI") -> UPI | H64: =IFERROR(__xludf.DUMMYFUNCTION("IFERROR(INDEX(IMPORTRANGE(""12PgU-zwv8gBrFfxvJpoPIPcxUHWup-vsxMH3HWUigZ8"",""💸 Expenses!A5:J200""),24,8),"""")"),"Sunil Kumar") -> Sunil Kumar | I64: =IFERROR(__xludf.DUMMYFUNCTION("IFERROR(INDEX(IMPORTRANGE(""12PgU-zwv8gBrFfxvJpoPIPcxUHWup-vsxMH3HWUigZ8"",""💸 Expenses!A5:J200""),24,9),"""")"),"Sheet Work") -> Sheet Work | J64: =IFERROR(__xludf.DUMMYFUNCTION("IFERROR(INDEX(IMPORTRANGE(""12PgU-zwv8gBrFfxvJpoPIPcxUHWup-vsxMH3HWUigZ8"",""💸 Expenses!A5:J200""),24,10),"""")"),"Temple Development") -> Temple Development
A65: =IFERROR(__xludf.DUMMYFUNCTION("IFERROR(INDEX(IMPORTRANGE(""12PgU-zwv8gBrFfxvJpoPIPcxUHWup-vsxMH3HWUigZ8"",""💸 Expenses!A5:J200""),25,1),"""")"),"2026/EX/25") -> 2026/EX/25 | B65: =IFERROR(__xludf.DUMMYFUNCTION("IFERROR(IF(INDEX(IMPORTRANGE(""12PgU-zwv8gBrFfxvJpoPIPcxUHWup-vsxMH3HWUigZ8"",""💸 Expenses!A5:J200""),25,2)="""","""",TEXT(INDEX(IMPORTRANGE(""12PgU-zwv8gBrFfxvJpoPIPcxUHWup-vsxMH3HWUigZ8"",""💸 Expenses!A5:J200""),25,2),""DD-MM-YYYY"")),"""")"),"02-06-2026") -> 02-06-2026 | C65: =IFERROR(__xludf.DUMMYFUNCTION("IFERROR(INDEX(IMPORTRANGE(""12PgU-zwv8gBrFfxvJpoPIPcxUHWup-vsxMH3HWUigZ8"",""💸 Expenses!A5:J200""),25,3),"""")"),"N.S. Bismi Traders") -> N.S. Bismi Traders | D65: =IFERROR(__xludf.DUMMYFUNCTION("IFERROR(INDEX(IMPORTRANGE(""12PgU-zwv8gBrFfxvJpoPIPcxUHWup-vsxMH3HWUigZ8"",""💸 Expenses!A5:J200""),25,4),"""")"),"Additional Screws") -> Additional Screws | E65: =IFERROR(__xludf.DUMMYFUNCTION("IFERROR(INDEX(IMPORTRANGE(""12PgU-zwv8gBrFfxvJpoPIPcxUHWup-vsxMH3HWUigZ8"",""💸 Expenses!A5:J200""),25,5),"""")"),"Materials") -> Materials | F65: =IFERROR(__xludf.DUMMYFUNCTION("IFERROR(IFERROR(INDEX(IMPORTRANGE(""12PgU-zwv8gBrFfxvJpoPIPcxUHWup-vsxMH3HWUigZ8"",""💸 Expenses!A5:J200""),25,6)*1,0),0)"),450.0) -> 450 | G65: =IFERROR(__xludf.DUMMYFUNCTION("IFERROR(INDEX(IMPORTRANGE(""12PgU-zwv8gBrFfxvJpoPIPcxUHWup-vsxMH3HWUigZ8"",""💸 Expenses!A5:J200""),25,7),"""")"),"UPI") -> UPI | H65: =IFERROR(__xludf.DUMMYFUNCTION("IFERROR(INDEX(IMPORTRANGE(""12PgU-zwv8gBrFfxvJpoPIPcxUHWup-vsxMH3HWUigZ8"",""💸 Expenses!A5:J200""),25,8),"""")"),"Sunil Kumar") -> Sunil Kumar | I65: =IFERROR(__xludf.DUMMYFUNCTION("IFERROR(INDEX(IMPORTRANGE(""12PgU-zwv8gBrFfxvJpoPIPcxUHWup-vsxMH3HWUigZ8"",""💸 Expenses!A5:J200""),25,9),"""")"),"Sheet Work") -> Sheet Work | J65: =IFERROR(__xludf.DUMMYFUNCTION("IFERROR(INDEX(IMPORTRANGE(""12PgU-zwv8gBrFfxvJpoPIPcxUHWup-vsxMH3HWUigZ8"",""💸 Expenses!A5:J200""),25,10),"""")"),"Temple Development") -> Temple Development
A66: =IFERROR(__xludf.DUMMYFUNCTION("IFERROR(INDEX(IMPORTRANGE(""12PgU-zwv8gBrFfxvJpoPIPcxUHWup-vsxMH3HWUigZ8"",""💸 Expenses!A5:J200""),26,1),"""")"),"2026/EX/26") -> 2026/EX/26 | B66: =IFERROR(__xludf.DUMMYFUNCTION("IFERROR(IF(INDEX(IMPORTRANGE(""12PgU-zwv8gBrFfxvJpoPIPcxUHWup-vsxMH3HWUigZ8"",""💸 Expenses!A5:J200""),26,2)="""","""",TEXT(INDEX(IMPORTRANGE(""12PgU-zwv8gBrFfxvJpoPIPcxUHWup-vsxMH3HWUigZ8"",""💸 Expenses!A5:J200""),26,2),""DD-MM-YYYY"")),"""")"),"02-06-2026") -> 02-06-2026 | C66: =IFERROR(__xludf.DUMMYFUNCTION("IFERROR(INDEX(IMPORTRANGE(""12PgU-zwv8gBrFfxvJpoPIPcxUHWup-vsxMH3HWUigZ8"",""💸 Expenses!A5:J200""),26,3),"""")"),"Kumar") -> Kumar | D66: =IFERROR(__xludf.DUMMYFUNCTION("IFERROR(INDEX(IMPORTRANGE(""12PgU-zwv8gBrFfxvJpoPIPcxUHWup-vsxMH3HWUigZ8"",""💸 Expenses!A5:J200""),26,4),"""")"),"Cement and Msand") -> Cement and Msand | E66: =IFERROR(__xludf.DUMMYFUNCTION("IFERROR(INDEX(IMPORTRANGE(""12PgU-zwv8gBrFfxvJpoPIPcxUHWup-vsxMH3HWUigZ8"",""💸 Expenses!A5:J200""),26,5),"""")"),"Materials") -> Materials | F66: =IFERROR(__xludf.DUMMYFUNCTION("IFERROR(IFERROR(INDEX(IMPORTRANGE(""12PgU-zwv8gBrFfxvJpoPIPcxUHWup-vsxMH3HWUigZ8"",""💸 Expenses!A5:J200""),26,6)*1,0),0)"),450.0) -> 450 | G66: =IFERROR(__xludf.DUMMYFUNCTION("IFERROR(INDEX(IMPORTRANGE(""12PgU-zwv8gBrFfxvJpoPIPcxUHWup-vsxMH3HWUigZ8"",""💸 Expenses!A5:J200""),26,7),"""")"),"UPI") -> UPI | H66: =IFERROR(__xludf.DUMMYFUNCTION("IFERROR(INDEX(IMPORTRANGE(""12PgU-zwv8gBrFfxvJpoPIPcxUHWup-vsxMH3HWUigZ8"",""💸 Expenses!A5:J200""),26,8),"""")"),"Sunil Kumar") -> Sunil Kumar | I66: =IFERROR(__xludf.DUMMYFUNCTION("IFERROR(INDEX(IMPORTRANGE(""12PgU-zwv8gBrFfxvJpoPIPcxUHWup-vsxMH3HWUigZ8"",""💸 Expenses!A5:J200""),26,9),"""")"),"Sheet Work") -> Sheet Work | J66: =IFERROR(__xludf.DUMMYFUNCTION("IFERROR(INDEX(IMPORTRANGE(""12PgU-zwv8gBrFfxvJpoPIPcxUHWup-vsxMH3HWUigZ8"",""💸 Expenses!A5:J200""),26,10),"""")"),"Temple Development") -> Temple Development
A67: =IFERROR(__xludf.DUMMYFUNCTION("IFERROR(INDEX(IMPORTRANGE(""12PgU-zwv8gBrFfxvJpoPIPcxUHWup-vsxMH3HWUigZ8"",""💸 Expenses!A5:J200""),27,1),"""")"),"2026/EX/27") -> 2026/EX/27 | B67: =IFERROR(__xludf.DUMMYFUNCTION("IFERROR(IF(INDEX(IMPORTRANGE(""12PgU-zwv8gBrFfxvJpoPIPcxUHWup-vsxMH3HWUigZ8"",""💸 Expenses!A5:J200""),27,2)="""","""",TEXT(INDEX(IMPORTRANGE(""12PgU-zwv8gBrFfxvJpoPIPcxUHWup-vsxMH3HWUigZ8"",""💸 Expenses!A5:J200""),27,2),""DD-MM-YYYY"")),"""")"),"06-06-2026") -> 06-06-2026 | C67: =IFERROR(__xludf.DUMMYFUNCTION("IFERROR(INDEX(IMPORTRANGE(""12PgU-zwv8gBrFfxvJpoPIPcxUHWup-vsxMH3HWUigZ8"",""💸 Expenses!A5:J200""),27,3),"""")"),"Dharmalingam") -> Dharmalingam | D67: =IFERROR(__xludf.DUMMYFUNCTION("IFERROR(INDEX(IMPORTRANGE(""12PgU-zwv8gBrFfxvJpoPIPcxUHWup-vsxMH3HWUigZ8"",""💸 Expenses!A5:J200""),27,4),"""")"),"Pooja Items - Advance") -> Pooja Items - Advance | E67: =IFERROR(__xludf.DUMMYFUNCTION("IFERROR(INDEX(IMPORTRANGE(""12PgU-zwv8gBrFfxvJpoPIPcxUHWup-vsxMH3HWUigZ8"",""💸 Expenses!A5:J200""),27,5),"""")"),"Puja & Rituals") -> Puja & Rituals | F67: =IFERROR(__xludf.DUMMYFUNCTION("IFERROR(IFERROR(INDEX(IMPORTRANGE(""12PgU-zwv8gBrFfxvJpoPIPcxUHWup-vsxMH3HWUigZ8"",""💸 Expenses!A5:J200""),27,6)*1,0),0)"),9500.0) -> 9500 | G67: =IFERROR(__xludf.DUMMYFUNCTION("IFERROR(INDEX(IMPORTRANGE(""12PgU-zwv8gBrFfxvJpoPIPcxUHWup-vsxMH3HWUigZ8"",""💸 Expenses!A5:J200""),27,7),"""")"),"Cash") -> Cash | H67: =IFERROR(__xludf.DUMMYFUNCTION("IFERROR(INDEX(IMPORTRANGE(""12PgU-zwv8gBrFfxvJpoPIPcxUHWup-vsxMH3HWUigZ8"",""💸 Expenses!A5:J200""),27,8),"""")"),"Sunil Kumar") -> Sunil Kumar | I67: =IFERROR(__xludf.DUMMYFUNCTION("IFERROR(INDEX(IMPORTRANGE(""12PgU-zwv8gBrFfxvJpoPIPcxUHWup-vsxMH3HWUigZ8"",""💸 Expenses!A5:J200""),27,9),"""")"),"") | J67: =IFERROR(__xludf.DUMMYFUNCTION("IFERROR(INDEX(IMPORTRANGE(""12PgU-zwv8gBrFfxvJpoPIPcxUHWup-vsxMH3HWUigZ8"",""💸 Expenses!A5:J200""),27,10),"""")"),"Aadi Festival") -> Aadi Festival
A68: =IFERROR(__xludf.DUMMYFUNCTION("IFERROR(INDEX(IMPORTRANGE(""12PgU-zwv8gBrFfxvJpoPIPcxUHWup-vsxMH3HWUigZ8"",""💸 Expenses!A5:J200""),28,1),"""")"),"") | B68: =IFERROR(__xludf.DUMMYFUNCTION("IFERROR(IF(INDEX(IMPORTRANGE(""12PgU-zwv8gBrFfxvJpoPIPcxUHWup-vsxMH3HWUigZ8"",""💸 Expenses!A5:J200""),28,2)="""","""",TEXT(INDEX(IMPORTRANGE(""12PgU-zwv8gBrFfxvJpoPIPcxUHWup-vsxMH3HWUigZ8"",""💸 Expenses!A5:J200""),28,2),""DD-MM-YYYY"")),"""")"),"") | C68: =IFERROR(__xludf.DUMMYFUNCTION("IFERROR(INDEX(IMPORTRANGE(""12PgU-zwv8gBrFfxvJpoPIPcxUHWup-vsxMH3HWUigZ8"",""💸 Expenses!A5:J200""),28,3),"""")"),"") | D68: =IFERROR(__xludf.DUMMYFUNCTION("IFERROR(INDEX(IMPORTRANGE(""12PgU-zwv8gBrFfxvJpoPIPcxUHWup-vsxMH3HWUigZ8"",""💸 Expenses!A5:J200""),28,4),"""")"),"") | E68: =IFERROR(__xludf.DUMMYFUNCTION("IFERROR(INDEX(IMPORTRANGE(""12PgU-zwv8gBrFfxvJpoPIPcxUHWup-vsxMH3HWUigZ8"",""💸 Expenses!A5:J200""),28,5),"""")"),"") | F68: =IFERROR(__xludf.DUMMYFUNCTION("IFERROR(IFERROR(INDEX(IMPORTRANGE(""12PgU-zwv8gBrFfxvJpoPIPcxUHWup-vsxMH3HWUigZ8"",""💸 Expenses!A5:J200""),28,6)*1,0),0)"),0.0) -> 0 | G68: =IFERROR(__xludf.DUMMYFUNCTION("IFERROR(INDEX(IMPORTRANGE(""12PgU-zwv8gBrFfxvJpoPIPcxUHWup-vsxMH3HWUigZ8"",""💸 Expenses!A5:J200""),28,7),"""")"),"") | H68: =IFERROR(__xludf.DUMMYFUNCTION("IFERROR(INDEX(IMPORTRANGE(""12PgU-zwv8gBrFfxvJpoPIPcxUHWup-vsxMH3HWUigZ8"",""💸 Expenses!A5:J200""),28,8),"""")"),"") | I68: =IFERROR(__xludf.DUMMYFUNCTION("IFERROR(INDEX(IMPORTRANGE(""12PgU-zwv8gBrFfxvJpoPIPcxUHWup-vsxMH3HWUigZ8"",""💸 Expenses!A5:J200""),28,9),"""")"),"") | J68: =IFERROR(__xludf.DUMMYFUNCTION("IFERROR(INDEX(IMPORTRANGE(""12PgU-zwv8gBrFfxvJpoPIPcxUHWup-vsxMH3HWUigZ8"",""💸 Expenses!A5:J200""),28,10),"""")"),"")
A69: =IFERROR(__xludf.DUMMYFUNCTION("IFERROR(INDEX(IMPORTRANGE(""12PgU-zwv8gBrFfxvJpoPIPcxUHWup-vsxMH3HWUigZ8"",""💸 Expenses!A5:J200""),29,1),"""")"),"") | B69: =IFERROR(__xludf.DUMMYFUNCTION("IFERROR(IF(INDEX(IMPORTRANGE(""12PgU-zwv8gBrFfxvJpoPIPcxUHWup-vsxMH3HWUigZ8"",""💸 Expenses!A5:J200""),29,2)="""","""",TEXT(INDEX(IMPORTRANGE(""12PgU-zwv8gBrFfxvJpoPIPcxUHWup-vsxMH3HWUigZ8"",""💸 Expenses!A5:J200""),29,2),""DD-MM-YYYY"")),"""")"),"") | C69: =IFERROR(__xludf.DUMMYFUNCTION("IFERROR(INDEX(IMPORTRANGE(""12PgU-zwv8gBrFfxvJpoPIPcxUHWup-vsxMH3HWUigZ8"",""💸 Expenses!A5:J200""),29,3),"""")"),"") | D69: =IFERROR(__xludf.DUMMYFUNCTION("IFERROR(INDEX(IMPORTRANGE(""12PgU-zwv8gBrFfxvJpoPIPcxUHWup-vsxMH3HWUigZ8"",""💸 Expenses!A5:J200""),29,4),"""")"),"") | E69: =IFERROR(__xludf.DUMMYFUNCTION("IFERROR(INDEX(IMPORTRANGE(""12PgU-zwv8gBrFfxvJpoPIPcxUHWup-vsxMH3HWUigZ8"",""💸 Expenses!A5:J200""),29,5),"""")"),"") | F69: =IFERROR(__xludf.DUMMYFUNCTION("IFERROR(IFERROR(INDEX(IMPORTRANGE(""12PgU-zwv8gBrFfxvJpoPIPcxUHWup-vsxMH3HWUigZ8"",""💸 Expenses!A5:J200""),29,6)*1,0),0)"),0.0) -> 0 | G69: =IFERROR(__xludf.DUMMYFUNCTION("IFERROR(INDEX(IMPORTRANGE(""12PgU-zwv8gBrFfxvJpoPIPcxUHWup-vsxMH3HWUigZ8"",""💸 Expenses!A5:J200""),29,7),"""")"),"") | H69: =IFERROR(__xludf.DUMMYFUNCTION("IFERROR(INDEX(IMPORTRANGE(""12PgU-zwv8gBrFfxvJpoPIPcxUHWup-vsxMH3HWUigZ8"",""💸 Expenses!A5:J200""),29,8),"""")"),"") | I69: =IFERROR(__xludf.DUMMYFUNCTION("IFERROR(INDEX(IMPORTRANGE(""12PgU-zwv8gBrFfxvJpoPIPcxUHWup-vsxMH3HWUigZ8"",""💸 Expenses!A5:J200""),29,9),"""")"),"") | J69: =IFERROR(__xludf.DUMMYFUNCTION("IFERROR(INDEX(IMPORTRANGE(""12PgU-zwv8gBrFfxvJpoPIPcxUHWup-vsxMH3HWUigZ8"",""💸 Expenses!A5:J200""),29,10),"""")"),"")
A70: =IFERROR(__xludf.DUMMYFUNCTION("IFERROR(INDEX(IMPORTRANGE(""12PgU-zwv8gBrFfxvJpoPIPcxUHWup-vsxMH3HWUigZ8"",""💸 Expenses!A5:J200""),30,1),"""")"),"") | B70: =IFERROR(__xludf.DUMMYFUNCTION("IFERROR(IF(INDEX(IMPORTRANGE(""12PgU-zwv8gBrFfxvJpoPIPcxUHWup-vsxMH3HWUigZ8"",""💸 Expenses!A5:J200""),30,2)="""","""",TEXT(INDEX(IMPORTRANGE(""12PgU-zwv8gBrFfxvJpoPIPcxUHWup-vsxMH3HWUigZ8"",""💸 Expenses!A5:J200""),30,2),""DD-MM-YYYY"")),"""")"),"") | C70: =IFERROR(__xludf.DUMMYFUNCTION("IFERROR(INDEX(IMPORTRANGE(""12PgU-zwv8gBrFfxvJpoPIPcxUHWup-vsxMH3HWUigZ8"",""💸 Expenses!A5:J200""),30,3),"""")"),"") | D70: =IFERROR(__xludf.DUMMYFUNCTION("IFERROR(INDEX(IMPORTRANGE(""12PgU-zwv8gBrFfxvJpoPIPcxUHWup-vsxMH3HWUigZ8"",""💸 Expenses!A5:J200""),30,4),"""")"),"") | E70: =IFERROR(__xludf.DUMMYFUNCTION("IFERROR(INDEX(IMPORTRANGE(""12PgU-zwv8gBrFfxvJpoPIPcxUHWup-vsxMH3HWUigZ8"",""💸 Expenses!A5:J200""),30,5),"""")"),"") | F70: =IFERROR(__xludf.DUMMYFUNCTION("IFERROR(IFERROR(INDEX(IMPORTRANGE(""12PgU-zwv8gBrFfxvJpoPIPcxUHWup-vsxMH3HWUigZ8"",""💸 Expenses!A5:J200""),30,6)*1,0),0)"),0.0) -> 0 | G70: =IFERROR(__xludf.DUMMYFUNCTION("IFERROR(INDEX(IMPORTRANGE(""12PgU-zwv8gBrFfxvJpoPIPcxUHWup-vsxMH3HWUigZ8"",""💸 Expenses!A5:J200""),30,7),"""")"),"") | H70: =IFERROR(__xludf.DUMMYFUNCTION("IFERROR(INDEX(IMPORTRANGE(""12PgU-zwv8gBrFfxvJpoPIPcxUHWup-vsxMH3HWUigZ8"",""💸 Expenses!A5:J200""),30,8),"""")"),"") | I70: =IFERROR(__xludf.DUMMYFUNCTION("IFERROR(INDEX(IMPORTRANGE(""12PgU-zwv8gBrFfxvJpoPIPcxUHWup-vsxMH3HWUigZ8"",""💸 Expenses!A5:J200""),30,9),"""")"),"") | J70: =IFERROR(__xludf.DUMMYFUNCTION("IFERROR(INDEX(IMPORTRANGE(""12PgU-zwv8gBrFfxvJpoPIPcxUHWup-vsxMH3HWUigZ8"",""💸 Expenses!A5:J200""),30,10),"""")"),"")
A71: TOTAL EXPENSES | F71: =SUMPRODUCT((A41:A70<>"")*F41:F70) -> 147622
A73: 💝 DONATION TYPE SUMMARY
A74: # | B74: Donation Type | D74: Pledged (₹) | E74: Received (₹) | F74: Pending (₹)
A75: 1 | B75: Aadi Festival | D75: =IFERROR(__xludf.DUMMYFUNCTION("IFERROR(INDEX(QUERY(IMPORTRANGE(""12PgU-zwv8gBrFfxvJpoPIPcxUHWup-vsxMH3HWUigZ8"",""💰 Donations!C4:M200""),""SELECT SUM(Col1) WHERE Col11='Aadi Festival' LABEL SUM(Col1) ''""),1),0)"),204603.0) -> 204603 | E75: =IFERROR(__xludf.DUMMYFUNCTION("IFERROR(INDEX(QUERY(IMPORTRANGE(""12PgU-zwv8gBrFfxvJpoPIPcxUHWup-vsxMH3HWUigZ8"",""💰 Donations!C4:M200""),""SELECT SUM(Col2) WHERE Col11='Aadi Festival' LABEL SUM(Col2) ''""),1),0)"),149603.0) -> 149603 | F75: =D75-E75 -> 55000
A76: 2 | B76: Temple Development | D76: =IFERROR(__xludf.DUMMYFUNCTION("IFERROR(INDEX(QUERY(IMPORTRANGE(""12PgU-zwv8gBrFfxvJpoPIPcxUHWup-vsxMH3HWUigZ8"",""💰 Donations!C4:M200""),""SELECT SUM(Col1) WHERE Col11='Temple Development' LABEL SUM(Col1) ''""),1),0)"),88500.0) -> 88500 | E76: =IFERROR(__xludf.DUMMYFUNCTION("IFERROR(INDEX(QUERY(IMPORTRANGE(""12PgU-zwv8gBrFfxvJpoPIPcxUHWup-vsxMH3HWUigZ8"",""💰 Donations!C4:M200""),""SELECT SUM(Col2) WHERE Col11='Temple Development' LABEL SUM(Col2) ''""),1),0)"),83500.0) -> 83500 | F76: =D76-E76 -> 5000
A77: 3 | B77: Birthday Pooja | D77: =IFERROR(__xludf.DUMMYFUNCTION("IFERROR(INDEX(QUERY(IMPORTRANGE(""12PgU-zwv8gBrFfxvJpoPIPcxUHWup-vsxMH3HWUigZ8"",""💰 Donations!C4:M200""),""SELECT SUM(Col1) WHERE Col11='Birthday Pooja' LABEL SUM(Col1) ''""),1),0)"),800.0) -> 800 | E77: =IFERROR(__xludf.DUMMYFUNCTION("IFERROR(INDEX(QUERY(IMPORTRANGE(""12PgU-zwv8gBrFfxvJpoPIPcxUHWup-vsxMH3HWUigZ8"",""💰 Donations!C4:M200""),""SELECT SUM(Col2) WHERE Col11='Birthday Pooja' LABEL SUM(Col2) ''""),1),0)"),800.0) -> 800 | F77: =D77-E77 -> 0
A78: 4 | B78: Anniversary Pooja | D78: =IFERROR(__xludf.DUMMYFUNCTION("IFERROR(INDEX(QUERY(IMPORTRANGE(""12PgU-zwv8gBrFfxvJpoPIPcxUHWup-vsxMH3HWUigZ8"",""💰 Donations!C4:M200""),""SELECT SUM(Col1) WHERE Col11='Anniversary Pooja' LABEL SUM(Col1) ''""),1),0)"),0.0) -> 0 | E78: =IFERROR(__xludf.DUMMYFUNCTION("IFERROR(INDEX(QUERY(IMPORTRANGE(""12PgU-zwv8gBrFfxvJpoPIPcxUHWup-vsxMH3HWUigZ8"",""💰 Donations!C4:M200""),""SELECT SUM(Col2) WHERE Col11='Anniversary Pooja' LABEL SUM(Col2) ''""),1),0)"),0.0) -> 0 | F78: =D78-E78 -> 0
A79: 5 | B79: Pournami Pooja | D79: =IFERROR(__xludf.DUMMYFUNCTION("IFERROR(INDEX(QUERY(IMPORTRANGE(""12PgU-zwv8gBrFfxvJpoPIPcxUHWup-vsxMH3HWUigZ8"",""💰 Donations!C4:M200""),""SELECT SUM(Col1) WHERE Col11='Pournami Pooja' LABEL SUM(Col1) ''""),1),0)"),0.0) -> 0 | E79: =IFERROR(__xludf.DUMMYFUNCTION("IFERROR(INDEX(QUERY(IMPORTRANGE(""12PgU-zwv8gBrFfxvJpoPIPcxUHWup-vsxMH3HWUigZ8"",""💰 Donations!C4:M200""),""SELECT SUM(Col2) WHERE Col11='Pournami Pooja' LABEL SUM(Col2) ''""),1),0)"),0.0) -> 0 | F79: =D79-E79 -> 0
A80: 6 | B80: Amavasai Pooja | D80: =IFERROR(__xludf.DUMMYFUNCTION("IFERROR(INDEX(QUERY(IMPORTRANGE(""12PgU-zwv8gBrFfxvJpoPIPcxUHWup-vsxMH3HWUigZ8"",""💰 Donations!C4:M200""),""SELECT SUM(Col1) WHERE Col11='Amavasai Pooja' LABEL SUM(Col1) ''""),1),0)"),0.0) -> 0 | E80: =IFERROR(__xludf.DUMMYFUNCTION("IFERROR(INDEX(QUERY(IMPORTRANGE(""12PgU-zwv8gBrFfxvJpoPIPcxUHWup-vsxMH3HWUigZ8"",""💰 Donations!C4:M200""),""SELECT SUM(Col2) WHERE Col11='Amavasai Pooja' LABEL SUM(Col2) ''""),1),0)"),0.0) -> 0 | F80: =D80-E80 -> 0
A81: 7 | B81: Weekly Pooja | D81: =IFERROR(__xludf.DUMMYFUNCTION("IFERROR(INDEX(QUERY(IMPORTRANGE(""12PgU-zwv8gBrFfxvJpoPIPcxUHWup-vsxMH3HWUigZ8"",""💰 Donations!C4:M200""),""SELECT SUM(Col1) WHERE Col11='Weekly Pooja' LABEL SUM(Col1) ''""),1),0)"),500.0) -> 500 | E81: =IFERROR(__xludf.DUMMYFUNCTION("IFERROR(INDEX(QUERY(IMPORTRANGE(""12PgU-zwv8gBrFfxvJpoPIPcxUHWup-vsxMH3HWUigZ8"",""💰 Donations!C4:M200""),""SELECT SUM(Col2) WHERE Col11='Weekly Pooja' LABEL SUM(Col2) ''""),1),0)"),500.0) -> 500 | F81: =D81-E81 -> 0
A82: 8 | B82: Others | D82: =IFERROR(__xludf.DUMMYFUNCTION("IFERROR(INDEX(QUERY(IMPORTRANGE(""12PgU-zwv8gBrFfxvJpoPIPcxUHWup-vsxMH3HWUigZ8"",""💰 Donations!C4:M200""),""SELECT SUM(Col1) WHERE Col11='Others' LABEL SUM(Col1) ''""),1),0)"),13400.0) -> 13400 | E82: =IFERROR(__xludf.DUMMYFUNCTION("IFERROR(INDEX(QUERY(IMPORTRANGE(""12PgU-zwv8gBrFfxvJpoPIPcxUHWup-vsxMH3HWUigZ8"",""💰 Donations!C4:M200""),""SELECT SUM(Col2) WHERE Col11='Others' LABEL SUM(Col2) ''""),1),0)"),13400.0) -> 13400 | F82: =D82-E82 -> 0
A83: TOTAL | D83: =SUM(D75:D82) -> 307803 | E83: =SUM(E75:E82) -> 247803 | F83: =D83-E83 -> 60000
A85: 🙏 DONOR LIST
A86: # | B86: Donor Name | D86: Pledged (₹) | E86: Received (₹) | F86: Balance (₹) | G86: Status | H86: Pay Mode | I86: Date Rcvd | J86: Received By | K86: Purpose / Notes | L86: Type | M86: Person Name | N86: Exp. Pay Date
A87: =IFERROR(__xludf.DUMMYFUNCTION("IFERROR(INDEX(IMPORTRANGE(""12PgU-zwv8gBrFfxvJpoPIPcxUHWup-vsxMH3HWUigZ8"",""💰 Donations!A4:N200""),1,1),"""")"),"2026/D/1") -> 2026/D/1 | B87: =IFERROR(__xludf.DUMMYFUNCTION("IFERROR(INDEX(IMPORTRANGE(""12PgU-zwv8gBrFfxvJpoPIPcxUHWup-vsxMH3HWUigZ8"",""💰 Donations!A4:N200""),1,2),"""")"),"S Shekar") -> S Shekar | D87: =IFERROR(__xludf.DUMMYFUNCTION("IFERROR(IFERROR(INDEX(IMPORTRANGE(""12PgU-zwv8gBrFfxvJpoPIPcxUHWup-vsxMH3HWUigZ8"",""💰 Donations!A4:N200""),1,3)*1,0),0)"),12000.0) -> 12000 | E87: =IFERROR(__xludf.DUMMYFUNCTION("IFERROR(IFERROR(INDEX(IMPORTRANGE(""12PgU-zwv8gBrFfxvJpoPIPcxUHWup-vsxMH3HWUigZ8"",""💰 Donations!A4:N200""),1,4)*1,0),0)"),0.0) -> 0 | F87: =IFERROR(D87-E87,0) -> 12000 | G87: =IF(A87="","",IF(OR(E87=0,E87=""),"Pending",IF(E87>=D87,"Received","Partially Received"))) -> Pending | H87: =IFERROR(__xludf.DUMMYFUNCTION("IFERROR(INDEX(IMPORTRANGE(""12PgU-zwv8gBrFfxvJpoPIPcxUHWup-vsxMH3HWUigZ8"",""💰 Donations!A4:N200""),1,6),"""")"),"") | I87: =IFERROR(__xludf.DUMMYFUNCTION("IFERROR(IF(INDEX(IMPORTRANGE(""12PgU-zwv8gBrFfxvJpoPIPcxUHWup-vsxMH3HWUigZ8"",""💰 Donations!A4:N200""),1,7)="""","""",TEXT(INDEX(IMPORTRANGE(""12PgU-zwv8gBrFfxvJpoPIPcxUHWup-vsxMH3HWUigZ8"",""💰 Donations!A4:N200""),1,7),""DD-MM-YYYY"")),"""")"),"") | J87: =IFERROR(__xludf.DUMMYFUNCTION("IFERROR(INDEX(IMPORTRANGE(""12PgU-zwv8gBrFfxvJpoPIPcxUHWup-vsxMH3HWUigZ8"",""💰 Donations!A4:N200""),1,8),"""")"),"") | K87: =IFERROR(__xludf.DUMMYFUNCTION("IFERROR(INDEX(IMPORTRANGE(""12PgU-zwv8gBrFfxvJpoPIPcxUHWup-vsxMH3HWUigZ8"",""💰 Donations!A4:N200""),1,11),"""")"),"Towards Iyer") -> Towards Iyer | L87: =IFERROR(__xludf.DUMMYFUNCTION("IFERROR(INDEX(IMPORTRANGE(""12PgU-zwv8gBrFfxvJpoPIPcxUHWup-vsxMH3HWUigZ8"",""💰 Donations!A4:N200""),1,13),"""")"),"Aadi Festival") -> Aadi Festival | M87: =IFERROR(__xludf.DUMMYFUNCTION("IFERROR(INDEX(IMPORTRANGE(""12PgU-zwv8gBrFfxvJpoPIPcxUHWup-vsxMH3HWUigZ8"",""💰 Donations!A4:N200""),1,14),"""")"),"") | N87: =IFERROR(__xludf.DUMMYFUNCTION("IFERROR(IF(INDEX(IMPORTRANGE(""12PgU-zwv8gBrFfxvJpoPIPcxUHWup-vsxMH3HWUigZ8"",""💰 Donations!A4:N200""),1,10)="""","""",TEXT(INDEX(IMPORTRANGE(""12PgU-zwv8gBrFfxvJpoPIPcxUHWup-vsxMH3HWUigZ8"",""💰 Donations!A4:N200""),1,10),""DD-MM-YYYY"")),"""")"),"10-08-2026") -> 10-08-2026
A88: =IFERROR(__xludf.DUMMYFUNCTION("IFERROR(INDEX(IMPORTRANGE(""12PgU-zwv8gBrFfxvJpoPIPcxUHWup-vsxMH3HWUigZ8"",""💰 Donations!A4:N200""),2,1),"""")"),"2026/D/2") -> 2026/D/2 | B88: =IFERROR(__xludf.DUMMYFUNCTION("IFERROR(INDEX(IMPORTRANGE(""12PgU-zwv8gBrFfxvJpoPIPcxUHWup-vsxMH3HWUigZ8"",""💰 Donations!A4:N200""),2,2),"""")"),"D Sunil Kumar") -> D Sunil Kumar | D88: =IFERROR(__xludf.DUMMYFUNCTION("IFERROR(IFERROR(INDEX(IMPORTRANGE(""12PgU-zwv8gBrFfxvJpoPIPcxUHWup-vsxMH3HWUigZ8"",""💰 Donations!A4:N200""),2,3)*1,0),0)"),10000.0) -> 10000 | E88: =IFERROR(__xludf.DUMMYFUNCTION("IFERROR(IFERROR(INDEX(IMPORTRANGE(""12PgU-zwv8gBrFfxvJpoPIPcxUHWup-vsxMH3HWUigZ8"",""💰 Donations!A4:N200""),2,4)*1,0),0)"),10000.0) -> 10000 | F88: =IFERROR(D88-E88,0) -> 0 | G88: =IF(A88="","",IF(OR(E88=0,E88=""),"Pending",IF(E88>=D88,"Received","Partially Received"))) -> Received | H88: =IFERROR(__xludf.DUMMYFUNCTION("IFERROR(INDEX(IMPORTRANGE(""12PgU-zwv8gBrFfxvJpoPIPcxUHWup-vsxMH3HWUigZ8"",""💰 Donations!A4:N200""),2,6),"""")"),"UPI") -> UPI | I88: =IFERROR(__xludf.DUMMYFUNCTION("IFERROR(IF(INDEX(IMPORTRANGE(""12PgU-zwv8gBrFfxvJpoPIPcxUHWup-vsxMH3HWUigZ8"",""💰 Donations!A4:N200""),2,7)="""","""",TEXT(INDEX(IMPORTRANGE(""12PgU-zwv8gBrFfxvJpoPIPcxUHWup-vsxMH3HWUigZ8"",""💰 Donations!A4:N200""),2,7),""DD-MM-YYYY"")),"""")"),"24-05-2026") -> 24-05-2026 | J88: =IFERROR(__xludf.DUMMYFUNCTION("IFERROR(INDEX(IMPORTRANGE(""12PgU-zwv8gBrFfxvJpoPIPcxUHWup-vsxMH3HWUigZ8"",""💰 Donations!A4:N200""),2,8),"""")"),"Sunil Kumar") -> Sunil Kumar | K88: =IFERROR(__xludf.DUMMYFUNCTION("IFERROR(INDEX(IMPORTRANGE(""12PgU-zwv8gBrFfxvJpoPIPcxUHWup-vsxMH3HWUigZ8"",""💰 Donations!A4:N200""),2,11),"""")"),"Pooja Items") -> Pooja Items | L88: =IFERROR(__xludf.DUMMYFUNCTION("IFERROR(INDEX(IMPORTRANGE(""12PgU-zwv8gBrFfxvJpoPIPcxUHWup-vsxMH3HWUigZ8"",""💰 Donations!A4:N200""),2,13),"""")"),"Aadi Festival") -> Aadi Festival | M88: =IFERROR(__xludf.DUMMYFUNCTION("IFERROR(INDEX(IMPORTRANGE(""12PgU-zwv8gBrFfxvJpoPIPcxUHWup-vsxMH3HWUigZ8"",""💰 Donations!A4:N200""),2,14),"""")"),"") | N88: =IFERROR(__xludf.DUMMYFUNCTION("IFERROR(IF(INDEX(IMPORTRANGE(""12PgU-zwv8gBrFfxvJpoPIPcxUHWup-vsxMH3HWUigZ8"",""💰 Donations!A4:N200""),2,10)="""","""",TEXT(INDEX(IMPORTRANGE(""12PgU-zwv8gBrFfxvJpoPIPcxUHWup-vsxMH3HWUigZ8"",""💰 Donations!A4:N200""),2,10),""DD-MM-YYYY"")),"""")"),"")
A89: =IFERROR(__xludf.DUMMYFUNCTION("IFERROR(INDEX(IMPORTRANGE(""12PgU-zwv8gBrFfxvJpoPIPcxUHWup-vsxMH3HWUigZ8"",""💰 Donations!A4:N200""),3,1),"""")"),"2026/D/3") -> 2026/D/3 | B89: =IFERROR(__xludf.DUMMYFUNCTION("IFERROR(INDEX(IMPORTRANGE(""12PgU-zwv8gBrFfxvJpoPIPcxUHWup-vsxMH3HWUigZ8"",""💰 Donations!A4:N200""),3,2),"""")"),"Suresh Velu") -> Suresh Velu | D89: =IFERROR(__xludf.DUMMYFUNCTION("IFERROR(IFERROR(INDEX(IMPORTRANGE(""12PgU-zwv8gBrFfxvJpoPIPcxUHWup-vsxMH3HWUigZ8"",""💰 Donations!A4:N200""),3,3)*1,0),0)"),13000.0) -> 13000 | E89: =IFERROR(__xludf.DUMMYFUNCTION("IFERROR(IFERROR(INDEX(IMPORTRANGE(""12PgU-zwv8gBrFfxvJpoPIPcxUHWup-vsxMH3HWUigZ8"",""💰 Donations!A4:N200""),3,4)*1,0),0)"),13000.0) -> 13000 | F89: =IFERROR(D89-E89,0) -> 0 | G89: =IF(A89="","",IF(OR(E89=0,E89=""),"Pending",IF(E89>=D89,"Received","Partially Received"))) -> Received | H89: =IFERROR(__xludf.DUMMYFUNCTION("IFERROR(INDEX(IMPORTRANGE(""12PgU-zwv8gBrFfxvJpoPIPcxUHWup-vsxMH3HWUigZ8"",""💰 Donations!A4:N200""),3,6),"""")"),"Cash") -> Cash | I89: =IFERROR(__xludf.DUMMYFUNCTION("IFERROR(IF(INDEX(IMPORTRANGE(""12PgU-zwv8gBrFfxvJpoPIPcxUHWup-vsxMH3HWUigZ8"",""💰 Donations!A4:N200""),3,7)="""","""",TEXT(INDEX(IMPORTRANGE(""12PgU-zwv8gBrFfxvJpoPIPcxUHWup-vsxMH3HWUigZ8"",""💰 Donations!A4:N200""),3,7),""DD-MM-YYYY"")),"""")"),"06-07-2026") -> 06-07-2026 | J89: =IFERROR(__xludf.DUMMYFUNCTION("IFERROR(INDEX(IMPORTRANGE(""12PgU-zwv8gBrFfxvJpoPIPcxUHWup-vsxMH3HWUigZ8"",""💰 Donations!A4:N200""),3,8),"""")"),"Suresh Velu") -> Suresh Velu | K89: =IFERROR(__xludf.DUMMYFUNCTION("IFERROR(INDEX(IMPORTRANGE(""12PgU-zwv8gBrFfxvJpoPIPcxUHWup-vsxMH3HWUigZ8"",""💰 Donations!A4:N200""),3,11),"""")"),"Chariot - Flowers & Flower Decoration and Crackers") -> Chariot - Flowers & Flower Decoration and Crackers | L89: =IFERROR(__xludf.DUMMYFUNCTION("IFERROR(INDEX(IMPORTRANGE(""12PgU-zwv8gBrFfxvJpoPIPcxUHWup-vsxMH3HWUigZ8"",""💰 Donations!A4:N200""),3,13),"""")"),"Aadi Festival") -> Aadi Festival | M89: =IFERROR(__xludf.DUMMYFUNCTION("IFERROR(INDEX(IMPORTRANGE(""12PgU-zwv8gBrFfxvJpoPIPcxUHWup-vsxMH3HWUigZ8"",""💰 Donations!A4:N200""),3,14),"""")"),"") | N89: =IFERROR(__xludf.DUMMYFUNCTION("IFERROR(IF(INDEX(IMPORTRANGE(""12PgU-zwv8gBrFfxvJpoPIPcxUHWup-vsxMH3HWUigZ8"",""💰 Donations!A4:N200""),3,10)="""","""",TEXT(INDEX(IMPORTRANGE(""12PgU-zwv8gBrFfxvJpoPIPcxUHWup-vsxMH3HWUigZ8"",""💰 Donations!A4:N200""),3,10),""DD-MM-YYYY"")),"""")"),"10-08-2026") -> 10-08-2026
A90: =IFERROR(__xludf.DUMMYFUNCTION("IFERROR(INDEX(IMPORTRANGE(""12PgU-zwv8gBrFfxvJpoPIPcxUHWup-vsxMH3HWUigZ8"",""💰 Donations!A4:N200""),4,1),"""")"),"2026/D/4") -> 2026/D/4 | B90: =IFERROR(__xludf.DUMMYFUNCTION("IFERROR(INDEX(IMPORTRANGE(""12PgU-zwv8gBrFfxvJpoPIPcxUHWup-vsxMH3HWUigZ8"",""💰 Donations!A4:N200""),4,2),"""")"),"Gayathri & Perumal ") -> Gayathri & Perumal | D90: =IFERROR(__xludf.DUMMYFUNCTION("IFERROR(IFERROR(INDEX(IMPORTRANGE(""12PgU-zwv8gBrFfxvJpoPIPcxUHWup-vsxMH3HWUigZ8"",""💰 Donations!A4:N200""),4,3)*1,0),0)"),7500.0) -> 7500 | E90: =IFERROR(__xludf.DUMMYFUNCTION("IFERROR(IFERROR(INDEX(IMPORTRANGE(""12PgU-zwv8gBrFfxvJpoPIPcxUHWup-vsxMH3HWUigZ8"",""💰 Donations!A4:N200""),4,4)*1,0),0)"),7500.0) -> 7500 | F90: =IFERROR(D90-E90,0) -> 0 | G90: =IF(A90="","",IF(OR(E90=0,E90=""),"Pending",IF(E90>=D90,"Received","Partially Received"))) -> Received | H90: =IFERROR(__xludf.DUMMYFUNCTION("IFERROR(INDEX(IMPORTRANGE(""12PgU-zwv8gBrFfxvJpoPIPcxUHWup-vsxMH3HWUigZ8"",""💰 Donations!A4:N200""),4,6),"""")"),"UPI") -> UPI | I90: =IFERROR(__xludf.DUMMYFUNCTION("IFERROR(IF(INDEX(IMPORTRANGE(""12PgU-zwv8gBrFfxvJpoPIPcxUHWup-vsxMH3HWUigZ8"",""💰 Donations!A4:N200""),4,7)="""","""",TEXT(INDEX(IMPORTRANGE(""12PgU-zwv8gBrFfxvJpoPIPcxUHWup-vsxMH3HWUigZ8"",""💰 Donations!A4:N200""),4,7),""DD-MM-YYYY"")),"""")"),"24-05-2026") -> 24-05-2026 | J90: =IFERROR(__xludf.DUMMYFUNCTION("IFERROR(INDEX(IMPORTRANGE(""12PgU-zwv8gBrFfxvJpoPIPcxUHWup-vsxMH3HWUigZ8"",""💰 Donations!A4:N200""),4,8),"""")"),"Sunil Kumar") -> Sunil Kumar | K90: =IFERROR(__xludf.DUMMYFUNCTION("IFERROR(INDEX(IMPORTRANGE(""12PgU-zwv8gBrFfxvJpoPIPcxUHWup-vsxMH3HWUigZ8"",""💰 Donations!A4:N200""),4,11),"""")"),"Decoration of Ponniamman & tempo charges for Procession") -> Decoration of Ponniamman & tempo charges for Procession | L90: =IFERROR(__xludf.DUMMYFUNCTION("IFERROR(INDEX(IMPORTRANGE(""12PgU-zwv8gBrFfxvJpoPIPcxUHWup-vsxMH3HWUigZ8"",""💰 Donations!A4:N200""),4,13),"""")"),"Aadi Festival") -> Aadi Festival | M90: =IFERROR(__xludf.DUMMYFUNCTION("IFERROR(INDEX(IMPORTRANGE(""12PgU-zwv8gBrFfxvJpoPIPcxUHWup-vsxMH3HWUigZ8"",""💰 Donations!A4:N200""),4,14),"""")"),"") | N90: =IFERROR(__xludf.DUMMYFUNCTION("IFERROR(IF(INDEX(IMPORTRANGE(""12PgU-zwv8gBrFfxvJpoPIPcxUHWup-vsxMH3HWUigZ8"",""💰 Donations!A4:N200""),4,10)="""","""",TEXT(INDEX(IMPORTRANGE(""12PgU-zwv8gBrFfxvJpoPIPcxUHWup-vsxMH3HWUigZ8"",""💰 Donations!A4:N200""),4,10),""DD-MM-YYYY"")),"""")"),"")
A91: =IFERROR(__xludf.DUMMYFUNCTION("IFERROR(INDEX(IMPORTRANGE(""12PgU-zwv8gBrFfxvJpoPIPcxUHWup-vsxMH3HWUigZ8"",""💰 Donations!A4:N200""),5,1),"""")"),"2026/D/5") -> 2026/D/5 | B91: =IFERROR(__xludf.DUMMYFUNCTION("IFERROR(INDEX(IMPORTRANGE(""12PgU-zwv8gBrFfxvJpoPIPcxUHWup-vsxMH3HWUigZ8"",""💰 Donations!A4:N200""),5,2),"""")"),"Manikandan & Nandini") -> Manikandan & Nandini | D91: =IFERROR(__xludf.DUMMYFUNCTION("IFERROR(IFERROR(INDEX(IMPORTRANGE(""12PgU-zwv8gBrFfxvJpoPIPcxUHWup-vsxMH3HWUigZ8"",""💰 Donations!A4:N200""),5,3)*1,0),0)"),40000.0) -> 40000 | E91: =IFERROR(__xludf.DUMMYFUNCTION("IFERROR(IFERROR(INDEX(IMPORTRANGE(""12PgU-zwv8gBrFfxvJpoPIPcxUHWup-vsxMH3HWUigZ8"",""💰 Donations!A4:N200""),5,4)*1,0),0)"),40000.0) -> 40000 | F91: =IFERROR(D91-E91,0) -> 0 | G91: =IF(A91="","",IF(OR(E91=0,E91=""),"Pending",IF(E91>=D91,"Received","Partially Received"))) -> Received | H91: =IFERROR(__xludf.DUMMYFUNCTION("IFERROR(INDEX(IMPORTRANGE(""12PgU-zwv8gBrFfxvJpoPIPcxUHWup-vsxMH3HWUigZ8"",""💰 Donations!A4:N200""),5,6),"""")"),"UPI") -> UPI | I91: =IFERROR(__xludf.DUMMYFUNCTION("IFERROR(IF(INDEX(IMPORTRANGE(""12PgU-zwv8gBrFfxvJpoPIPcxUHWup-vsxMH3HWUigZ8"",""💰 Donations!A4:N200""),5,7)="""","""",TEXT(INDEX(IMPORTRANGE(""12PgU-zwv8gBrFfxvJpoPIPcxUHWup-vsxMH3HWUigZ8"",""💰 Donations!A4:N200""),5,7),""DD-MM-YYYY"")),"""")"),"31-05-2026") -> 31-05-2026 | J91: =IFERROR(__xludf.DUMMYFUNCTION("IFERROR(INDEX(IMPORTRANGE(""12PgU-zwv8gBrFfxvJpoPIPcxUHWup-vsxMH3HWUigZ8"",""💰 Donations!A4:N200""),5,8),"""")"),"Sunil Kumar") -> Sunil Kumar | K91: =IFERROR(__xludf.DUMMYFUNCTION("IFERROR(INDEX(IMPORTRANGE(""12PgU-zwv8gBrFfxvJpoPIPcxUHWup-vsxMH3HWUigZ8"",""💰 Donations!A4:N200""),5,11),"""")"),"Food Expenses - Breakfast, Lunch, Dinner & 2 variety of Prasadam") -> Food Expenses - Breakfast, Lunch, Dinner & 2 variety of Prasadam | L91: =IFERROR(__xludf.DUMMYFUNCTION("IFERROR(INDEX(IMPORTRANGE(""12PgU-zwv8gBrFfxvJpoPIPcxUHWup-vsxMH3HWUigZ8"",""💰 Donations!A4:N200""),5,13),"""")"),"Aadi Festival") -> Aadi Festival | M91: =IFERROR(__xludf.DUMMYFUNCTION("IFERROR(INDEX(IMPORTRANGE(""12PgU-zwv8gBrFfxvJpoPIPcxUHWup-vsxMH3HWUigZ8"",""💰 Donations!A4:N200""),5,14),"""")"),"") | N91: =IFERROR(__xludf.DUMMYFUNCTION("IFERROR(IF(INDEX(IMPORTRANGE(""12PgU-zwv8gBrFfxvJpoPIPcxUHWup-vsxMH3HWUigZ8"",""💰 Donations!A4:N200""),5,10)="""","""",TEXT(INDEX(IMPORTRANGE(""12PgU-zwv8gBrFfxvJpoPIPcxUHWup-vsxMH3HWUigZ8"",""💰 Donations!A4:N200""),5,10),""DD-MM-YYYY"")),"""")"),"")
A92: =IFERROR(__xludf.DUMMYFUNCTION("IFERROR(INDEX(IMPORTRANGE(""12PgU-zwv8gBrFfxvJpoPIPcxUHWup-vsxMH3HWUigZ8"",""💰 Donations!A4:N200""),6,1),"""")"),"2026/D/6") -> 2026/D/6 | B92: =IFERROR(__xludf.DUMMYFUNCTION("IFERROR(INDEX(IMPORTRANGE(""12PgU-zwv8gBrFfxvJpoPIPcxUHWup-vsxMH3HWUigZ8"",""💰 Donations!A4:N200""),6,2),"""")"),"Srinivasan Nateshan") -> Srinivasan Nateshan | D92: =IFERROR(__xludf.DUMMYFUNCTION("IFERROR(IFERROR(INDEX(IMPORTRANGE(""12PgU-zwv8gBrFfxvJpoPIPcxUHWup-vsxMH3HWUigZ8"",""💰 Donations!A4:N200""),6,3)*1,0),0)"),6000.0) -> 6000 | E92: =IFERROR(__xludf.DUMMYFUNCTION("IFERROR(IFERROR(INDEX(IMPORTRANGE(""12PgU-zwv8gBrFfxvJpoPIPcxUHWup-vsxMH3HWUigZ8"",""💰 Donations!A4:N200""),6,4)*1,0),0)"),6000.0) -> 6000 | F92: =IFERROR(D92-E92,0) -> 0 | G92: =IF(A92="","",IF(OR(E92=0,E92=""),"Pending",IF(E92>=D92,"Received","Partially Received"))) -> Received | H92: =IFERROR(__xludf.DUMMYFUNCTION("IFERROR(INDEX(IMPORTRANGE(""12PgU-zwv8gBrFfxvJpoPIPcxUHWup-vsxMH3HWUigZ8"",""💰 Donations!A4:N200""),6,6),"""")"),"Cash") -> Cash | I92: =IFERROR(__xludf.DUMMYFUNCTION("IFERROR(IF(INDEX(IMPORTRANGE(""12PgU-zwv8gBrFfxvJpoPIPcxUHWup-vsxMH3HWUigZ8"",""💰 Donations!A4:N200""),6,7)="""","""",TEXT(INDEX(IMPORTRANGE(""12PgU-zwv8gBrFfxvJpoPIPcxUHWup-vsxMH3HWUigZ8"",""💰 Donations!A4:N200""),6,7),""DD-MM-YYYY"")),"""")"),"24-05-2026") -> 24-05-2026 | J92: =IFERROR(__xludf.DUMMYFUNCTION("IFERROR(INDEX(IMPORTRANGE(""12PgU-zwv8gBrFfxvJpoPIPcxUHWup-vsxMH3HWUigZ8"",""💰 Donations!A4:N200""),6,8),"""")"),"Sunil Kumar") -> Sunil Kumar | K92: =IFERROR(__xludf.DUMMYFUNCTION("IFERROR(INDEX(IMPORTRANGE(""12PgU-zwv8gBrFfxvJpoPIPcxUHWup-vsxMH3HWUigZ8"",""💰 Donations!A4:N200""),6,11),"""")"),"Photography") -> Photography | L92: =IFERROR(__xludf.DUMMYFUNCTION("IFERROR(INDEX(IMPORTRANGE(""12PgU-zwv8gBrFfxvJpoPIPcxUHWup-vsxMH3HWUigZ8"",""💰 Donations!A4:N200""),6,13),"""")"),"Aadi Festival") -> Aadi Festival | M92: =IFERROR(__xludf.DUMMYFUNCTION("IFERROR(INDEX(IMPORTRANGE(""12PgU-zwv8gBrFfxvJpoPIPcxUHWup-vsxMH3HWUigZ8"",""💰 Donations!A4:N200""),6,14),"""")"),"") | N92: =IFERROR(__xludf.DUMMYFUNCTION("IFERROR(IF(INDEX(IMPORTRANGE(""12PgU-zwv8gBrFfxvJpoPIPcxUHWup-vsxMH3HWUigZ8"",""💰 Donations!A4:N200""),6,10)="""","""",TEXT(INDEX(IMPORTRANGE(""12PgU-zwv8gBrFfxvJpoPIPcxUHWup-vsxMH3HWUigZ8"",""💰 Donations!A4:N200""),6,10),""DD-MM-YYYY"")),"""")"),"")
A93: =IFERROR(__xludf.DUMMYFUNCTION("IFERROR(INDEX(IMPORTRANGE(""12PgU-zwv8gBrFfxvJpoPIPcxUHWup-vsxMH3HWUigZ8"",""💰 Donations!A4:N200""),7,1),"""")"),"2026/D/7") -> 2026/D/7 | B93: =IFERROR(__xludf.DUMMYFUNCTION("IFERROR(INDEX(IMPORTRANGE(""12PgU-zwv8gBrFfxvJpoPIPcxUHWup-vsxMH3HWUigZ8"",""💰 Donations!A4:N200""),7,2),"""")"),"D Vasudevan") -> D Vasudevan | D93: =IFERROR(__xludf.DUMMYFUNCTION("IFERROR(IFERROR(INDEX(IMPORTRANGE(""12PgU-zwv8gBrFfxvJpoPIPcxUHWup-vsxMH3HWUigZ8"",""💰 Donations!A4:N200""),7,3)*1,0),0)"),7500.0) -> 7500 | E93: =IFERROR(__xludf.DUMMYFUNCTION("IFERROR(IFERROR(INDEX(IMPORTRANGE(""12PgU-zwv8gBrFfxvJpoPIPcxUHWup-vsxMH3HWUigZ8"",""💰 Donations!A4:N200""),7,4)*1,0),0)"),0.0) -> 0 | F93: =IFERROR(D93-E93,0) -> 7500 | G93: =IF(A93="","",IF(OR(E93=0,E93=""),"Pending",IF(E93>=D93,"Received","Partially Received"))) -> Pending | H93: =IFERROR(__xludf.DUMMYFUNCTION("IFERROR(INDEX(IMPORTRANGE(""12PgU-zwv8gBrFfxvJpoPIPcxUHWup-vsxMH3HWUigZ8"",""💰 Donations!A4:N200""),7,6),"""")"),"") | I93: =IFERROR(__xludf.DUMMYFUNCTION("IFERROR(IF(INDEX(IMPORTRANGE(""12PgU-zwv8gBrFfxvJpoPIPcxUHWup-vsxMH3HWUigZ8"",""💰 Donations!A4:N200""),7,7)="""","""",TEXT(INDEX(IMPORTRANGE(""12PgU-zwv8gBrFfxvJpoPIPcxUHWup-vsxMH3HWUigZ8"",""💰 Donations!A4:N200""),7,7),""DD-MM-YYYY"")),"""")"),"") | J93: =IFERROR(__xludf.DUMMYFUNCTION("IFERROR(INDEX(IMPORTRANGE(""12PgU-zwv8gBrFfxvJpoPIPcxUHWup-vsxMH3HWUigZ8"",""💰 Donations!A4:N200""),7,8),"""")"),"") | K93: =IFERROR(__xludf.DUMMYFUNCTION("IFERROR(INDEX(IMPORTRANGE(""12PgU-zwv8gBrFfxvJpoPIPcxUHWup-vsxMH3HWUigZ8"",""💰 Donations!A4:N200""),7,11),"""")"),"Nadaeswaram") -> Nadaeswaram | L93: =IFERROR(__xludf.DUMMYFUNCTION("IFERROR(INDEX(IMPORTRANGE(""12PgU-zwv8gBrFfxvJpoPIPcxUHWup-vsxMH3HWUigZ8"",""💰 Donations!A4:N200""),7,13),"""")"),"Aadi Festival") -> Aadi Festival | M93: =IFERROR(__xludf.DUMMYFUNCTION("IFERROR(INDEX(IMPORTRANGE(""12PgU-zwv8gBrFfxvJpoPIPcxUHWup-vsxMH3HWUigZ8"",""💰 Donations!A4:N200""),7,14),"""")"),"") | N93: =IFERROR(__xludf.DUMMYFUNCTION("IFERROR(IF(INDEX(IMPORTRANGE(""12PgU-zwv8gBrFfxvJpoPIPcxUHWup-vsxMH3HWUigZ8"",""💰 Donations!A4:N200""),7,10)="""","""",TEXT(INDEX(IMPORTRANGE(""12PgU-zwv8gBrFfxvJpoPIPcxUHWup-vsxMH3HWUigZ8"",""💰 Donations!A4:N200""),7,10),""DD-MM-YYYY"")),"""")"),"10-08-2026") -> 10-08-2026
A94: =IFERROR(__xludf.DUMMYFUNCTION("IFERROR(INDEX(IMPORTRANGE(""12PgU-zwv8gBrFfxvJpoPIPcxUHWup-vsxMH3HWUigZ8"",""💰 Donations!A4:N200""),8,1),"""")"),"2026/D/8") -> 2026/D/8 | B94: =IFERROR(__xludf.DUMMYFUNCTION("IFERROR(INDEX(IMPORTRANGE(""12PgU-zwv8gBrFfxvJpoPIPcxUHWup-vsxMH3HWUigZ8"",""💰 Donations!A4:N200""),8,2),"""")"),"PRL Srinivasan ") -> PRL Srinivasan | D94: =IFERROR(__xludf.DUMMYFUNCTION("IFERROR(IFERROR(INDEX(IMPORTRANGE(""12PgU-zwv8gBrFfxvJpoPIPcxUHWup-vsxMH3HWUigZ8"",""💰 Donations!A4:N200""),8,3)*1,0),0)"),5500.0) -> 5500 | E94: =IFERROR(__xludf.DUMMYFUNCTION("IFERROR(IFERROR(INDEX(IMPORTRANGE(""12PgU-zwv8gBrFfxvJpoPIPcxUHWup-vsxMH3HWUigZ8"",""💰 Donations!A4:N200""),8,4)*1,0),0)"),0.0) -> 0 | F94: =IFERROR(D94-E94,0) -> 5500 | G94: =IF(A94="","",IF(OR(E94=0,E94=""),"Pending",IF(E94>=D94,"Received","Partially Received"))) -> Pending | H94: =IFERROR(__xludf.DUMMYFUNCTION("IFERROR(INDEX(IMPORTRANGE(""12PgU-zwv8gBrFfxvJpoPIPcxUHWup-vsxMH3HWUigZ8"",""💰 Donations!A4:N200""),8,6),"""")"),"") | I94: =IFERROR(__xludf.DUMMYFUNCTION("IFERROR(IF(INDEX(IMPORTRANGE(""12PgU-zwv8gBrFfxvJpoPIPcxUHWup-vsxMH3HWUigZ8"",""💰 Donations!A4:N200""),8,7)="""","""",TEXT(INDEX(IMPORTRANGE(""12PgU-zwv8gBrFfxvJpoPIPcxUHWup-vsxMH3HWUigZ8"",""💰 Donations!A4:N200""),8,7),""DD-MM-YYYY"")),"""")"),"") | J94: =IFERROR(__xludf.DUMMYFUNCTION("IFERROR(INDEX(IMPORTRANGE(""12PgU-zwv8gBrFfxvJpoPIPcxUHWup-vsxMH3HWUigZ8"",""💰 Donations!A4:N200""),8,8),"""")"),"") | K94: =IFERROR(__xludf.DUMMYFUNCTION("IFERROR(INDEX(IMPORTRANGE(""12PgU-zwv8gBrFfxvJpoPIPcxUHWup-vsxMH3HWUigZ8"",""💰 Donations!A4:N200""),8,11),"""")")," Electrical Lighting & Generator, Mic & Sound system") -> Electrical Lighting & Generator, Mic & Sound system | L94: =IFERROR(__xludf.DUMMYFUNCTION("IFERROR(INDEX(IMPORTRANGE(""12PgU-zwv8gBrFfxvJpoPIPcxUHWup-vsxMH3HWUigZ8"",""💰 Donations!A4:N200""),8,13),"""")"),"Aadi Festival") -> Aadi Festival | M94: =IFERROR(__xludf.DUMMYFUNCTION("IFERROR(INDEX(IMPORTRANGE(""12PgU-zwv8gBrFfxvJpoPIPcxUHWup-vsxMH3HWUigZ8"",""💰 Donations!A4:N200""),8,14),"""")"),"") | N94: =IFERROR(__xludf.DUMMYFUNCTION("IFERROR(IF(INDEX(IMPORTRANGE(""12PgU-zwv8gBrFfxvJpoPIPcxUHWup-vsxMH3HWUigZ8"",""💰 Donations!A4:N200""),8,10)="""","""",TEXT(INDEX(IMPORTRANGE(""12PgU-zwv8gBrFfxvJpoPIPcxUHWup-vsxMH3HWUigZ8"",""💰 Donations!A4:N200""),8,10),""DD-MM-YYYY"")),"""")"),"10-08-2026") -> 10-08-2026
A95: =IFERROR(__xludf.DUMMYFUNCTION("IFERROR(INDEX(IMPORTRANGE(""12PgU-zwv8gBrFfxvJpoPIPcxUHWup-vsxMH3HWUigZ8"",""💰 Donations!A4:N200""),9,1),"""")"),"2026/D/9") -> 2026/D/9 | B95: =IFERROR(__xludf.DUMMYFUNCTION("IFERROR(INDEX(IMPORTRANGE(""12PgU-zwv8gBrFfxvJpoPIPcxUHWup-vsxMH3HWUigZ8"",""💰 Donations!A4:N200""),9,2),"""")"),"R. Rukumagadhan") -> R. Rukumagadhan | D95: =IFERROR(__xludf.DUMMYFUNCTION("IFERROR(IFERROR(INDEX(IMPORTRANGE(""12PgU-zwv8gBrFfxvJpoPIPcxUHWup-vsxMH3HWUigZ8"",""💰 Donations!A4:N200""),9,3)*1,0),0)"),5500.0) -> 5500 | E95: =IFERROR(__xludf.DUMMYFUNCTION("IFERROR(IFERROR(INDEX(IMPORTRANGE(""12PgU-zwv8gBrFfxvJpoPIPcxUHWup-vsxMH3HWUigZ8"",""💰 Donations!A4:N200""),9,4)*1,0),0)"),0.0) -> 0 | F95: =IFERROR(D95-E95,0) -> 5500 | G95: =IF(A95="","",IF(OR(E95=0,E95=""),"Pending",IF(E95>=D95,"Received","Partially Received"))) -> Pending | H95: =IFERROR(__xludf.DUMMYFUNCTION("IFERROR(INDEX(IMPORTRANGE(""12PgU-zwv8gBrFfxvJpoPIPcxUHWup-vsxMH3HWUigZ8"",""💰 Donations!A4:N200""),9,6),"""")"),"") | I95: =IFERROR(__xludf.DUMMYFUNCTION("IFERROR(IF(INDEX(IMPORTRANGE(""12PgU-zwv8gBrFfxvJpoPIPcxUHWup-vsxMH3HWUigZ8"",""💰 Donations!A4:N200""),9,7)="""","""",TEXT(INDEX(IMPORTRANGE(""12PgU-zwv8gBrFfxvJpoPIPcxUHWup-vsxMH3HWUigZ8"",""💰 Donations!A4:N200""),9,7),""DD-MM-YYYY"")),"""")"),"") | J95: =IFERROR(__xludf.DUMMYFUNCTION("IFERROR(INDEX(IMPORTRANGE(""12PgU-zwv8gBrFfxvJpoPIPcxUHWup-vsxMH3HWUigZ8"",""💰 Donations!A4:N200""),9,8),"""")"),"") | K95: =IFERROR(__xludf.DUMMYFUNCTION("IFERROR(INDEX(IMPORTRANGE(""12PgU-zwv8gBrFfxvJpoPIPcxUHWup-vsxMH3HWUigZ8"",""💰 Donations!A4:N200""),9,11),"""")")," Electrical Lighting & Generator, Mic & Sound system") -> Electrical Lighting & Generator, Mic & Sound system | L95: =IFERROR(__xludf.DUMMYFUNCTION("IFERROR(INDEX(IMPORTRANGE(""12PgU-zwv8gBrFfxvJpoPIPcxUHWup-vsxMH3HWUigZ8"",""💰 Donations!A4:N200""),9,13),"""")"),"Aadi Festival") -> Aadi Festival | M95: =IFERROR(__xludf.DUMMYFUNCTION("IFERROR(INDEX(IMPORTRANGE(""12PgU-zwv8gBrFfxvJpoPIPcxUHWup-vsxMH3HWUigZ8"",""💰 Donations!A4:N200""),9,14),"""")"),"") | N95: =IFERROR(__xludf.DUMMYFUNCTION("IFERROR(IF(INDEX(IMPORTRANGE(""12PgU-zwv8gBrFfxvJpoPIPcxUHWup-vsxMH3HWUigZ8"",""💰 Donations!A4:N200""),9,10)="""","""",TEXT(INDEX(IMPORTRANGE(""12PgU-zwv8gBrFfxvJpoPIPcxUHWup-vsxMH3HWUigZ8"",""💰 Donations!A4:N200""),9,10),""DD-MM-YYYY"")),"""")"),"10-08-2026") -> 10-08-2026
A96: =IFERROR(__xludf.DUMMYFUNCTION("IFERROR(INDEX(IMPORTRANGE(""12PgU-zwv8gBrFfxvJpoPIPcxUHWup-vsxMH3HWUigZ8"",""💰 Donations!A4:N200""),10,1),"""")"),"2026/D/10") -> 2026/D/10 | B96: =IFERROR(__xludf.DUMMYFUNCTION("IFERROR(INDEX(IMPORTRANGE(""12PgU-zwv8gBrFfxvJpoPIPcxUHWup-vsxMH3HWUigZ8"",""💰 Donations!A4:N200""),10,2),"""")"),"Srinivasan V") -> Srinivasan V | D96: =IFERROR(__xludf.DUMMYFUNCTION("IFERROR(IFERROR(INDEX(IMPORTRANGE(""12PgU-zwv8gBrFfxvJpoPIPcxUHWup-vsxMH3HWUigZ8"",""💰 Donations!A4:N200""),10,3)*1,0),0)"),5500.0) -> 5500 | E96: =IFERROR(__xludf.DUMMYFUNCTION("IFERROR(IFERROR(INDEX(IMPORTRANGE(""12PgU-zwv8gBrFfxvJpoPIPcxUHWup-vsxMH3HWUigZ8"",""💰 Donations!A4:N200""),10,4)*1,0),0)"),0.0) -> 0 | F96: =IFERROR(D96-E96,0) -> 5500 | G96: =IF(A96="","",IF(OR(E96=0,E96=""),"Pending",IF(E96>=D96,"Received","Partially Received"))) -> Pending | H96: =IFERROR(__xludf.DUMMYFUNCTION("IFERROR(INDEX(IMPORTRANGE(""12PgU-zwv8gBrFfxvJpoPIPcxUHWup-vsxMH3HWUigZ8"",""💰 Donations!A4:N200""),10,6),"""")"),"") | I96: =IFERROR(__xludf.DUMMYFUNCTION("IFERROR(IF(INDEX(IMPORTRANGE(""12PgU-zwv8gBrFfxvJpoPIPcxUHWup-vsxMH3HWUigZ8"",""💰 Donations!A4:N200""),10,7)="""","""",TEXT(INDEX(IMPORTRANGE(""12PgU-zwv8gBrFfxvJpoPIPcxUHWup-vsxMH3HWUigZ8"",""💰 Donations!A4:N200""),10,7),""DD-MM-YYYY"")),"""")"),"") | J96: =IFERROR(__xludf.DUMMYFUNCTION("IFERROR(INDEX(IMPORTRANGE(""12PgU-zwv8gBrFfxvJpoPIPcxUHWup-vsxMH3HWUigZ8"",""💰 Donations!A4:N200""),10,8),"""")"),"") | K96: =IFERROR(__xludf.DUMMYFUNCTION("IFERROR(INDEX(IMPORTRANGE(""12PgU-zwv8gBrFfxvJpoPIPcxUHWup-vsxMH3HWUigZ8"",""💰 Donations!A4:N200""),10,11),"""")"),"Shamiana, Table, Chairs & Vessels") -> Shamiana, Table, Chairs & Vessels | L96: =IFERROR(__xludf.DUMMYFUNCTION("IFERROR(INDEX(IMPORTRANGE(""12PgU-zwv8gBrFfxvJpoPIPcxUHWup-vsxMH3HWUigZ8"",""💰 Donations!A4:N200""),10,13),"""")"),"Aadi Festival") -> Aadi Festival | M96: =IFERROR(__xludf.DUMMYFUNCTION("IFERROR(INDEX(IMPORTRANGE(""12PgU-zwv8gBrFfxvJpoPIPcxUHWup-vsxMH3HWUigZ8"",""💰 Donations!A4:N200""),10,14),"""")"),"") | N96: =IFERROR(__xludf.DUMMYFUNCTION("IFERROR(IF(INDEX(IMPORTRANGE(""12PgU-zwv8gBrFfxvJpoPIPcxUHWup-vsxMH3HWUigZ8"",""💰 Donations!A4:N200""),10,10)="""","""",TEXT(INDEX(IMPORTRANGE(""12PgU-zwv8gBrFfxvJpoPIPcxUHWup-vsxMH3HWUigZ8"",""💰 Donations!A4:N200""),10,10),""DD-MM-YYYY"")),"""")"),"10-08-2026") -> 10-08-2026
A97: =IFERROR(__xludf.DUMMYFUNCTION("IFERROR(INDEX(IMPORTRANGE(""12PgU-zwv8gBrFfxvJpoPIPcxUHWup-vsxMH3HWUigZ8"",""💰 Donations!A4:N200""),11,1),"""")"),"2026/D/11") -> 2026/D/11 | B97: =IFERROR(__xludf.DUMMYFUNCTION("IFERROR(INDEX(IMPORTRANGE(""12PgU-zwv8gBrFfxvJpoPIPcxUHWup-vsxMH3HWUigZ8"",""💰 Donations!A4:N200""),11,2),"""")"),"Nateshan Andal") -> Nateshan Andal | D97: =IFERROR(__xludf.DUMMYFUNCTION("IFERROR(IFERROR(INDEX(IMPORTRANGE(""12PgU-zwv8gBrFfxvJpoPIPcxUHWup-vsxMH3HWUigZ8"",""💰 Donations!A4:N200""),11,3)*1,0),0)"),1000.0) -> 1000 | E97: =IFERROR(__xludf.DUMMYFUNCTION("IFERROR(IFERROR(INDEX(IMPORTRANGE(""12PgU-zwv8gBrFfxvJpoPIPcxUHWup-vsxMH3HWUigZ8"",""💰 Donations!A4:N200""),11,4)*1,0),0)"),1000.0) -> 1000 | F97: =IFERROR(D97-E97,0) -> 0 | G97: =IF(A97="","",IF(OR(E97=0,E97=""),"Pending",IF(E97>=D97,"Received","Partially Received"))) -> Received | H97: =IFERROR(__xludf.DUMMYFUNCTION("IFERROR(INDEX(IMPORTRANGE(""12PgU-zwv8gBrFfxvJpoPIPcxUHWup-vsxMH3HWUigZ8"",""💰 Donations!A4:N200""),11,6),"""")"),"UPI") -> UPI | I97: =IFERROR(__xludf.DUMMYFUNCTION("IFERROR(IF(INDEX(IMPORTRANGE(""12PgU-zwv8gBrFfxvJpoPIPcxUHWup-vsxMH3HWUigZ8"",""💰 Donations!A4:N200""),11,7)="""","""",TEXT(INDEX(IMPORTRANGE(""12PgU-zwv8gBrFfxvJpoPIPcxUHWup-vsxMH3HWUigZ8"",""💰 Donations!A4:N200""),11,7),""DD-MM-YYYY"")),"""")"),"24-05-2026") -> 24-05-2026 | J97: =IFERROR(__xludf.DUMMYFUNCTION("IFERROR(INDEX(IMPORTRANGE(""12PgU-zwv8gBrFfxvJpoPIPcxUHWup-vsxMH3HWUigZ8"",""💰 Donations!A4:N200""),11,8),"""")"),"Sunil Kumar") -> Sunil Kumar | K97: =IFERROR(__xludf.DUMMYFUNCTION("IFERROR(INDEX(IMPORTRANGE(""12PgU-zwv8gBrFfxvJpoPIPcxUHWup-vsxMH3HWUigZ8"",""💰 Donations!A4:N200""),11,11),"""")"),"Plantian Leaf 2 Nos.") -> Plantian Leaf 2 Nos. | L97: =IFERROR(__xludf.DUMMYFUNCTION("IFERROR(INDEX(IMPORTRANGE(""12PgU-zwv8gBrFfxvJpoPIPcxUHWup-vsxMH3HWUigZ8"",""💰 Donations!A4:N200""),11,13),"""")"),"Aadi Festival") -> Aadi Festival | M97: =IFERROR(__xludf.DUMMYFUNCTION("IFERROR(INDEX(IMPORTRANGE(""12PgU-zwv8gBrFfxvJpoPIPcxUHWup-vsxMH3HWUigZ8"",""💰 Donations!A4:N200""),11,14),"""")"),"") | N97: =IFERROR(__xludf.DUMMYFUNCTION("IFERROR(IF(INDEX(IMPORTRANGE(""12PgU-zwv8gBrFfxvJpoPIPcxUHWup-vsxMH3HWUigZ8"",""💰 Donations!A4:N200""),11,10)="""","""",TEXT(INDEX(IMPORTRANGE(""12PgU-zwv8gBrFfxvJpoPIPcxUHWup-vsxMH3HWUigZ8"",""💰 Donations!A4:N200""),11,10),""DD-MM-YYYY"")),"""")"),"")
A98: =IFERROR(__xludf.DUMMYFUNCTION("IFERROR(INDEX(IMPORTRANGE(""12PgU-zwv8gBrFfxvJpoPIPcxUHWup-vsxMH3HWUigZ8"",""💰 Donations!A4:N200""),12,1),"""")"),"2026/D/12") -> 2026/D/12 | B98: =IFERROR(__xludf.DUMMYFUNCTION("IFERROR(INDEX(IMPORTRANGE(""12PgU-zwv8gBrFfxvJpoPIPcxUHWup-vsxMH3HWUigZ8"",""💰 Donations!A4:N200""),12,2),"""")"),"Mohan Aishwarya") -> Mohan Aishwarya | D98: =IFERROR(__xludf.DUMMYFUNCTION("IFERROR(IFERROR(INDEX(IMPORTRANGE(""12PgU-zwv8gBrFfxvJpoPIPcxUHWup-vsxMH3HWUigZ8"",""💰 Donations!A4:N200""),12,3)*1,0),0)"),1000.0) -> 1000 | E98: =IFERROR(__xludf.DUMMYFUNCTION("IFERROR(IFERROR(INDEX(IMPORTRANGE(""12PgU-zwv8gBrFfxvJpoPIPcxUHWup-vsxMH3HWUigZ8"",""💰 Donations!A4:N200""),12,4)*1,0),0)"),1000.0) -> 1000 | F98: =IFERROR(D98-E98,0) -> 0 | G98: =IF(A98="","",IF(OR(E98=0,E98=""),"Pending",IF(E98>=D98,"Received","Partially Received"))) -> Received | H98: =IFERROR(__xludf.DUMMYFUNCTION("IFERROR(INDEX(IMPORTRANGE(""12PgU-zwv8gBrFfxvJpoPIPcxUHWup-vsxMH3HWUigZ8"",""💰 Donations!A4:N200""),12,6),"""")"),"UPI") -> UPI | I98: =IFERROR(__xludf.DUMMYFUNCTION("IFERROR(IF(INDEX(IMPORTRANGE(""12PgU-zwv8gBrFfxvJpoPIPcxUHWup-vsxMH3HWUigZ8"",""💰 Donations!A4:N200""),12,7)="""","""",TEXT(INDEX(IMPORTRANGE(""12PgU-zwv8gBrFfxvJpoPIPcxUHWup-vsxMH3HWUigZ8"",""💰 Donations!A4:N200""),12,7),""DD-MM-YYYY"")),"""")"),"24-05-2026") -> 24-05-2026 | J98: =IFERROR(__xludf.DUMMYFUNCTION("IFERROR(INDEX(IMPORTRANGE(""12PgU-zwv8gBrFfxvJpoPIPcxUHWup-vsxMH3HWUigZ8"",""💰 Donations!A4:N200""),12,8),"""")"),"Sunil Kumar") -> Sunil Kumar | K98: =IFERROR(__xludf.DUMMYFUNCTION("IFERROR(INDEX(IMPORTRANGE(""12PgU-zwv8gBrFfxvJpoPIPcxUHWup-vsxMH3HWUigZ8"",""💰 Donations!A4:N200""),12,11),"""")"),"Supply of water") -> Supply of water | L98: =IFERROR(__xludf.DUMMYFUNCTION("IFERROR(INDEX(IMPORTRANGE(""12PgU-zwv8gBrFfxvJpoPIPcxUHWup-vsxMH3HWUigZ8"",""💰 Donations!A4:N200""),12,13),"""")"),"Aadi Festival") -> Aadi Festival | M98: =IFERROR(__xludf.DUMMYFUNCTION("IFERROR(INDEX(IMPORTRANGE(""12PgU-zwv8gBrFfxvJpoPIPcxUHWup-vsxMH3HWUigZ8"",""💰 Donations!A4:N200""),12,14),"""")"),"") | N98: =IFERROR(__xludf.DUMMYFUNCTION("IFERROR(IF(INDEX(IMPORTRANGE(""12PgU-zwv8gBrFfxvJpoPIPcxUHWup-vsxMH3HWUigZ8"",""💰 Donations!A4:N200""),12,10)="""","""",TEXT(INDEX(IMPORTRANGE(""12PgU-zwv8gBrFfxvJpoPIPcxUHWup-vsxMH3HWUigZ8"",""💰 Donations!A4:N200""),12,10),""DD-MM-YYYY"")),"""")"),"")
A99: =IFERROR(__xludf.DUMMYFUNCTION("IFERROR(INDEX(IMPORTRANGE(""12PgU-zwv8gBrFfxvJpoPIPcxUHWup-vsxMH3HWUigZ8"",""💰 Donations!A4:N200""),13,1),"""")"),"2026/D/13") -> 2026/D/13 | B99: =IFERROR(__xludf.DUMMYFUNCTION("IFERROR(INDEX(IMPORTRANGE(""12PgU-zwv8gBrFfxvJpoPIPcxUHWup-vsxMH3HWUigZ8"",""💰 Donations!A4:N200""),13,2),"""")"),"Uday Kumar D") -> Uday Kumar D | D99: =IFERROR(__xludf.DUMMYFUNCTION("IFERROR(IFERROR(INDEX(IMPORTRANGE(""12PgU-zwv8gBrFfxvJpoPIPcxUHWup-vsxMH3HWUigZ8"",""💰 Donations!A4:N200""),13,3)*1,0),0)"),3000.0) -> 3000 | E99: =IFERROR(__xludf.DUMMYFUNCTION("IFERROR(IFERROR(INDEX(IMPORTRANGE(""12PgU-zwv8gBrFfxvJpoPIPcxUHWup-vsxMH3HWUigZ8"",""💰 Donations!A4:N200""),13,4)*1,0),0)"),3000.0) -> 3000 | F99: =IFERROR(D99-E99,0) -> 0 | G99: =IF(A99="","",IF(OR(E99=0,E99=""),"Pending",IF(E99>=D99,"Received","Partially Received"))) -> Received | H99: =IFERROR(__xludf.DUMMYFUNCTION("IFERROR(INDEX(IMPORTRANGE(""12PgU-zwv8gBrFfxvJpoPIPcxUHWup-vsxMH3HWUigZ8"",""💰 Donations!A4:N200""),13,6),"""")"),"UPI") -> UPI | I99: =IFERROR(__xludf.DUMMYFUNCTION("IFERROR(IF(INDEX(IMPORTRANGE(""12PgU-zwv8gBrFfxvJpoPIPcxUHWup-vsxMH3HWUigZ8"",""💰 Donations!A4:N200""),13,7)="""","""",TEXT(INDEX(IMPORTRANGE(""12PgU-zwv8gBrFfxvJpoPIPcxUHWup-vsxMH3HWUigZ8"",""💰 Donations!A4:N200""),13,7),""DD-MM-YYYY"")),"""")"),"24-05-2026") -> 24-05-2026 | J99: =IFERROR(__xludf.DUMMYFUNCTION("IFERROR(INDEX(IMPORTRANGE(""12PgU-zwv8gBrFfxvJpoPIPcxUHWup-vsxMH3HWUigZ8"",""💰 Donations!A4:N200""),13,8),"""")"),"Sunil Kumar") -> Sunil Kumar | K99: =IFERROR(__xludf.DUMMYFUNCTION("IFERROR(INDEX(IMPORTRANGE(""12PgU-zwv8gBrFfxvJpoPIPcxUHWup-vsxMH3HWUigZ8"",""💰 Donations!A4:N200""),13,11),"""")"),"Plate/cups Roll etc.") -> Plate/cups Roll etc. | L99: =IFERROR(__xludf.DUMMYFUNCTION("IFERROR(INDEX(IMPORTRANGE(""12PgU-zwv8gBrFfxvJpoPIPcxUHWup-vsxMH3HWUigZ8"",""💰 Donations!A4:N200""),13,13),"""")"),"Aadi Festival") -> Aadi Festival | M99: =IFERROR(__xludf.DUMMYFUNCTION("IFERROR(INDEX(IMPORTRANGE(""12PgU-zwv8gBrFfxvJpoPIPcxUHWup-vsxMH3HWUigZ8"",""💰 Donations!A4:N200""),13,14),"""")"),"") | N99: =IFERROR(__xludf.DUMMYFUNCTION("IFERROR(IF(INDEX(IMPORTRANGE(""12PgU-zwv8gBrFfxvJpoPIPcxUHWup-vsxMH3HWUigZ8"",""💰 Donations!A4:N200""),13,10)="""","""",TEXT(INDEX(IMPORTRANGE(""12PgU-zwv8gBrFfxvJpoPIPcxUHWup-vsxMH3HWUigZ8"",""💰 Donations!A4:N200""),13,10),""DD-MM-YYYY"")),"""")"),"")
A100: =IFERROR(__xludf.DUMMYFUNCTION("IFERROR(INDEX(IMPORTRANGE(""12PgU-zwv8gBrFfxvJpoPIPcxUHWup-vsxMH3HWUigZ8"",""💰 Donations!A4:N200""),14,1),"""")"),"2026/D/14") -> 2026/D/14 | B100: =IFERROR(__xludf.DUMMYFUNCTION("IFERROR(INDEX(IMPORTRANGE(""12PgU-zwv8gBrFfxvJpoPIPcxUHWup-vsxMH3HWUigZ8"",""💰 Donations!A4:N200""),14,2),"""")"),"Shalini S") -> Shalini S | D100: =IFERROR(__xludf.DUMMYFUNCTION("IFERROR(IFERROR(INDEX(IMPORTRANGE(""12PgU-zwv8gBrFfxvJpoPIPcxUHWup-vsxMH3HWUigZ8"",""💰 Donations!A4:N200""),14,3)*1,0),0)"),1000.0) -> 1000 | E100: =IFERROR(__xludf.DUMMYFUNCTION("IFERROR(IFERROR(INDEX(IMPORTRANGE(""12PgU-zwv8gBrFfxvJpoPIPcxUHWup-vsxMH3HWUigZ8"",""💰 Donations!A4:N200""),14,4)*1,0),0)"),1000.0) -> 1000 | F100: =IFERROR(D100-E100,0) -> 0 | G100: =IF(A100="","",IF(OR(E100=0,E100=""),"Pending",IF(E100>=D100,"Received","Partially Received"))) -> Received | H100: =IFERROR(__xludf.DUMMYFUNCTION("IFERROR(INDEX(IMPORTRANGE(""12PgU-zwv8gBrFfxvJpoPIPcxUHWup-vsxMH3HWUigZ8"",""💰 Donations!A4:N200""),14,6),"""")"),"UPI") -> UPI | I100: =IFERROR(__xludf.DUMMYFUNCTION("IFERROR(IF(INDEX(IMPORTRANGE(""12PgU-zwv8gBrFfxvJpoPIPcxUHWup-vsxMH3HWUigZ8"",""💰 Donations!A4:N200""),14,7)="""","""",TEXT(INDEX(IMPORTRANGE(""12PgU-zwv8gBrFfxvJpoPIPcxUHWup-vsxMH3HWUigZ8"",""💰 Donations!A4:N200""),14,7),""DD-MM-YYYY"")),"""")"),"24-05-2026") -> 24-05-2026 | J100: =IFERROR(__xludf.DUMMYFUNCTION("IFERROR(INDEX(IMPORTRANGE(""12PgU-zwv8gBrFfxvJpoPIPcxUHWup-vsxMH3HWUigZ8"",""💰 Donations!A4:N200""),14,8),"""")"),"Sunil Kumar") -> Sunil Kumar | K100: =IFERROR(__xludf.DUMMYFUNCTION("IFERROR(INDEX(IMPORTRANGE(""12PgU-zwv8gBrFfxvJpoPIPcxUHWup-vsxMH3HWUigZ8"",""💰 Donations!A4:N200""),14,11),"""")"),"Night Sweets") -> Night Sweets | L100: =IFERROR(__xludf.DUMMYFUNCTION("IFERROR(INDEX(IMPORTRANGE(""12PgU-zwv8gBrFfxvJpoPIPcxUHWup-vsxMH3HWUigZ8"",""💰 Donations!A4:N200""),14,13),"""")"),"Aadi Festival") -> Aadi Festival | M100: =IFERROR(__xludf.DUMMYFUNCTION("IFERROR(INDEX(IMPORTRANGE(""12PgU-zwv8gBrFfxvJpoPIPcxUHWup-vsxMH3HWUigZ8"",""💰 Donations!A4:N200""),14,14),"""")"),"") | N100: =IFERROR(__xludf.DUMMYFUNCTION("IFERROR(IF(INDEX(IMPORTRANGE(""12PgU-zwv8gBrFfxvJpoPIPcxUHWup-vsxMH3HWUigZ8"",""💰 Donations!A4:N200""),14,10)="""","""",TEXT(INDEX(IMPORTRANGE(""12PgU-zwv8gBrFfxvJpoPIPcxUHWup-vsxMH3HWUigZ8"",""💰 Donations!A4:N200""),14,10),""DD-MM-YYYY"")),"""")"),"")
A101: =IFERROR(__xludf.DUMMYFUNCTION("IFERROR(INDEX(IMPORTRANGE(""12PgU-zwv8gBrFfxvJpoPIPcxUHWup-vsxMH3HWUigZ8"",""💰 Donations!A4:N200""),15,1),"""")"),"2026/D/15") -> 2026/D/15 | B101: =IFERROR(__xludf.DUMMYFUNCTION("IFERROR(INDEX(IMPORTRANGE(""12PgU-zwv8gBrFfxvJpoPIPcxUHWup-vsxMH3HWUigZ8"",""💰 Donations!A4:N200""),15,2),"""")"),"Devi D") -> Devi D | D101: =IFERROR(__xludf.DUMMYFUNCTION("IFERROR(IFERROR(INDEX(IMPORTRANGE(""12PgU-zwv8gBrFfxvJpoPIPcxUHWup-vsxMH3HWUigZ8"",""💰 Donations!A4:N200""),15,3)*1,0),0)"),8000.0) -> 8000 | E101: =IFERROR(__xludf.DUMMYFUNCTION("IFERROR(IFERROR(INDEX(IMPORTRANGE(""12PgU-zwv8gBrFfxvJpoPIPcxUHWup-vsxMH3HWUigZ8"",""💰 Donations!A4:N200""),15,4)*1,0),0)"),8000.0) -> 8000 | F101: =IFERROR(D101-E101,0) -> 0 | G101: =IF(A101="","",IF(OR(E101=0,E101=""),"Pending",IF(E101>=D101,"Received","Partially Received"))) -> Received | H101: =IFERROR(__xludf.DUMMYFUNCTION("IFERROR(INDEX(IMPORTRANGE(""12PgU-zwv8gBrFfxvJpoPIPcxUHWup-vsxMH3HWUigZ8"",""💰 Donations!A4:N200""),15,6),"""")"),"UPI") -> UPI | I101: =IFERROR(__xludf.DUMMYFUNCTION("IFERROR(IF(INDEX(IMPORTRANGE(""12PgU-zwv8gBrFfxvJpoPIPcxUHWup-vsxMH3HWUigZ8"",""💰 Donations!A4:N200""),15,7)="""","""",TEXT(INDEX(IMPORTRANGE(""12PgU-zwv8gBrFfxvJpoPIPcxUHWup-vsxMH3HWUigZ8"",""💰 Donations!A4:N200""),15,7),""DD-MM-YYYY"")),"""")"),"24-05-2026") -> 24-05-2026 | J101: =IFERROR(__xludf.DUMMYFUNCTION("IFERROR(INDEX(IMPORTRANGE(""12PgU-zwv8gBrFfxvJpoPIPcxUHWup-vsxMH3HWUigZ8"",""💰 Donations!A4:N200""),15,8),"""")"),"Sunil Kumar") -> Sunil Kumar | K101: =IFERROR(__xludf.DUMMYFUNCTION("IFERROR(INDEX(IMPORTRANGE(""12PgU-zwv8gBrFfxvJpoPIPcxUHWup-vsxMH3HWUigZ8"",""💰 Donations!A4:N200""),15,11),"""")"),"Fruits/Coconut") -> Fruits/Coconut | L101: =IFERROR(__xludf.DUMMYFUNCTION("IFERROR(INDEX(IMPORTRANGE(""12PgU-zwv8gBrFfxvJpoPIPcxUHWup-vsxMH3HWUigZ8"",""💰 Donations!A4:N200""),15,13),"""")"),"Aadi Festival") -> Aadi Festival | M101: =IFERROR(__xludf.DUMMYFUNCTION("IFERROR(INDEX(IMPORTRANGE(""12PgU-zwv8gBrFfxvJpoPIPcxUHWup-vsxMH3HWUigZ8"",""💰 Donations!A4:N200""),15,14),"""")"),"") | N101: =IFERROR(__xludf.DUMMYFUNCTION("IFERROR(IF(INDEX(IMPORTRANGE(""12PgU-zwv8gBrFfxvJpoPIPcxUHWup-vsxMH3HWUigZ8"",""💰 Donations!A4:N200""),15,10)="""","""",TEXT(INDEX(IMPORTRANGE(""12PgU-zwv8gBrFfxvJpoPIPcxUHWup-vsxMH3HWUigZ8"",""💰 Donations!A4:N200""),15,10),""DD-MM-YYYY"")),"""")"),"")
A102: =IFERROR(__xludf.DUMMYFUNCTION("IFERROR(INDEX(IMPORTRANGE(""12PgU-zwv8gBrFfxvJpoPIPcxUHWup-vsxMH3HWUigZ8"",""💰 Donations!A4:N200""),16,1),"""")"),"2026/D/16") -> 2026/D/16 | B102: =IFERROR(__xludf.DUMMYFUNCTION("IFERROR(INDEX(IMPORTRANGE(""12PgU-zwv8gBrFfxvJpoPIPcxUHWup-vsxMH3HWUigZ8"",""💰 Donations!A4:N200""),16,2),"""")"),"Vidyashree S") -> Vidyashree S | D102: =IFERROR(__xludf.DUMMYFUNCTION("IFERROR(IFERROR(INDEX(IMPORTRANGE(""12PgU-zwv8gBrFfxvJpoPIPcxUHWup-vsxMH3HWUigZ8"",""💰 Donations!A4:N200""),16,3)*1,0),0)"),4000.0) -> 4000 | E102: =IFERROR(__xludf.DUMMYFUNCTION("IFERROR(IFERROR(INDEX(IMPORTRANGE(""12PgU-zwv8gBrFfxvJpoPIPcxUHWup-vsxMH3HWUigZ8"",""💰 Donations!A4:N200""),16,4)*1,0),0)"),0.0) -> 0 | F102: =IFERROR(D102-E102,0) -> 4000 | G102: =IF(A102="","",IF(OR(E102=0,E102=""),"Pending",IF(E102>=D102,"Received","Partially Received"))) -> Pending | H102: =IFERROR(__xludf.DUMMYFUNCTION("IFERROR(INDEX(IMPORTRANGE(""12PgU-zwv8gBrFfxvJpoPIPcxUHWup-vsxMH3HWUigZ8"",""💰 Donations!A4:N200""),16,6),"""")"),"") | I102: =IFERROR(__xludf.DUMMYFUNCTION("IFERROR(IF(INDEX(IMPORTRANGE(""12PgU-zwv8gBrFfxvJpoPIPcxUHWup-vsxMH3HWUigZ8"",""💰 Donations!A4:N200""),16,7)="""","""",TEXT(INDEX(IMPORTRANGE(""12PgU-zwv8gBrFfxvJpoPIPcxUHWup-vsxMH3HWUigZ8"",""💰 Donations!A4:N200""),16,7),""DD-MM-YYYY"")),"""")"),"") | J102: =IFERROR(__xludf.DUMMYFUNCTION("IFERROR(INDEX(IMPORTRANGE(""12PgU-zwv8gBrFfxvJpoPIPcxUHWup-vsxMH3HWUigZ8"",""💰 Donations!A4:N200""),16,8),"""")"),"") | K102: =IFERROR(__xludf.DUMMYFUNCTION("IFERROR(INDEX(IMPORTRANGE(""12PgU-zwv8gBrFfxvJpoPIPcxUHWup-vsxMH3HWUigZ8"",""💰 Donations!A4:N200""),16,11),"""")"),"Pamplet Printing & Crackers") -> Pamplet Printing & Crackers | L102: =IFERROR(__xludf.DUMMYFUNCTION("IFERROR(INDEX(IMPORTRANGE(""12PgU-zwv8gBrFfxvJpoPIPcxUHWup-vsxMH3HWUigZ8"",""💰 Donations!A4:N200""),16,13),"""")"),"Aadi Festival") -> Aadi Festival | M102: =IFERROR(__xludf.DUMMYFUNCTION("IFERROR(INDEX(IMPORTRANGE(""12PgU-zwv8gBrFfxvJpoPIPcxUHWup-vsxMH3HWUigZ8"",""💰 Donations!A4:N200""),16,14),"""")"),"") | N102: =IFERROR(__xludf.DUMMYFUNCTION("IFERROR(IF(INDEX(IMPORTRANGE(""12PgU-zwv8gBrFfxvJpoPIPcxUHWup-vsxMH3HWUigZ8"",""💰 Donations!A4:N200""),16,10)="""","""",TEXT(INDEX(IMPORTRANGE(""12PgU-zwv8gBrFfxvJpoPIPcxUHWup-vsxMH3HWUigZ8"",""💰 Donations!A4:N200""),16,10),""DD-MM-YYYY"")),"""")"),"10-06-2026") -> 10-06-2026
A103: =IFERROR(__xludf.DUMMYFUNCTION("IFERROR(INDEX(IMPORTRANGE(""12PgU-zwv8gBrFfxvJpoPIPcxUHWup-vsxMH3HWUigZ8"",""💰 Donations!A4:N200""),17,1),"""")"),"2026/D/17") -> 2026/D/17 | B103: =IFERROR(__xludf.DUMMYFUNCTION("IFERROR(INDEX(IMPORTRANGE(""12PgU-zwv8gBrFfxvJpoPIPcxUHWup-vsxMH3HWUigZ8"",""💰 Donations!A4:N200""),17,2),"""")"),"D. Gopala Krishan") -> D. Gopala Krishan | D103: =IFERROR(__xludf.DUMMYFUNCTION("IFERROR(IFERROR(INDEX(IMPORTRANGE(""12PgU-zwv8gBrFfxvJpoPIPcxUHWup-vsxMH3HWUigZ8"",""💰 Donations!A4:N200""),17,3)*1,0),0)"),10000.0) -> 10000 | E103: =IFERROR(__xludf.DUMMYFUNCTION("IFERROR(IFERROR(INDEX(IMPORTRANGE(""12PgU-zwv8gBrFfxvJpoPIPcxUHWup-vsxMH3HWUigZ8"",""💰 Donations!A4:N200""),17,4)*1,0),0)"),0.0) -> 0 | F103: =IFERROR(D103-E103,0) -> 10000 | G103: =IF(A103="","",IF(OR(E103=0,E103=""),"Pending",IF(E103>=D103,"Received","Partially Received"))) -> Pending | H103: =IFERROR(__xludf.DUMMYFUNCTION("IFERROR(INDEX(IMPORTRANGE(""12PgU-zwv8gBrFfxvJpoPIPcxUHWup-vsxMH3HWUigZ8"",""💰 Donations!A4:N200""),17,6),"""")"),"") | I103: =IFERROR(__xludf.DUMMYFUNCTION("IFERROR(IF(INDEX(IMPORTRANGE(""12PgU-zwv8gBrFfxvJpoPIPcxUHWup-vsxMH3HWUigZ8"",""💰 Donations!A4:N200""),17,7)="""","""",TEXT(INDEX(IMPORTRANGE(""12PgU-zwv8gBrFfxvJpoPIPcxUHWup-vsxMH3HWUigZ8"",""💰 Donations!A4:N200""),17,7),""DD-MM-YYYY"")),"""")"),"") | J103: =IFERROR(__xludf.DUMMYFUNCTION("IFERROR(INDEX(IMPORTRANGE(""12PgU-zwv8gBrFfxvJpoPIPcxUHWup-vsxMH3HWUigZ8"",""💰 Donations!A4:N200""),17,8),"""")"),"") | K103: =IFERROR(__xludf.DUMMYFUNCTION("IFERROR(INDEX(IMPORTRANGE(""12PgU-zwv8gBrFfxvJpoPIPcxUHWup-vsxMH3HWUigZ8"",""💰 Donations!A4:N200""),17,11),"""")"),"Blouse pieces / Kumkum set / Thread") -> Blouse pieces / Kumkum set / Thread | L103: =IFERROR(__xludf.DUMMYFUNCTION("IFERROR(INDEX(IMPORTRANGE(""12PgU-zwv8gBrFfxvJpoPIPcxUHWup-vsxMH3HWUigZ8"",""💰 Donations!A4:N200""),17,13),"""")"),"Aadi Festival") -> Aadi Festival | M103: =IFERROR(__xludf.DUMMYFUNCTION("IFERROR(INDEX(IMPORTRANGE(""12PgU-zwv8gBrFfxvJpoPIPcxUHWup-vsxMH3HWUigZ8"",""💰 Donations!A4:N200""),17,14),"""")"),"") | N103: =IFERROR(__xludf.DUMMYFUNCTION("IFERROR(IF(INDEX(IMPORTRANGE(""12PgU-zwv8gBrFfxvJpoPIPcxUHWup-vsxMH3HWUigZ8"",""💰 Donations!A4:N200""),17,10)="""","""",TEXT(INDEX(IMPORTRANGE(""12PgU-zwv8gBrFfxvJpoPIPcxUHWup-vsxMH3HWUigZ8"",""💰 Donations!A4:N200""),17,10),""DD-MM-YYYY"")),"""")"),"10-08-2026") -> 10-08-2026
A104: =IFERROR(__xludf.DUMMYFUNCTION("IFERROR(INDEX(IMPORTRANGE(""12PgU-zwv8gBrFfxvJpoPIPcxUHWup-vsxMH3HWUigZ8"",""💰 Donations!A4:N200""),18,1),"""")"),"2026/D/18") -> 2026/D/18 | B104: =IFERROR(__xludf.DUMMYFUNCTION("IFERROR(INDEX(IMPORTRANGE(""12PgU-zwv8gBrFfxvJpoPIPcxUHWup-vsxMH3HWUigZ8"",""💰 Donations!A4:N200""),18,2),"""")"),"Raghu Nataraj") -> Raghu Nataraj | D104: =IFERROR(__xludf.DUMMYFUNCTION("IFERROR(IFERROR(INDEX(IMPORTRANGE(""12PgU-zwv8gBrFfxvJpoPIPcxUHWup-vsxMH3HWUigZ8"",""💰 Donations!A4:N200""),18,3)*1,0),0)"),10500.0) -> 10500 | E104: =IFERROR(__xludf.DUMMYFUNCTION("IFERROR(IFERROR(INDEX(IMPORTRANGE(""12PgU-zwv8gBrFfxvJpoPIPcxUHWup-vsxMH3HWUigZ8"",""💰 Donations!A4:N200""),18,4)*1,0),0)"),10500.0) -> 10500 | F104: =IFERROR(D104-E104,0) -> 0 | G104: =IF(A104="","",IF(OR(E104=0,E104=""),"Pending",IF(E104>=D104,"Received","Partially Received"))) -> Received | H104: =IFERROR(__xludf.DUMMYFUNCTION("IFERROR(INDEX(IMPORTRANGE(""12PgU-zwv8gBrFfxvJpoPIPcxUHWup-vsxMH3HWUigZ8"",""💰 Donations!A4:N200""),18,6),"""")"),"UPI") -> UPI | I104: =IFERROR(__xludf.DUMMYFUNCTION("IFERROR(IF(INDEX(IMPORTRANGE(""12PgU-zwv8gBrFfxvJpoPIPcxUHWup-vsxMH3HWUigZ8"",""💰 Donations!A4:N200""),18,7)="""","""",TEXT(INDEX(IMPORTRANGE(""12PgU-zwv8gBrFfxvJpoPIPcxUHWup-vsxMH3HWUigZ8"",""💰 Donations!A4:N200""),18,7),""DD-MM-YYYY"")),"""")"),"06-03-2026") -> 06-03-2026 | J104: =IFERROR(__xludf.DUMMYFUNCTION("IFERROR(INDEX(IMPORTRANGE(""12PgU-zwv8gBrFfxvJpoPIPcxUHWup-vsxMH3HWUigZ8"",""💰 Donations!A4:N200""),18,8),"""")"),"Suresh Velu") -> Suresh Velu | K104: =IFERROR(__xludf.DUMMYFUNCTION("IFERROR(INDEX(IMPORTRANGE(""12PgU-zwv8gBrFfxvJpoPIPcxUHWup-vsxMH3HWUigZ8"",""💰 Donations!A4:N200""),18,11),"""")"),"Temple Painting,Temple Banner printing and installing") -> Temple Painting,Temple Banner printing and installing | L104: =IFERROR(__xludf.DUMMYFUNCTION("IFERROR(INDEX(IMPORTRANGE(""12PgU-zwv8gBrFfxvJpoPIPcxUHWup-vsxMH3HWUigZ8"",""💰 Donations!A4:N200""),18,13),"""")"),"Aadi Festival") -> Aadi Festival | M104: =IFERROR(__xludf.DUMMYFUNCTION("IFERROR(INDEX(IMPORTRANGE(""12PgU-zwv8gBrFfxvJpoPIPcxUHWup-vsxMH3HWUigZ8"",""💰 Donations!A4:N200""),18,14),"""")"),"") | N104: =IFERROR(__xludf.DUMMYFUNCTION("IFERROR(IF(INDEX(IMPORTRANGE(""12PgU-zwv8gBrFfxvJpoPIPcxUHWup-vsxMH3HWUigZ8"",""💰 Donations!A4:N200""),18,10)="""","""",TEXT(INDEX(IMPORTRANGE(""12PgU-zwv8gBrFfxvJpoPIPcxUHWup-vsxMH3HWUigZ8"",""💰 Donations!A4:N200""),18,10),""DD-MM-YYYY"")),"""")"),"10-08-2026") -> 10-08-2026
A105: =IFERROR(__xludf.DUMMYFUNCTION("IFERROR(INDEX(IMPORTRANGE(""12PgU-zwv8gBrFfxvJpoPIPcxUHWup-vsxMH3HWUigZ8"",""💰 Donations!A4:N200""),19,1),"""")"),"2026/D/19") -> 2026/D/19 | B105: =IFERROR(__xludf.DUMMYFUNCTION("IFERROR(INDEX(IMPORTRANGE(""12PgU-zwv8gBrFfxvJpoPIPcxUHWup-vsxMH3HWUigZ8"",""💰 Donations!A4:N200""),19,2),"""")"),"BM Neelakantan & Ramya") -> BM Neelakantan & Ramya | D105: =IFERROR(__xludf.DUMMYFUNCTION("IFERROR(IFERROR(INDEX(IMPORTRANGE(""12PgU-zwv8gBrFfxvJpoPIPcxUHWup-vsxMH3HWUigZ8"",""💰 Donations!A4:N200""),19,3)*1,0),0)"),3000.0) -> 3000 | E105: =IFERROR(__xludf.DUMMYFUNCTION("IFERROR(IFERROR(INDEX(IMPORTRANGE(""12PgU-zwv8gBrFfxvJpoPIPcxUHWup-vsxMH3HWUigZ8"",""💰 Donations!A4:N200""),19,4)*1,0),0)"),3000.0) -> 3000 | F105: =IFERROR(D105-E105,0) -> 0 | G105: =IF(A105="","",IF(OR(E105=0,E105=""),"Pending",IF(E105>=D105,"Received","Partially Received"))) -> Received | H105: =IFERROR(__xludf.DUMMYFUNCTION("IFERROR(INDEX(IMPORTRANGE(""12PgU-zwv8gBrFfxvJpoPIPcxUHWup-vsxMH3HWUigZ8"",""💰 Donations!A4:N200""),19,6),"""")"),"UPI") -> UPI | I105: =IFERROR(__xludf.DUMMYFUNCTION("IFERROR(IF(INDEX(IMPORTRANGE(""12PgU-zwv8gBrFfxvJpoPIPcxUHWup-vsxMH3HWUigZ8"",""💰 Donations!A4:N200""),19,7)="""","""",TEXT(INDEX(IMPORTRANGE(""12PgU-zwv8gBrFfxvJpoPIPcxUHWup-vsxMH3HWUigZ8"",""💰 Donations!A4:N200""),19,7),""DD-MM-YYYY"")),"""")"),"24-05-2026") -> 24-05-2026 | J105: =IFERROR(__xludf.DUMMYFUNCTION("IFERROR(INDEX(IMPORTRANGE(""12PgU-zwv8gBrFfxvJpoPIPcxUHWup-vsxMH3HWUigZ8"",""💰 Donations!A4:N200""),19,8),"""")"),"Sunil Kumar") -> Sunil Kumar | K105: =IFERROR(__xludf.DUMMYFUNCTION("IFERROR(INDEX(IMPORTRANGE(""12PgU-zwv8gBrFfxvJpoPIPcxUHWup-vsxMH3HWUigZ8"",""💰 Donations!A4:N200""),19,11),"""")"),"Temple premises cleaning") -> Temple premises cleaning | L105: =IFERROR(__xludf.DUMMYFUNCTION("IFERROR(INDEX(IMPORTRANGE(""12PgU-zwv8gBrFfxvJpoPIPcxUHWup-vsxMH3HWUigZ8"",""💰 Donations!A4:N200""),19,13),"""")"),"Aadi Festival") -> Aadi Festival | M105: =IFERROR(__xludf.DUMMYFUNCTION("IFERROR(INDEX(IMPORTRANGE(""12PgU-zwv8gBrFfxvJpoPIPcxUHWup-vsxMH3HWUigZ8"",""💰 Donations!A4:N200""),19,14),"""")"),"") | N105: =IFERROR(__xludf.DUMMYFUNCTION("IFERROR(IF(INDEX(IMPORTRANGE(""12PgU-zwv8gBrFfxvJpoPIPcxUHWup-vsxMH3HWUigZ8"",""💰 Donations!A4:N200""),19,10)="""","""",TEXT(INDEX(IMPORTRANGE(""12PgU-zwv8gBrFfxvJpoPIPcxUHWup-vsxMH3HWUigZ8"",""💰 Donations!A4:N200""),19,10),""DD-MM-YYYY"")),"""")"),"")
A106: =IFERROR(__xludf.DUMMYFUNCTION("IFERROR(INDEX(IMPORTRANGE(""12PgU-zwv8gBrFfxvJpoPIPcxUHWup-vsxMH3HWUigZ8"",""💰 Donations!A4:N200""),20,1),"""")"),"2026/D/20") -> 2026/D/20 | B106: =IFERROR(__xludf.DUMMYFUNCTION("IFERROR(INDEX(IMPORTRANGE(""12PgU-zwv8gBrFfxvJpoPIPcxUHWup-vsxMH3HWUigZ8"",""💰 Donations!A4:N200""),20,2),"""")"),"Manish Gupta and family") -> Manish Gupta and family | D106: =IFERROR(__xludf.DUMMYFUNCTION("IFERROR(IFERROR(INDEX(IMPORTRANGE(""12PgU-zwv8gBrFfxvJpoPIPcxUHWup-vsxMH3HWUigZ8"",""💰 Donations!A4:N200""),20,3)*1,0),0)"),5000.0) -> 5000 | E106: =IFERROR(__xludf.DUMMYFUNCTION("IFERROR(IFERROR(INDEX(IMPORTRANGE(""12PgU-zwv8gBrFfxvJpoPIPcxUHWup-vsxMH3HWUigZ8"",""💰 Donations!A4:N200""),20,4)*1,0),0)"),5000.0) -> 5000 | F106: =IFERROR(D106-E106,0) -> 0 | G106: =IF(A106="","",IF(OR(E106=0,E106=""),"Pending",IF(E106>=D106,"Received","Partially Received"))) -> Received | H106: =IFERROR(__xludf.DUMMYFUNCTION("IFERROR(INDEX(IMPORTRANGE(""12PgU-zwv8gBrFfxvJpoPIPcxUHWup-vsxMH3HWUigZ8"",""💰 Donations!A4:N200""),20,6),"""")"),"UPI") -> UPI | I106: =IFERROR(__xludf.DUMMYFUNCTION("IFERROR(IF(INDEX(IMPORTRANGE(""12PgU-zwv8gBrFfxvJpoPIPcxUHWup-vsxMH3HWUigZ8"",""💰 Donations!A4:N200""),20,7)="""","""",TEXT(INDEX(IMPORTRANGE(""12PgU-zwv8gBrFfxvJpoPIPcxUHWup-vsxMH3HWUigZ8"",""💰 Donations!A4:N200""),20,7),""DD-MM-YYYY"")),"""")"),"24-05-2026") -> 24-05-2026 | J106: =IFERROR(__xludf.DUMMYFUNCTION("IFERROR(INDEX(IMPORTRANGE(""12PgU-zwv8gBrFfxvJpoPIPcxUHWup-vsxMH3HWUigZ8"",""💰 Donations!A4:N200""),20,8),"""")"),"Sunil Kumar") -> Sunil Kumar | K106: =IFERROR(__xludf.DUMMYFUNCTION("IFERROR(INDEX(IMPORTRANGE(""12PgU-zwv8gBrFfxvJpoPIPcxUHWup-vsxMH3HWUigZ8"",""💰 Donations!A4:N200""),20,11),"""")"),"Others (Transport etc..)") -> Others (Transport etc..) | L106: =IFERROR(__xludf.DUMMYFUNCTION("IFERROR(INDEX(IMPORTRANGE(""12PgU-zwv8gBrFfxvJpoPIPcxUHWup-vsxMH3HWUigZ8"",""💰 Donations!A4:N200""),20,13),"""")"),"Aadi Festival") -> Aadi Festival | M106: =IFERROR(__xludf.DUMMYFUNCTION("IFERROR(INDEX(IMPORTRANGE(""12PgU-zwv8gBrFfxvJpoPIPcxUHWup-vsxMH3HWUigZ8"",""💰 Donations!A4:N200""),20,14),"""")"),"") | N106: =IFERROR(__xludf.DUMMYFUNCTION("IFERROR(IF(INDEX(IMPORTRANGE(""12PgU-zwv8gBrFfxvJpoPIPcxUHWup-vsxMH3HWUigZ8"",""💰 Donations!A4:N200""),20,10)="""","""",TEXT(INDEX(IMPORTRANGE(""12PgU-zwv8gBrFfxvJpoPIPcxUHWup-vsxMH3HWUigZ8"",""💰 Donations!A4:N200""),20,10),""DD-MM-YYYY"")),"""")"),"")
A107: =IFERROR(__xludf.DUMMYFUNCTION("IFERROR(INDEX(IMPORTRANGE(""12PgU-zwv8gBrFfxvJpoPIPcxUHWup-vsxMH3HWUigZ8"",""💰 Donations!A4:N200""),21,1),"""")"),"2026/D/21") -> 2026/D/21 | B107: =IFERROR(__xludf.DUMMYFUNCTION("IFERROR(INDEX(IMPORTRANGE(""12PgU-zwv8gBrFfxvJpoPIPcxUHWup-vsxMH3HWUigZ8"",""💰 Donations!A4:N200""),21,2),"""")"),"Manjula Narayanan") -> Manjula Narayanan | D107: =IFERROR(__xludf.DUMMYFUNCTION("IFERROR(IFERROR(INDEX(IMPORTRANGE(""12PgU-zwv8gBrFfxvJpoPIPcxUHWup-vsxMH3HWUigZ8"",""💰 Donations!A4:N200""),21,3)*1,0),0)"),5000.0) -> 5000 | E107: =IFERROR(__xludf.DUMMYFUNCTION("IFERROR(IFERROR(INDEX(IMPORTRANGE(""12PgU-zwv8gBrFfxvJpoPIPcxUHWup-vsxMH3HWUigZ8"",""💰 Donations!A4:N200""),21,4)*1,0),0)"),0.0) -> 0 | F107: =IFERROR(D107-E107,0) -> 5000 | G107: =IF(A107="","",IF(OR(E107=0,E107=""),"Pending",IF(E107>=D107,"Received","Partially Received"))) -> Pending | H107: =IFERROR(__xludf.DUMMYFUNCTION("IFERROR(INDEX(IMPORTRANGE(""12PgU-zwv8gBrFfxvJpoPIPcxUHWup-vsxMH3HWUigZ8"",""💰 Donations!A4:N200""),21,6),"""")"),"") | I107: =IFERROR(__xludf.DUMMYFUNCTION("IFERROR(IF(INDEX(IMPORTRANGE(""12PgU-zwv8gBrFfxvJpoPIPcxUHWup-vsxMH3HWUigZ8"",""💰 Donations!A4:N200""),21,7)="""","""",TEXT(INDEX(IMPORTRANGE(""12PgU-zwv8gBrFfxvJpoPIPcxUHWup-vsxMH3HWUigZ8"",""💰 Donations!A4:N200""),21,7),""DD-MM-YYYY"")),"""")"),"") | J107: =IFERROR(__xludf.DUMMYFUNCTION("IFERROR(INDEX(IMPORTRANGE(""12PgU-zwv8gBrFfxvJpoPIPcxUHWup-vsxMH3HWUigZ8"",""💰 Donations!A4:N200""),21,8),"""")"),"") | K107: =IFERROR(__xludf.DUMMYFUNCTION("IFERROR(INDEX(IMPORTRANGE(""12PgU-zwv8gBrFfxvJpoPIPcxUHWup-vsxMH3HWUigZ8"",""💰 Donations!A4:N200""),21,11),"""")"),"") | L107: =IFERROR(__xludf.DUMMYFUNCTION("IFERROR(INDEX(IMPORTRANGE(""12PgU-zwv8gBrFfxvJpoPIPcxUHWup-vsxMH3HWUigZ8"",""💰 Donations!A4:N200""),21,13),"""")"),"Aadi Festival") -> Aadi Festival | M107: =IFERROR(__xludf.DUMMYFUNCTION("IFERROR(INDEX(IMPORTRANGE(""12PgU-zwv8gBrFfxvJpoPIPcxUHWup-vsxMH3HWUigZ8"",""💰 Donations!A4:N200""),21,14),"""")"),"") | N107: =IFERROR(__xludf.DUMMYFUNCTION("IFERROR(IF(INDEX(IMPORTRANGE(""12PgU-zwv8gBrFfxvJpoPIPcxUHWup-vsxMH3HWUigZ8"",""💰 Donations!A4:N200""),21,10)="""","""",TEXT(INDEX(IMPORTRANGE(""12PgU-zwv8gBrFfxvJpoPIPcxUHWup-vsxMH3HWUigZ8"",""💰 Donations!A4:N200""),21,10),""DD-MM-YYYY"")),"""")"),"10-06-2026") -> 10-06-2026
...

Sheet 2027
A1: 🕉 SRI PONNIAMMAN TEMPLE — ANNUAL ACCOUNTS 2027 🕉
A2: Financial Year: 2027 | Live data via Google Sheets IMPORTRANGE
A4: 🎪 FESTIVALS / EVENTS IN THIS YEAR
A5: # | B5: Festival / Event | D5: Date | E5: Notes / Description
A6: 1
A8: 📊 ANNUAL SUMMARY
A9: Annual Budget (₹) | D9: =SUM(D20:D28) -> 0
A10: Total Donations Pledged (₹) | D10: =IFERROR(__xludf.DUMMYFUNCTION("IFERROR(INDEX(QUERY(IMPORTRANGE(""1wF8uimz-gnzzmqfjHb8Ua7fudqcoq5SrFyToq2B2IO0"",""💰 Donations!A4:D200""),""SELECT SUM(Col3) WHERE Col1 LIKE '2027/D/%' LABEL SUM(Col3) ''""),1),0)"),0.0) -> 0
A11: Donations Received (₹) | D11: =IFERROR(__xludf.DUMMYFUNCTION("IFERROR(INDEX(QUERY(IMPORTRANGE(""1wF8uimz-gnzzmqfjHb8Ua7fudqcoq5SrFyToq2B2IO0"",""💰 Donations!A4:D200""),""SELECT SUM(Col4) WHERE Col1 LIKE '2027/D/%' LABEL SUM(Col4) ''""),1),0)"),0.0) -> 0
A12: Donations Pending (₹) | D12: =D10-D11 -> 0
A13: In-Kind Donations (₹) | D13: =IFERROR(__xludf.DUMMYFUNCTION("IFERROR(INDEX(QUERY(IMPORTRANGE(""1wF8uimz-gnzzmqfjHb8Ua7fudqcoq5SrFyToq2B2IO0"",""🌿 In-Kind!A4:E200""),""SELECT SUM(Col5) WHERE Col1 LIKE '2027/IK/%' LABEL SUM(Col5) ''""),1),0)"),0.0) -> 0
A14: Total Expenses (₹) | D14: =IFERROR(__xludf.DUMMYFUNCTION("IFERROR(INDEX(QUERY(IMPORTRANGE(""1wF8uimz-gnzzmqfjHb8Ua7fudqcoq5SrFyToq2B2IO0"",""💸 Expenses!A5:F200""),""SELECT SUM(Col6) WHERE Col1 LIKE '2027/EX/%' LABEL SUM(Col6) ''""),1),0)"),0.0) -> 0
A15: Net Surplus / (Deficit) (₹) | D15: =D9-D14 -> 0
A16: Total Donors | D16: =IFERROR(__xludf.DUMMYFUNCTION("IFERROR(INDEX(QUERY(IMPORTRANGE(""1wF8uimz-gnzzmqfjHb8Ua7fudqcoq5SrFyToq2B2IO0"",""💰 Donations!A4:D200""),""SELECT COUNT(Col1) WHERE Col1 LIKE '2027/D/%' LABEL COUNT(Col1) ''""),1),0)"),1.0) -> 1
A18: 💰 EXPENSE CATEGORY BREAKDOWN (Budget vs Actual)
A19: # | B19: Category | C19: Group | D19: Budget (₹) | E19: Actual (₹) | F19: Balance (₹)
A20: 1 | B20: Puja & Rituals | C20: Aadi Festival | D20: =IFERROR(__xludf.DUMMYFUNCTION("IFERROR(INDEX(QUERY(IMPORTRANGE(""1wF8uimz-gnzzmqfjHb8Ua7fudqcoq5SrFyToq2B2IO0"",""💰 Budget!C5:E200""),""SELECT SUM(Col3) WHERE Col1='Puja & Rituals' LABEL SUM(Col3) ''""),1),0)"),0.0) -> 0 | E20: =IFERROR(__xludf.DUMMYFUNCTION("IFERROR(INDEX(QUERY(IMPORTRANGE(""1wF8uimz-gnzzmqfjHb8Ua7fudqcoq5SrFyToq2B2IO0"",""💸 Expenses!E5:F200""),""SELECT SUM(Col2) WHERE Col1='Puja & Rituals' LABEL SUM(Col2) ''""),1),0)"),0.0) -> 0 | F20: =D20-E20 -> 0
A21: 2 | B21: Decorations & Flowers | C21: Aadi Festival | D21: =IFERROR(__xludf.DUMMYFUNCTION("IFERROR(INDEX(QUERY(IMPORTRANGE(""1wF8uimz-gnzzmqfjHb8Ua7fudqcoq5SrFyToq2B2IO0"",""💰 Budget!C5:E200""),""SELECT SUM(Col3) WHERE Col1='Decorations & Flowers' LABEL SUM(Col3) ''""),1),0)"),0.0) -> 0 | E21: =IFERROR(__xludf.DUMMYFUNCTION("IFERROR(INDEX(QUERY(IMPORTRANGE(""1wF8uimz-gnzzmqfjHb8Ua7fudqcoq5SrFyToq2B2IO0"",""💸 Expenses!E5:F200""),""SELECT SUM(Col2) WHERE Col1='Decorations & Flowers' LABEL SUM(Col2) ''""),1),0)"),0.0) -> 0 | F21: =D21-E21 -> 0
A22: 3 | B22: Food & Catering | C22: Aadi Festival | D22: =IFERROR(__xludf.DUMMYFUNCTION("IFERROR(INDEX(QUERY(IMPORTRANGE(""1wF8uimz-gnzzmqfjHb8Ua7fudqcoq5SrFyToq2B2IO0"",""💰 Budget!C5:E200""),""SELECT SUM(Col3) WHERE Col1='Food & Catering' LABEL SUM(Col3) ''""),1),0)"),0.0) -> 0 | E22: =IFERROR(__xludf.DUMMYFUNCTION("IFERROR(INDEX(QUERY(IMPORTRANGE(""1wF8uimz-gnzzmqfjHb8Ua7fudqcoq5SrFyToq2B2IO0"",""💸 Expenses!E5:F200""),""SELECT SUM(Col2) WHERE Col1='Food & Catering' LABEL SUM(Col2) ''""),1),0)"),0.0) -> 0 | F22: =D22-E22 -> 0
A23: 4 | B23: Infrastructure & Logistics | C23: Aadi Festival | D23: =IFERROR(__xludf.DUMMYFUNCTION("IFERROR(INDEX(QUERY(IMPORTRANGE(""1wF8uimz-gnzzmqfjHb8Ua7fudqcoq5SrFyToq2B2IO0"",""💰 Budget!C5:E200""),""SELECT SUM(Col3) WHERE Col1='Infrastructure & Logistics' LABEL SUM(Col3) ''""),1),0)"),0.0) -> 0 | E23: =IFERROR(__xludf.DUMMYFUNCTION("IFERROR(INDEX(QUERY(IMPORTRANGE(""1wF8uimz-gnzzmqfjHb8Ua7fudqcoq5SrFyToq2B2IO0"",""💸 Expenses!E5:F200""),""SELECT SUM(Col2) WHERE Col1='Infrastructure & Logistics' LABEL SUM(Col2) ''""),1),0)"),0.0) -> 0 | F23: =D23-E23 -> 0
A24: 5 | B24: Miscellaneous | C24: Aadi Festival | D24: =IFERROR(__xludf.DUMMYFUNCTION("IFERROR(INDEX(QUERY(IMPORTRANGE(""1wF8uimz-gnzzmqfjHb8Ua7fudqcoq5SrFyToq2B2IO0"",""💰 Budget!C5:E200""),""SELECT SUM(Col3) WHERE Col1='Miscellaneous' LABEL SUM(Col3) ''""),1),0)"),0.0) -> 0 | E24: =IFERROR(__xludf.DUMMYFUNCTION("IFERROR(INDEX(QUERY(IMPORTRANGE(""1wF8uimz-gnzzmqfjHb8Ua7fudqcoq5SrFyToq2B2IO0"",""💸 Expenses!E5:F200""),""SELECT SUM(Col2) WHERE Col1='Miscellaneous' LABEL SUM(Col2) ''""),1),0)"),0.0) -> 0 | F24: =D24-E24 -> 0
A25: 6 | B25: Materials | C25: Temple Development | D25: =IFERROR(__xludf.DUMMYFUNCTION("IFERROR(INDEX(QUERY(IMPORTRANGE(""1wF8uimz-gnzzmqfjHb8Ua7fudqcoq5SrFyToq2B2IO0"",""💰 Budget!C5:E200""),""SELECT SUM(Col3) WHERE Col1='Materials' LABEL SUM(Col3) ''""),1),0)"),0.0) -> 0 | E25: =IFERROR(__xludf.DUMMYFUNCTION("IFERROR(INDEX(QUERY(IMPORTRANGE(""1wF8uimz-gnzzmqfjHb8Ua7fudqcoq5SrFyToq2B2IO0"",""💸 Expenses!E5:F200""),""SELECT SUM(Col2) WHERE Col1='Materials' LABEL SUM(Col2) ''""),1),0)"),0.0) -> 0 | F25: =D25-E25 -> 0
A26: 7 | B26: Labour | C26: Temple Development | D26: =IFERROR(__xludf.DUMMYFUNCTION("IFERROR(INDEX(QUERY(IMPORTRANGE(""1wF8uimz-gnzzmqfjHb8Ua7fudqcoq5SrFyToq2B2IO0"",""💰 Budget!C5:E200""),""SELECT SUM(Col3) WHERE Col1='Labour' LABEL SUM(Col3) ''""),1),0)"),0.0) -> 0 | E26: =IFERROR(__xludf.DUMMYFUNCTION("IFERROR(INDEX(QUERY(IMPORTRANGE(""1wF8uimz-gnzzmqfjHb8Ua7fudqcoq5SrFyToq2B2IO0"",""💸 Expenses!E5:F200""),""SELECT SUM(Col2) WHERE Col1='Labour' LABEL SUM(Col2) ''""),1),0)"),0.0) -> 0 | F26: =D26-E26 -> 0
A27: 8 | B27: Transport | C27: Temple Development | D27: =IFERROR(__xludf.DUMMYFUNCTION("IFERROR(INDEX(QUERY(IMPORTRANGE(""1wF8uimz-gnzzmqfjHb8Ua7fudqcoq5SrFyToq2B2IO0"",""💰 Budget!C5:E200""),""SELECT SUM(Col3) WHERE Col1='Transport' LABEL SUM(Col3) ''""),1),0)"),0.0) -> 0 | E27: =IFERROR(__xludf.DUMMYFUNCTION("IFERROR(INDEX(QUERY(IMPORTRANGE(""1wF8uimz-gnzzmqfjHb8Ua7fudqcoq5SrFyToq2B2IO0"",""💸 Expenses!E5:F200""),""SELECT SUM(Col2) WHERE Col1='Transport' LABEL SUM(Col2) ''""),1),0)"),0.0) -> 0 | F27: =D27-E27 -> 0
A28: 9 | B28: Food | C28: Temple Development | D28: =IFERROR(__xludf.DUMMYFUNCTION("IFERROR(INDEX(QUERY(IMPORTRANGE(""1wF8uimz-gnzzmqfjHb8Ua7fudqcoq5SrFyToq2B2IO0"",""💰 Budget!C5:E200""),""SELECT SUM(Col3) WHERE Col1='Food' LABEL SUM(Col3) ''""),1),0)"),0.0) -> 0 | E28: =IFERROR(__xludf.DUMMYFUNCTION("IFERROR(INDEX(QUERY(IMPORTRANGE(""1wF8uimz-gnzzmqfjHb8Ua7fudqcoq5SrFyToq2B2IO0"",""💸 Expenses!E5:F200""),""SELECT SUM(Col2) WHERE Col1='Food' LABEL SUM(Col2) ''""),1),0)"),0.0) -> 0 | F28: =D28-E28 -> 0
A29: TOTAL ALL CATEGORIES | D29: =SUM(D20:D28) -> 0 | E29: =SUM(E20:E28) -> 0 | F29: =D29-E29 -> 0
A31: 🗂️ EXPENSE TYPE SUMMARY
A32: # | B32: Expense Type | D32: Total Amount (₹)
A33: 1 | B33: Aadi Festival | D33: =IFERROR(__xludf.DUMMYFUNCTION("IFERROR(INDEX(QUERY(IMPORTRANGE(""1wF8uimz-gnzzmqfjHb8Ua7fudqcoq5SrFyToq2B2IO0"",""💸 Expenses!F5:J200""),""SELECT SUM(Col1) WHERE Col5='Aadi Festival' LABEL SUM(Col1) ''""),1),0)"),0.0) -> 0
A34: 2 | B34: Temple Development | D34: =IFERROR(__xludf.DUMMYFUNCTION("IFERROR(INDEX(QUERY(IMPORTRANGE(""1wF8uimz-gnzzmqfjHb8Ua7fudqcoq5SrFyToq2B2IO0"",""💸 Expenses!F5:J200""),""SELECT SUM(Col1) WHERE Col5='Temple Development' LABEL SUM(Col1) ''""),1),0)"),0.0) -> 0
A35: 3 | B35: Temple Operations | D35: =IFERROR(__xludf.DUMMYFUNCTION("IFERROR(INDEX(QUERY(IMPORTRANGE(""1wF8uimz-gnzzmqfjHb8Ua7fudqcoq5SrFyToq2B2IO0"",""💸 Expenses!F5:J200""),""SELECT SUM(Col1) WHERE Col5='Temple Operations' LABEL SUM(Col1) ''""),1),0)"),0.0) -> 0
A36: 4 | B36: Others | D36: =IFERROR(__xludf.DUMMYFUNCTION("IFERROR(INDEX(QUERY(IMPORTRANGE(""1wF8uimz-gnzzmqfjHb8Ua7fudqcoq5SrFyToq2B2IO0"",""💸 Expenses!F5:J200""),""SELECT SUM(Col1) WHERE Col5='Others' LABEL SUM(Col1) ''""),1),0)"),0.0) -> 0
A37: TOTAL | D37: =SUM(D33:D36) -> 0
A39: 💸 EXPENSE LOG
A40: # | B40: Date | C40: Vendor / Payee | D40: Description | E40: Category | F40: Amount (₹) | G40: Mode | H40: Paid By | I40: Remarks | J40: Type
A41: =IFERROR(__xludf.DUMMYFUNCTION("IFERROR(INDEX(IMPORTRANGE(""1wF8uimz-gnzzmqfjHb8Ua7fudqcoq5SrFyToq2B2IO0"",""💸 Expenses!A5:J200""),1,1),"""")"),"2027/EX/1") -> 2027/EX/1 | B41: =IFERROR(__xludf.DUMMYFUNCTION("IFERROR(IF(INDEX(IMPORTRANGE(""1wF8uimz-gnzzmqfjHb8Ua7fudqcoq5SrFyToq2B2IO0"",""💸 Expenses!A5:J200""),1,2)="""","""",TEXT(INDEX(IMPORTRANGE(""1wF8uimz-gnzzmqfjHb8Ua7fudqcoq5SrFyToq2B2IO0"",""💸 Expenses!A5:J200""),1,2),""DD-MM-YYYY"")),"""")"),"25-05-26") -> 25-05-26 | C41: =IFERROR(__xludf.DUMMYFUNCTION("IFERROR(INDEX(IMPORTRANGE(""1wF8uimz-gnzzmqfjHb8Ua7fudqcoq5SrFyToq2B2IO0"",""💸 Expenses!A5:J200""),1,3),"""")"),"Thimiri Press") -> Thimiri Press | D41: =IFERROR(__xludf.DUMMYFUNCTION("IFERROR(INDEX(IMPORTRANGE(""1wF8uimz-gnzzmqfjHb8Ua7fudqcoq5SrFyToq2B2IO0"",""💸 Expenses!A5:J200""),1,4),"""")"),"Card Printing") -> Card Printing | E41: =IFERROR(__xludf.DUMMYFUNCTION("IFERROR(INDEX(IMPORTRANGE(""1wF8uimz-gnzzmqfjHb8Ua7fudqcoq5SrFyToq2B2IO0"",""💸 Expenses!A5:J200""),1,5),"""")"),"Miscellaneous") -> Miscellaneous | F41: =IFERROR(__xludf.DUMMYFUNCTION("IFERROR(IFERROR(INDEX(IMPORTRANGE(""1wF8uimz-gnzzmqfjHb8Ua7fudqcoq5SrFyToq2B2IO0"",""💸 Expenses!A5:J200""),1,6)*1,0),0)"),0.0) -> 0 | G41: =IFERROR(__xludf.DUMMYFUNCTION("IFERROR(INDEX(IMPORTRANGE(""1wF8uimz-gnzzmqfjHb8Ua7fudqcoq5SrFyToq2B2IO0"",""💸 Expenses!A5:J200""),1,7),"""")"),"UPI") -> UPI | H41: =IFERROR(__xludf.DUMMYFUNCTION("IFERROR(INDEX(IMPORTRANGE(""1wF8uimz-gnzzmqfjHb8Ua7fudqcoq5SrFyToq2B2IO0"",""💸 Expenses!A5:J200""),1,8),"""")"),"Sunil Kumar") -> Sunil Kumar | I41: =IFERROR(__xludf.DUMMYFUNCTION("IFERROR(INDEX(IMPORTRANGE(""1wF8uimz-gnzzmqfjHb8Ua7fudqcoq5SrFyToq2B2IO0"",""💸 Expenses!A5:J200""),1,9),"""")"),"") | J41: =IFERROR(__xludf.DUMMYFUNCTION("IFERROR(INDEX(IMPORTRANGE(""1wF8uimz-gnzzmqfjHb8Ua7fudqcoq5SrFyToq2B2IO0"",""💸 Expenses!A5:J200""),1,10),"""")"),"Aadi Festival") -> Aadi Festival
A42: =IFERROR(__xludf.DUMMYFUNCTION("IFERROR(INDEX(IMPORTRANGE(""1wF8uimz-gnzzmqfjHb8Ua7fudqcoq5SrFyToq2B2IO0"",""💸 Expenses!A5:J200""),2,1),"""")"),"") | B42: =IFERROR(__xludf.DUMMYFUNCTION("IFERROR(IF(INDEX(IMPORTRANGE(""1wF8uimz-gnzzmqfjHb8Ua7fudqcoq5SrFyToq2B2IO0"",""💸 Expenses!A5:J200""),2,2)="""","""",TEXT(INDEX(IMPORTRANGE(""1wF8uimz-gnzzmqfjHb8Ua7fudqcoq5SrFyToq2B2IO0"",""💸 Expenses!A5:J200""),2,2),""DD-MM-YYYY"")),"""")"),"") | C42: =IFERROR(__xludf.DUMMYFUNCTION("IFERROR(INDEX(IMPORTRANGE(""1wF8uimz-gnzzmqfjHb8Ua7fudqcoq5SrFyToq2B2IO0"",""💸 Expenses!A5:J200""),2,3),"""")"),"") | D42: =IFERROR(__xludf.DUMMYFUNCTION("IFERROR(INDEX(IMPORTRANGE(""1wF8uimz-gnzzmqfjHb8Ua7fudqcoq5SrFyToq2B2IO0"",""💸 Expenses!A5:J200""),2,4),"""")"),"") | E42: =IFERROR(__xludf.DUMMYFUNCTION("IFERROR(INDEX(IMPORTRANGE(""1wF8uimz-gnzzmqfjHb8Ua7fudqcoq5SrFyToq2B2IO0"",""💸 Expenses!A5:J200""),2,5),"""")"),"") | F42: =IFERROR(__xludf.DUMMYFUNCTION("IFERROR(IFERROR(INDEX(IMPORTRANGE(""1wF8uimz-gnzzmqfjHb8Ua7fudqcoq5SrFyToq2B2IO0"",""💸 Expenses!A5:J200""),2,6)*1,0),0)"),0.0) -> 0 | G42: =IFERROR(__xludf.DUMMYFUNCTION("IFERROR(INDEX(IMPORTRANGE(""1wF8uimz-gnzzmqfjHb8Ua7fudqcoq5SrFyToq2B2IO0"",""💸 Expenses!A5:J200""),2,7),"""")"),"") | H42: =IFERROR(__xludf.DUMMYFUNCTION("IFERROR(INDEX(IMPORTRANGE(""1wF8uimz-gnzzmqfjHb8Ua7fudqcoq5SrFyToq2B2IO0"",""💸 Expenses!A5:J200""),2,8),"""")"),"") | I42: =IFERROR(__xludf.DUMMYFUNCTION("IFERROR(INDEX(IMPORTRANGE(""1wF8uimz-gnzzmqfjHb8Ua7fudqcoq5SrFyToq2B2IO0"",""💸 Expenses!A5:J200""),2,9),"""")"),"") | J42: =IFERROR(__xludf.DUMMYFUNCTION("IFERROR(INDEX(IMPORTRANGE(""1wF8uimz-gnzzmqfjHb8Ua7fudqcoq5SrFyToq2B2IO0"",""💸 Expenses!A5:J200""),2,10),"""")"),"")
A43: =IFERROR(__xludf.DUMMYFUNCTION("IFERROR(INDEX(IMPORTRANGE(""1wF8uimz-gnzzmqfjHb8Ua7fudqcoq5SrFyToq2B2IO0"",""💸 Expenses!A5:J200""),3,1),"""")"),"") | B43: =IFERROR(__xludf.DUMMYFUNCTION("IFERROR(IF(INDEX(IMPORTRANGE(""1wF8uimz-gnzzmqfjHb8Ua7fudqcoq5SrFyToq2B2IO0"",""💸 Expenses!A5:J200""),3,2)="""","""",TEXT(INDEX(IMPORTRANGE(""1wF8uimz-gnzzmqfjHb8Ua7fudqcoq5SrFyToq2B2IO0"",""💸 Expenses!A5:J200""),3,2),""DD-MM-YYYY"")),"""")"),"") | C43: =IFERROR(__xludf.DUMMYFUNCTION("IFERROR(INDEX(IMPORTRANGE(""1wF8uimz-gnzzmqfjHb8Ua7fudqcoq5SrFyToq2B2IO0"",""💸 Expenses!A5:J200""),3,3),"""")"),"") | D43: =IFERROR(__xludf.DUMMYFUNCTION("IFERROR(INDEX(IMPORTRANGE(""1wF8uimz-gnzzmqfjHb8Ua7fudqcoq5SrFyToq2B2IO0"",""💸 Expenses!A5:J200""),3,4),"""")"),"") | E43: =IFERROR(__xludf.DUMMYFUNCTION("IFERROR(INDEX(IMPORTRANGE(""1wF8uimz-gnzzmqfjHb8Ua7fudqcoq5SrFyToq2B2IO0"",""💸 Expenses!A5:J200""),3,5),"""")"),"") | F43: =IFERROR(__xludf.DUMMYFUNCTION("IFERROR(IFERROR(INDEX(IMPORTRANGE(""1wF8uimz-gnzzmqfjHb8Ua7fudqcoq5SrFyToq2B2IO0"",""💸 Expenses!A5:J200""),3,6)*1,0),0)"),0.0) -> 0 | G43: =IFERROR(__xludf.DUMMYFUNCTION("IFERROR(INDEX(IMPORTRANGE(""1wF8uimz-gnzzmqfjHb8Ua7fudqcoq5SrFyToq2B2IO0"",""💸 Expenses!A5:J200""),3,7),"""")"),"") | H43: =IFERROR(__xludf.DUMMYFUNCTION("IFERROR(INDEX(IMPORTRANGE(""1wF8uimz-gnzzmqfjHb8Ua7fudqcoq5SrFyToq2B2IO0"",""💸 Expenses!A5:J200""),3,8),"""")"),"") | I43: =IFERROR(__xludf.DUMMYFUNCTION("IFERROR(INDEX(IMPORTRANGE(""1wF8uimz-gnzzmqfjHb8Ua7fudqcoq5SrFyToq2B2IO0"",""💸 Expenses!A5:J200""),3,9),"""")"),"") | J43: =IFERROR(__xludf.DUMMYFUNCTION("IFERROR(INDEX(IMPORTRANGE(""1wF8uimz-gnzzmqfjHb8Ua7fudqcoq5SrFyToq2B2IO0"",""💸 Expenses!A5:J200""),3,10),"""")"),"")
A44: =IFERROR(__xludf.DUMMYFUNCTION("IFERROR(INDEX(IMPORTRANGE(""1wF8uimz-gnzzmqfjHb8Ua7fudqcoq5SrFyToq2B2IO0"",""💸 Expenses!A5:J200""),4,1),"""")"),"") | B44: =IFERROR(__xludf.DUMMYFUNCTION("IFERROR(IF(INDEX(IMPORTRANGE(""1wF8uimz-gnzzmqfjHb8Ua7fudqcoq5SrFyToq2B2IO0"",""💸 Expenses!A5:J200""),4,2)="""","""",TEXT(INDEX(IMPORTRANGE(""1wF8uimz-gnzzmqfjHb8Ua7fudqcoq5SrFyToq2B2IO0"",""💸 Expenses!A5:J200""),4,2),""DD-MM-YYYY"")),"""")"),"") | C44: =IFERROR(__xludf.DUMMYFUNCTION("IFERROR(INDEX(IMPORTRANGE(""1wF8uimz-gnzzmqfjHb8Ua7fudqcoq5SrFyToq2B2IO0"",""💸 Expenses!A5:J200""),4,3),"""")"),"") | D44: =IFERROR(__xludf.DUMMYFUNCTION("IFERROR(INDEX(IMPORTRANGE(""1wF8uimz-gnzzmqfjHb8Ua7fudqcoq5SrFyToq2B2IO0"",""💸 Expenses!A5:J200""),4,4),"""")"),"") | E44: =IFERROR(__xludf.DUMMYFUNCTION("IFERROR(INDEX(IMPORTRANGE(""1wF8uimz-gnzzmqfjHb8Ua7fudqcoq5SrFyToq2B2IO0"",""💸 Expenses!A5:J200""),4,5),"""")"),"") | F44: =IFERROR(__xludf.DUMMYFUNCTION("IFERROR(IFERROR(INDEX(IMPORTRANGE(""1wF8uimz-gnzzmqfjHb8Ua7fudqcoq5SrFyToq2B2IO0"",""💸 Expenses!A5:J200""),4,6)*1,0),0)"),0.0) -> 0 | G44: =IFERROR(__xludf.DUMMYFUNCTION("IFERROR(INDEX(IMPORTRANGE(""1wF8uimz-gnzzmqfjHb8Ua7fudqcoq5SrFyToq2B2IO0"",""💸 Expenses!A5:J200""),4,7),"""")"),"") | H44: =IFERROR(__xludf.DUMMYFUNCTION("IFERROR(INDEX(IMPORTRANGE(""1wF8uimz-gnzzmqfjHb8Ua7fudqcoq5SrFyToq2B2IO0"",""💸 Expenses!A5:J200""),4,8),"""")"),"") | I44: =IFERROR(__xludf.DUMMYFUNCTION("IFERROR(INDEX(IMPORTRANGE(""1wF8uimz-gnzzmqfjHb8Ua7fudqcoq5SrFyToq2B2IO0"",""💸 Expenses!A5:J200""),4,9),"""")"),"") | J44: =IFERROR(__xludf.DUMMYFUNCTION("IFERROR(INDEX(IMPORTRANGE(""1wF8uimz-gnzzmqfjHb8Ua7fudqcoq5SrFyToq2B2IO0"",""💸 Expenses!A5:J200""),4,10),"""")"),"")
A45: =IFERROR(__xludf.DUMMYFUNCTION("IFERROR(INDEX(IMPORTRANGE(""1wF8uimz-gnzzmqfjHb8Ua7fudqcoq5SrFyToq2B2IO0"",""💸 Expenses!A5:J200""),5,1),"""")"),"") | B45: =IFERROR(__xludf.DUMMYFUNCTION("IFERROR(IF(INDEX(IMPORTRANGE(""1wF8uimz-gnzzmqfjHb8Ua7fudqcoq5SrFyToq2B2IO0"",""💸 Expenses!A5:J200""),5,2)="""","""",TEXT(INDEX(IMPORTRANGE(""1wF8uimz-gnzzmqfjHb8Ua7fudqcoq5SrFyToq2B2IO0"",""💸 Expenses!A5:J200""),5,2),""DD-MM-YYYY"")),"""")"),"") | C45: =IFERROR(__xludf.DUMMYFUNCTION("IFERROR(INDEX(IMPORTRANGE(""1wF8uimz-gnzzmqfjHb8Ua7fudqcoq5SrFyToq2B2IO0"",""💸 Expenses!A5:J200""),5,3),"""")"),"") | D45: =IFERROR(__xludf.DUMMYFUNCTION("IFERROR(INDEX(IMPORTRANGE(""1wF8uimz-gnzzmqfjHb8Ua7fudqcoq5SrFyToq2B2IO0"",""💸 Expenses!A5:J200""),5,4),"""")"),"") | E45: =IFERROR(__xludf.DUMMYFUNCTION("IFERROR(INDEX(IMPORTRANGE(""1wF8uimz-gnzzmqfjHb8Ua7fudqcoq5SrFyToq2B2IO0"",""💸 Expenses!A5:J200""),5,5),"""")"),"") | F45: =IFERROR(__xludf.DUMMYFUNCTION("IFERROR(IFERROR(INDEX(IMPORTRANGE(""1wF8uimz-gnzzmqfjHb8Ua7fudqcoq5SrFyToq2B2IO0"",""💸 Expenses!A5:J200""),5,6)*1,0),0)"),0.0) -> 0 | G45: =IFERROR(__xludf.DUMMYFUNCTION("IFERROR(INDEX(IMPORTRANGE(""1wF8uimz-gnzzmqfjHb8Ua7fudqcoq5SrFyToq2B2IO0"",""💸 Expenses!A5:J200""),5,7),"""")"),"") | H45: =IFERROR(__xludf.DUMMYFUNCTION("IFERROR(INDEX(IMPORTRANGE(""1wF8uimz-gnzzmqfjHb8Ua7fudqcoq5SrFyToq2B2IO0"",""💸 Expenses!A5:J200""),5,8),"""")"),"") | I45: =IFERROR(__xludf.DUMMYFUNCTION("IFERROR(INDEX(IMPORTRANGE(""1wF8uimz-gnzzmqfjHb8Ua7fudqcoq5SrFyToq2B2IO0"",""💸 Expenses!A5:J200""),5,9),"""")"),"") | J45: =IFERROR(__xludf.DUMMYFUNCTION("IFERROR(INDEX(IMPORTRANGE(""1wF8uimz-gnzzmqfjHb8Ua7fudqcoq5SrFyToq2B2IO0"",""💸 Expenses!A5:J200""),5,10),"""")"),"")
A46: =IFERROR(__xludf.DUMMYFUNCTION("IFERROR(INDEX(IMPORTRANGE(""1wF8uimz-gnzzmqfjHb8Ua7fudqcoq5SrFyToq2B2IO0"",""💸 Expenses!A5:J200""),6,1),"""")"),"") | B46: =IFERROR(__xludf.DUMMYFUNCTION("IFERROR(IF(INDEX(IMPORTRANGE(""1wF8uimz-gnzzmqfjHb8Ua7fudqcoq5SrFyToq2B2IO0"",""💸 Expenses!A5:J200""),6,2)="""","""",TEXT(INDEX(IMPORTRANGE(""1wF8uimz-gnzzmqfjHb8Ua7fudqcoq5SrFyToq2B2IO0"",""💸 Expenses!A5:J200""),6,2),""DD-MM-YYYY"")),"""")"),"") | C46: =IFERROR(__xludf.DUMMYFUNCTION("IFERROR(INDEX(IMPORTRANGE(""1wF8uimz-gnzzmqfjHb8Ua7fudqcoq5SrFyToq2B2IO0"",""💸 Expenses!A5:J200""),6,3),"""")"),"") | D46: =IFERROR(__xludf.DUMMYFUNCTION("IFERROR(INDEX(IMPORTRANGE(""1wF8uimz-gnzzmqfjHb8Ua7fudqcoq5SrFyToq2B2IO0"",""💸 Expenses!A5:J200""),6,4),"""")"),"") | E46: =IFERROR(__xludf.DUMMYFUNCTION("IFERROR(INDEX(IMPORTRANGE(""1wF8uimz-gnzzmqfjHb8Ua7fudqcoq5SrFyToq2B2IO0"",""💸 Expenses!A5:J200""),6,5),"""")"),"") | F46: =IFERROR(__xludf.DUMMYFUNCTION("IFERROR(IFERROR(INDEX(IMPORTRANGE(""1wF8uimz-gnzzmqfjHb8Ua7fudqcoq5SrFyToq2B2IO0"",""💸 Expenses!A5:J200""),6,6)*1,0),0)"),0.0) -> 0 | G46: =IFERROR(__xludf.DUMMYFUNCTION("IFERROR(INDEX(IMPORTRANGE(""1wF8uimz-gnzzmqfjHb8Ua7fudqcoq5SrFyToq2B2IO0"",""💸 Expenses!A5:J200""),6,7),"""")"),"") | H46: =IFERROR(__xludf.DUMMYFUNCTION("IFERROR(INDEX(IMPORTRANGE(""1wF8uimz-gnzzmqfjHb8Ua7fudqcoq5SrFyToq2B2IO0"",""💸 Expenses!A5:J200""),6,8),"""")"),"") | I46: =IFERROR(__xludf.DUMMYFUNCTION("IFERROR(INDEX(IMPORTRANGE(""1wF8uimz-gnzzmqfjHb8Ua7fudqcoq5SrFyToq2B2IO0"",""💸 Expenses!A5:J200""),6,9),"""")"),"") | J46: =IFERROR(__xludf.DUMMYFUNCTION("IFERROR(INDEX(IMPORTRANGE(""1wF8uimz-gnzzmqfjHb8Ua7fudqcoq5SrFyToq2B2IO0"",""💸 Expenses!A5:J200""),6,10),"""")"),"")
A47: =IFERROR(__xludf.DUMMYFUNCTION("IFERROR(INDEX(IMPORTRANGE(""1wF8uimz-gnzzmqfjHb8Ua7fudqcoq5SrFyToq2B2IO0"",""💸 Expenses!A5:J200""),7,1),"""")"),"") | B47: =IFERROR(__xludf.DUMMYFUNCTION("IFERROR(IF(INDEX(IMPORTRANGE(""1wF8uimz-gnzzmqfjHb8Ua7fudqcoq5SrFyToq2B2IO0"",""💸 Expenses!A5:J200""),7,2)="""","""",TEXT(INDEX(IMPORTRANGE(""1wF8uimz-gnzzmqfjHb8Ua7fudqcoq5SrFyToq2B2IO0"",""💸 Expenses!A5:J200""),7,2),""DD-MM-YYYY"")),"""")"),"") | C47: =IFERROR(__xludf.DUMMYFUNCTION("IFERROR(INDEX(IMPORTRANGE(""1wF8uimz-gnzzmqfjHb8Ua7fudqcoq5SrFyToq2B2IO0"",""💸 Expenses!A5:J200""),7,3),"""")"),"") | D47: =IFERROR(__xludf.DUMMYFUNCTION("IFERROR(INDEX(IMPORTRANGE(""1wF8uimz-gnzzmqfjHb8Ua7fudqcoq5SrFyToq2B2IO0"",""💸 Expenses!A5:J200""),7,4),"""")"),"") | E47: =IFERROR(__xludf.DUMMYFUNCTION("IFERROR(INDEX(IMPORTRANGE(""1wF8uimz-gnzzmqfjHb8Ua7fudqcoq5SrFyToq2B2IO0"",""💸 Expenses!A5:J200""),7,5),"""")"),"") | F47: =IFERROR(__xludf.DUMMYFUNCTION("IFERROR(IFERROR(INDEX(IMPORTRANGE(""1wF8uimz-gnzzmqfjHb8Ua7fudqcoq5SrFyToq2B2IO0"",""💸 Expenses!A5:J200""),7,6)*1,0),0)"),0.0) -> 0 | G47: =IFERROR(__xludf.DUMMYFUNCTION("IFERROR(INDEX(IMPORTRANGE(""1wF8uimz-gnzzmqfjHb8Ua7fudqcoq5SrFyToq2B2IO0"",""💸 Expenses!A5:J200""),7,7),"""")"),"") | H47: =IFERROR(__xludf.DUMMYFUNCTION("IFERROR(INDEX(IMPORTRANGE(""1wF8uimz-gnzzmqfjHb8Ua7fudqcoq5SrFyToq2B2IO0"",""💸 Expenses!A5:J200""),7,8),"""")"),"") | I47: =IFERROR(__xludf.DUMMYFUNCTION("IFERROR(INDEX(IMPORTRANGE(""1wF8uimz-gnzzmqfjHb8Ua7fudqcoq5SrFyToq2B2IO0"",""💸 Expenses!A5:J200""),7,9),"""")"),"") | J47: =IFERROR(__xludf.DUMMYFUNCTION("IFERROR(INDEX(IMPORTRANGE(""1wF8uimz-gnzzmqfjHb8Ua7fudqcoq5SrFyToq2B2IO0"",""💸 Expenses!A5:J200""),7,10),"""")"),"")
A48: =IFERROR(__xludf.DUMMYFUNCTION("IFERROR(INDEX(IMPORTRANGE(""1wF8uimz-gnzzmqfjHb8Ua7fudqcoq5SrFyToq2B2IO0"",""💸 Expenses!A5:J200""),8,1),"""")"),"") | B48: =IFERROR(__xludf.DUMMYFUNCTION("IFERROR(IF(INDEX(IMPORTRANGE(""1wF8uimz-gnzzmqfjHb8Ua7fudqcoq5SrFyToq2B2IO0"",""💸 Expenses!A5:J200""),8,2)="""","""",TEXT(INDEX(IMPORTRANGE(""1wF8uimz-gnzzmqfjHb8Ua7fudqcoq5SrFyToq2B2IO0"",""💸 Expenses!A5:J200""),8,2),""DD-MM-YYYY"")),"""")"),"") | C48: =IFERROR(__xludf.DUMMYFUNCTION("IFERROR(INDEX(IMPORTRANGE(""1wF8uimz-gnzzmqfjHb8Ua7fudqcoq5SrFyToq2B2IO0"",""💸 Expenses!A5:J200""),8,3),"""")"),"") | D48: =IFERROR(__xludf.DUMMYFUNCTION("IFERROR(INDEX(IMPORTRANGE(""1wF8uimz-gnzzmqfjHb8Ua7fudqcoq5SrFyToq2B2IO0"",""💸 Expenses!A5:J200""),8,4),"""")"),"") | E48: =IFERROR(__xludf.DUMMYFUNCTION("IFERROR(INDEX(IMPORTRANGE(""1wF8uimz-gnzzmqfjHb8Ua7fudqcoq5SrFyToq2B2IO0"",""💸 Expenses!A5:J200""),8,5),"""")"),"") | F48: =IFERROR(__xludf.DUMMYFUNCTION("IFERROR(IFERROR(INDEX(IMPORTRANGE(""1wF8uimz-gnzzmqfjHb8Ua7fudqcoq5SrFyToq2B2IO0"",""💸 Expenses!A5:J200""),8,6)*1,0),0)"),0.0) -> 0 | G48: =IFERROR(__xludf.DUMMYFUNCTION("IFERROR(INDEX(IMPORTRANGE(""1wF8uimz-gnzzmqfjHb8Ua7fudqcoq5SrFyToq2B2IO0"",""💸 Expenses!A5:J200""),8,7),"""")"),"") | H48: =IFERROR(__xludf.DUMMYFUNCTION("IFERROR(INDEX(IMPORTRANGE(""1wF8uimz-gnzzmqfjHb8Ua7fudqcoq5SrFyToq2B2IO0"",""💸 Expenses!A5:J200""),8,8),"""")"),"") | I48: =IFERROR(__xludf.DUMMYFUNCTION("IFERROR(INDEX(IMPORTRANGE(""1wF8uimz-gnzzmqfjHb8Ua7fudqcoq5SrFyToq2B2IO0"",""💸 Expenses!A5:J200""),8,9),"""")"),"") | J48: =IFERROR(__xludf.DUMMYFUNCTION("IFERROR(INDEX(IMPORTRANGE(""1wF8uimz-gnzzmqfjHb8Ua7fudqcoq5SrFyToq2B2IO0"",""💸 Expenses!A5:J200""),8,10),"""")"),"")
A49: =IFERROR(__xludf.DUMMYFUNCTION("IFERROR(INDEX(IMPORTRANGE(""1wF8uimz-gnzzmqfjHb8Ua7fudqcoq5SrFyToq2B2IO0"",""💸 Expenses!A5:J200""),9,1),"""")"),"") | B49: =IFERROR(__xludf.DUMMYFUNCTION("IFERROR(IF(INDEX(IMPORTRANGE(""1wF8uimz-gnzzmqfjHb8Ua7fudqcoq5SrFyToq2B2IO0"",""💸 Expenses!A5:J200""),9,2)="""","""",TEXT(INDEX(IMPORTRANGE(""1wF8uimz-gnzzmqfjHb8Ua7fudqcoq5SrFyToq2B2IO0"",""💸 Expenses!A5:J200""),9,2),""DD-MM-YYYY"")),"""")"),"") | C49: =IFERROR(__xludf.DUMMYFUNCTION("IFERROR(INDEX(IMPORTRANGE(""1wF8uimz-gnzzmqfjHb8Ua7fudqcoq5SrFyToq2B2IO0"",""💸 Expenses!A5:J200""),9,3),"""")"),"") | D49: =IFERROR(__xludf.DUMMYFUNCTION("IFERROR(INDEX(IMPORTRANGE(""1wF8uimz-gnzzmqfjHb8Ua7fudqcoq5SrFyToq2B2IO0"",""💸 Expenses!A5:J200""),9,4),"""")"),"") | E49: =IFERROR(__xludf.DUMMYFUNCTION("IFERROR(INDEX(IMPORTRANGE(""1wF8uimz-gnzzmqfjHb8Ua7fudqcoq5SrFyToq2B2IO0"",""💸 Expenses!A5:J200""),9,5),"""")"),"") | F49: =IFERROR(__xludf.DUMMYFUNCTION("IFERROR(IFERROR(INDEX(IMPORTRANGE(""1wF8uimz-gnzzmqfjHb8Ua7fudqcoq5SrFyToq2B2IO0"",""💸 Expenses!A5:J200""),9,6)*1,0),0)"),0.0) -> 0 | G49: =IFERROR(__xludf.DUMMYFUNCTION("IFERROR(INDEX(IMPORTRANGE(""1wF8uimz-gnzzmqfjHb8Ua7fudqcoq5SrFyToq2B2IO0"",""💸 Expenses!A5:J200""),9,7),"""")"),"") | H49: =IFERROR(__xludf.DUMMYFUNCTION("IFERROR(INDEX(IMPORTRANGE(""1wF8uimz-gnzzmqfjHb8Ua7fudqcoq5SrFyToq2B2IO0"",""💸 Expenses!A5:J200""),9,8),"""")"),"") | I49: =IFERROR(__xludf.DUMMYFUNCTION("IFERROR(INDEX(IMPORTRANGE(""1wF8uimz-gnzzmqfjHb8Ua7fudqcoq5SrFyToq2B2IO0"",""💸 Expenses!A5:J200""),9,9),"""")"),"") | J49: =IFERROR(__xludf.DUMMYFUNCTION("IFERROR(INDEX(IMPORTRANGE(""1wF8uimz-gnzzmqfjHb8Ua7fudqcoq5SrFyToq2B2IO0"",""💸 Expenses!A5:J200""),9,10),"""")"),"")
A50: =IFERROR(__xludf.DUMMYFUNCTION("IFERROR(INDEX(IMPORTRANGE(""1wF8uimz-gnzzmqfjHb8Ua7fudqcoq5SrFyToq2B2IO0"",""💸 Expenses!A5:J200""),10,1),"""")"),"") | B50: =IFERROR(__xludf.DUMMYFUNCTION("IFERROR(IF(INDEX(IMPORTRANGE(""1wF8uimz-gnzzmqfjHb8Ua7fudqcoq5SrFyToq2B2IO0"",""💸 Expenses!A5:J200""),10,2)="""","""",TEXT(INDEX(IMPORTRANGE(""1wF8uimz-gnzzmqfjHb8Ua7fudqcoq5SrFyToq2B2IO0"",""💸 Expenses!A5:J200""),10,2),""DD-MM-YYYY"")),"""")"),"") | C50: =IFERROR(__xludf.DUMMYFUNCTION("IFERROR(INDEX(IMPORTRANGE(""1wF8uimz-gnzzmqfjHb8Ua7fudqcoq5SrFyToq2B2IO0"",""💸 Expenses!A5:J200""),10,3),"""")"),"") | D50: =IFERROR(__xludf.DUMMYFUNCTION("IFERROR(INDEX(IMPORTRANGE(""1wF8uimz-gnzzmqfjHb8Ua7fudqcoq5SrFyToq2B2IO0"",""💸 Expenses!A5:J200""),10,4),"""")"),"") | E50: =IFERROR(__xludf.DUMMYFUNCTION("IFERROR(INDEX(IMPORTRANGE(""1wF8uimz-gnzzmqfjHb8Ua7fudqcoq5SrFyToq2B2IO0"",""💸 Expenses!A5:J200""),10,5),"""")"),"") | F50: =IFERROR(__xludf.DUMMYFUNCTION("IFERROR(IFERROR(INDEX(IMPORTRANGE(""1wF8uimz-gnzzmqfjHb8Ua7fudqcoq5SrFyToq2B2IO0"",""💸 Expenses!A5:J200""),10,6)*1,0),0)"),0.0) -> 0 | G50: =IFERROR(__xludf.DUMMYFUNCTION("IFERROR(INDEX(IMPORTRANGE(""1wF8uimz-gnzzmqfjHb8Ua7fudqcoq5SrFyToq2B2IO0"",""💸 Expenses!A5:J200""),10,7),"""")"),"") | H50: =IFERROR(__xludf.DUMMYFUNCTION("IFERROR(INDEX(IMPORTRANGE(""1wF8uimz-gnzzmqfjHb8Ua7fudqcoq5SrFyToq2B2IO0"",""💸 Expenses!A5:J200""),10,8),"""")"),"") | I50: =IFERROR(__xludf.DUMMYFUNCTION("IFERROR(INDEX(IMPORTRANGE(""1wF8uimz-gnzzmqfjHb8Ua7fudqcoq5SrFyToq2B2IO0"",""💸 Expenses!A5:J200""),10,9),"""")"),"") | J50: =IFERROR(__xludf.DUMMYFUNCTION("IFERROR(INDEX(IMPORTRANGE(""1wF8uimz-gnzzmqfjHb8Ua7fudqcoq5SrFyToq2B2IO0"",""💸 Expenses!A5:J200""),10,10),"""")"),"")
A51: =IFERROR(__xludf.DUMMYFUNCTION("IFERROR(INDEX(IMPORTRANGE(""1wF8uimz-gnzzmqfjHb8Ua7fudqcoq5SrFyToq2B2IO0"",""💸 Expenses!A5:J200""),11,1),"""")"),"") | B51: =IFERROR(__xludf.DUMMYFUNCTION("IFERROR(IF(INDEX(IMPORTRANGE(""1wF8uimz-gnzzmqfjHb8Ua7fudqcoq5SrFyToq2B2IO0"",""💸 Expenses!A5:J200""),11,2)="""","""",TEXT(INDEX(IMPORTRANGE(""1wF8uimz-gnzzmqfjHb8Ua7fudqcoq5SrFyToq2B2IO0"",""💸 Expenses!A5:J200""),11,2),""DD-MM-YYYY"")),"""")"),"") | C51: =IFERROR(__xludf.DUMMYFUNCTION("IFERROR(INDEX(IMPORTRANGE(""1wF8uimz-gnzzmqfjHb8Ua7fudqcoq5SrFyToq2B2IO0"",""💸 Expenses!A5:J200""),11,3),"""")"),"") | D51: =IFERROR(__xludf.DUMMYFUNCTION("IFERROR(INDEX(IMPORTRANGE(""1wF8uimz-gnzzmqfjHb8Ua7fudqcoq5SrFyToq2B2IO0"",""💸 Expenses!A5:J200""),11,4),"""")"),"") | E51: =IFERROR(__xludf.DUMMYFUNCTION("IFERROR(INDEX(IMPORTRANGE(""1wF8uimz-gnzzmqfjHb8Ua7fudqcoq5SrFyToq2B2IO0"",""💸 Expenses!A5:J200""),11,5),"""")"),"") | F51: =IFERROR(__xludf.DUMMYFUNCTION("IFERROR(IFERROR(INDEX(IMPORTRANGE(""1wF8uimz-gnzzmqfjHb8Ua7fudqcoq5SrFyToq2B2IO0"",""💸 Expenses!A5:J200""),11,6)*1,0),0)"),0.0) -> 0 | G51: =IFERROR(__xludf.DUMMYFUNCTION("IFERROR(INDEX(IMPORTRANGE(""1wF8uimz-gnzzmqfjHb8Ua7fudqcoq5SrFyToq2B2IO0"",""💸 Expenses!A5:J200""),11,7),"""")"),"") | H51: =IFERROR(__xludf.DUMMYFUNCTION("IFERROR(INDEX(IMPORTRANGE(""1wF8uimz-gnzzmqfjHb8Ua7fudqcoq5SrFyToq2B2IO0"",""💸 Expenses!A5:J200""),11,8),"""")"),"") | I51: =IFERROR(__xludf.DUMMYFUNCTION("IFERROR(INDEX(IMPORTRANGE(""1wF8uimz-gnzzmqfjHb8Ua7fudqcoq5SrFyToq2B2IO0"",""💸 Expenses!A5:J200""),11,9),"""")"),"") | J51: =IFERROR(__xludf.DUMMYFUNCTION("IFERROR(INDEX(IMPORTRANGE(""1wF8uimz-gnzzmqfjHb8Ua7fudqcoq5SrFyToq2B2IO0"",""💸 Expenses!A5:J200""),11,10),"""")"),"")
A52: =IFERROR(__xludf.DUMMYFUNCTION("IFERROR(INDEX(IMPORTRANGE(""1wF8uimz-gnzzmqfjHb8Ua7fudqcoq5SrFyToq2B2IO0"",""💸 Expenses!A5:J200""),12,1),"""")"),"") | B52: =IFERROR(__xludf.DUMMYFUNCTION("IFERROR(IF(INDEX(IMPORTRANGE(""1wF8uimz-gnzzmqfjHb8Ua7fudqcoq5SrFyToq2B2IO0"",""💸 Expenses!A5:J200""),12,2)="""","""",TEXT(INDEX(IMPORTRANGE(""1wF8uimz-gnzzmqfjHb8Ua7fudqcoq5SrFyToq2B2IO0"",""💸 Expenses!A5:J200""),12,2),""DD-MM-YYYY"")),"""")"),"") | C52: =IFERROR(__xludf.DUMMYFUNCTION("IFERROR(INDEX(IMPORTRANGE(""1wF8uimz-gnzzmqfjHb8Ua7fudqcoq5SrFyToq2B2IO0"",""💸 Expenses!A5:J200""),12,3),"""")"),"") | D52: =IFERROR(__xludf.DUMMYFUNCTION("IFERROR(INDEX(IMPORTRANGE(""1wF8uimz-gnzzmqfjHb8Ua7fudqcoq5SrFyToq2B2IO0"",""💸 Expenses!A5:J200""),12,4),"""")"),"") | E52: =IFERROR(__xludf.DUMMYFUNCTION("IFERROR(INDEX(IMPORTRANGE(""1wF8uimz-gnzzmqfjHb8Ua7fudqcoq5SrFyToq2B2IO0"",""💸 Expenses!A5:J200""),12,5),"""")"),"") | F52: =IFERROR(__xludf.DUMMYFUNCTION("IFERROR(IFERROR(INDEX(IMPORTRANGE(""1wF8uimz-gnzzmqfjHb8Ua7fudqcoq5SrFyToq2B2IO0"",""💸 Expenses!A5:J200""),12,6)*1,0),0)"),0.0) -> 0 | G52: =IFERROR(__xludf.DUMMYFUNCTION("IFERROR(INDEX(IMPORTRANGE(""1wF8uimz-gnzzmqfjHb8Ua7fudqcoq5SrFyToq2B2IO0"",""💸 Expenses!A5:J200""),12,7),"""")"),"") | H52: =IFERROR(__xludf.DUMMYFUNCTION("IFERROR(INDEX(IMPORTRANGE(""1wF8uimz-gnzzmqfjHb8Ua7fudqcoq5SrFyToq2B2IO0"",""💸 Expenses!A5:J200""),12,8),"""")"),"") | I52: =IFERROR(__xludf.DUMMYFUNCTION("IFERROR(INDEX(IMPORTRANGE(""1wF8uimz-gnzzmqfjHb8Ua7fudqcoq5SrFyToq2B2IO0"",""💸 Expenses!A5:J200""),12,9),"""")"),"") | J52: =IFERROR(__xludf.DUMMYFUNCTION("IFERROR(INDEX(IMPORTRANGE(""1wF8uimz-gnzzmqfjHb8Ua7fudqcoq5SrFyToq2B2IO0"",""💸 Expenses!A5:J200""),12,10),"""")"),"")
A53: =IFERROR(__xludf.DUMMYFUNCTION("IFERROR(INDEX(IMPORTRANGE(""1wF8uimz-gnzzmqfjHb8Ua7fudqcoq5SrFyToq2B2IO0"",""💸 Expenses!A5:J200""),13,1),"""")"),"") | B53: =IFERROR(__xludf.DUMMYFUNCTION("IFERROR(IF(INDEX(IMPORTRANGE(""1wF8uimz-gnzzmqfjHb8Ua7fudqcoq5SrFyToq2B2IO0"",""💸 Expenses!A5:J200""),13,2)="""","""",TEXT(INDEX(IMPORTRANGE(""1wF8uimz-gnzzmqfjHb8Ua7fudqcoq5SrFyToq2B2IO0"",""💸 Expenses!A5:J200""),13,2),""DD-MM-YYYY"")),"""")"),"") | C53: =IFERROR(__xludf.DUMMYFUNCTION("IFERROR(INDEX(IMPORTRANGE(""1wF8uimz-gnzzmqfjHb8Ua7fudqcoq5SrFyToq2B2IO0"",""💸 Expenses!A5:J200""),13,3),"""")"),"") | D53: =IFERROR(__xludf.DUMMYFUNCTION("IFERROR(INDEX(IMPORTRANGE(""1wF8uimz-gnzzmqfjHb8Ua7fudqcoq5SrFyToq2B2IO0"",""💸 Expenses!A5:J200""),13,4),"""")"),"") | E53: =IFERROR(__xludf.DUMMYFUNCTION("IFERROR(INDEX(IMPORTRANGE(""1wF8uimz-gnzzmqfjHb8Ua7fudqcoq5SrFyToq2B2IO0"",""💸 Expenses!A5:J200""),13,5),"""")"),"") | F53: =IFERROR(__xludf.DUMMYFUNCTION("IFERROR(IFERROR(INDEX(IMPORTRANGE(""1wF8uimz-gnzzmqfjHb8Ua7fudqcoq5SrFyToq2B2IO0"",""💸 Expenses!A5:J200""),13,6)*1,0),0)"),0.0) -> 0 | G53: =IFERROR(__xludf.DUMMYFUNCTION("IFERROR(INDEX(IMPORTRANGE(""1wF8uimz-gnzzmqfjHb8Ua7fudqcoq5SrFyToq2B2IO0"",""💸 Expenses!A5:J200""),13,7),"""")"),"") | H53: =IFERROR(__xludf.DUMMYFUNCTION("IFERROR(INDEX(IMPORTRANGE(""1wF8uimz-gnzzmqfjHb8Ua7fudqcoq5SrFyToq2B2IO0"",""💸 Expenses!A5:J200""),13,8),"""")"),"") | I53: =IFERROR(__xludf.DUMMYFUNCTION("IFERROR(INDEX(IMPORTRANGE(""1wF8uimz-gnzzmqfjHb8Ua7fudqcoq5SrFyToq2B2IO0"",""💸 Expenses!A5:J200""),13,9),"""")"),"") | J53: =IFERROR(__xludf.DUMMYFUNCTION("IFERROR(INDEX(IMPORTRANGE(""1wF8uimz-gnzzmqfjHb8Ua7fudqcoq5SrFyToq2B2IO0"",""💸 Expenses!A5:J200""),13,10),"""")"),"")
A54: =IFERROR(__xludf.DUMMYFUNCTION("IFERROR(INDEX(IMPORTRANGE(""1wF8uimz-gnzzmqfjHb8Ua7fudqcoq5SrFyToq2B2IO0"",""💸 Expenses!A5:J200""),14,1),"""")"),"") | B54: =IFERROR(__xludf.DUMMYFUNCTION("IFERROR(IF(INDEX(IMPORTRANGE(""1wF8uimz-gnzzmqfjHb8Ua7fudqcoq5SrFyToq2B2IO0"",""💸 Expenses!A5:J200""),14,2)="""","""",TEXT(INDEX(IMPORTRANGE(""1wF8uimz-gnzzmqfjHb8Ua7fudqcoq5SrFyToq2B2IO0"",""💸 Expenses!A5:J200""),14,2),""DD-MM-YYYY"")),"""")"),"") | C54: =IFERROR(__xludf.DUMMYFUNCTION("IFERROR(INDEX(IMPORTRANGE(""1wF8uimz-gnzzmqfjHb8Ua7fudqcoq5SrFyToq2B2IO0"",""💸 Expenses!A5:J200""),14,3),"""")"),"") | D54: =IFERROR(__xludf.DUMMYFUNCTION("IFERROR(INDEX(IMPORTRANGE(""1wF8uimz-gnzzmqfjHb8Ua7fudqcoq5SrFyToq2B2IO0"",""💸 Expenses!A5:J200""),14,4),"""")"),"") | E54: =IFERROR(__xludf.DUMMYFUNCTION("IFERROR(INDEX(IMPORTRANGE(""1wF8uimz-gnzzmqfjHb8Ua7fudqcoq5SrFyToq2B2IO0"",""💸 Expenses!A5:J200""),14,5),"""")"),"") | F54: =IFERROR(__xludf.DUMMYFUNCTION("IFERROR(IFERROR(INDEX(IMPORTRANGE(""1wF8uimz-gnzzmqfjHb8Ua7fudqcoq5SrFyToq2B2IO0"",""💸 Expenses!A5:J200""),14,6)*1,0),0)"),0.0) -> 0 | G54: =IFERROR(__xludf.DUMMYFUNCTION("IFERROR(INDEX(IMPORTRANGE(""1wF8uimz-gnzzmqfjHb8Ua7fudqcoq5SrFyToq2B2IO0"",""💸 Expenses!A5:J200""),14,7),"""")"),"") | H54: =IFERROR(__xludf.DUMMYFUNCTION("IFERROR(INDEX(IMPORTRANGE(""1wF8uimz-gnzzmqfjHb8Ua7fudqcoq5SrFyToq2B2IO0"",""💸 Expenses!A5:J200""),14,8),"""")"),"") | I54: =IFERROR(__xludf.DUMMYFUNCTION("IFERROR(INDEX(IMPORTRANGE(""1wF8uimz-gnzzmqfjHb8Ua7fudqcoq5SrFyToq2B2IO0"",""💸 Expenses!A5:J200""),14,9),"""")"),"") | J54: =IFERROR(__xludf.DUMMYFUNCTION("IFERROR(INDEX(IMPORTRANGE(""1wF8uimz-gnzzmqfjHb8Ua7fudqcoq5SrFyToq2B2IO0"",""💸 Expenses!A5:J200""),14,10),"""")"),"")
A55: =IFERROR(__xludf.DUMMYFUNCTION("IFERROR(INDEX(IMPORTRANGE(""1wF8uimz-gnzzmqfjHb8Ua7fudqcoq5SrFyToq2B2IO0"",""💸 Expenses!A5:J200""),15,1),"""")"),"") | B55: =IFERROR(__xludf.DUMMYFUNCTION("IFERROR(IF(INDEX(IMPORTRANGE(""1wF8uimz-gnzzmqfjHb8Ua7fudqcoq5SrFyToq2B2IO0"",""💸 Expenses!A5:J200""),15,2)="""","""",TEXT(INDEX(IMPORTRANGE(""1wF8uimz-gnzzmqfjHb8Ua7fudqcoq5SrFyToq2B2IO0"",""💸 Expenses!A5:J200""),15,2),""DD-MM-YYYY"")),"""")"),"") | C55: =IFERROR(__xludf.DUMMYFUNCTION("IFERROR(INDEX(IMPORTRANGE(""1wF8uimz-gnzzmqfjHb8Ua7fudqcoq5SrFyToq2B2IO0"",""💸 Expenses!A5:J200""),15,3),"""")"),"") | D55: =IFERROR(__xludf.DUMMYFUNCTION("IFERROR(INDEX(IMPORTRANGE(""1wF8uimz-gnzzmqfjHb8Ua7fudqcoq5SrFyToq2B2IO0"",""💸 Expenses!A5:J200""),15,4),"""")"),"") | E55: =IFERROR(__xludf.DUMMYFUNCTION("IFERROR(INDEX(IMPORTRANGE(""1wF8uimz-gnzzmqfjHb8Ua7fudqcoq5SrFyToq2B2IO0"",""💸 Expenses!A5:J200""),15,5),"""")"),"") | F55: =IFERROR(__xludf.DUMMYFUNCTION("IFERROR(IFERROR(INDEX(IMPORTRANGE(""1wF8uimz-gnzzmqfjHb8Ua7fudqcoq5SrFyToq2B2IO0"",""💸 Expenses!A5:J200""),15,6)*1,0),0)"),0.0) -> 0 | G55: =IFERROR(__xludf.DUMMYFUNCTION("IFERROR(INDEX(IMPORTRANGE(""1wF8uimz-gnzzmqfjHb8Ua7fudqcoq5SrFyToq2B2IO0"",""💸 Expenses!A5:J200""),15,7),"""")"),"") | H55: =IFERROR(__xludf.DUMMYFUNCTION("IFERROR(INDEX(IMPORTRANGE(""1wF8uimz-gnzzmqfjHb8Ua7fudqcoq5SrFyToq2B2IO0"",""💸 Expenses!A5:J200""),15,8),"""")"),"") | I55: =IFERROR(__xludf.DUMMYFUNCTION("IFERROR(INDEX(IMPORTRANGE(""1wF8uimz-gnzzmqfjHb8Ua7fudqcoq5SrFyToq2B2IO0"",""💸 Expenses!A5:J200""),15,9),"""")"),"") | J55: =IFERROR(__xludf.DUMMYFUNCTION("IFERROR(INDEX(IMPORTRANGE(""1wF8uimz-gnzzmqfjHb8Ua7fudqcoq5SrFyToq2B2IO0"",""💸 Expenses!A5:J200""),15,10),"""")"),"")
A56: =IFERROR(__xludf.DUMMYFUNCTION("IFERROR(INDEX(IMPORTRANGE(""1wF8uimz-gnzzmqfjHb8Ua7fudqcoq5SrFyToq2B2IO0"",""💸 Expenses!A5:J200""),16,1),"""")"),"") | B56: =IFERROR(__xludf.DUMMYFUNCTION("IFERROR(IF(INDEX(IMPORTRANGE(""1wF8uimz-gnzzmqfjHb8Ua7fudqcoq5SrFyToq2B2IO0"",""💸 Expenses!A5:J200""),16,2)="""","""",TEXT(INDEX(IMPORTRANGE(""1wF8uimz-gnzzmqfjHb8Ua7fudqcoq5SrFyToq2B2IO0"",""💸 Expenses!A5:J200""),16,2),""DD-MM-YYYY"")),"""")"),"") | C56: =IFERROR(__xludf.DUMMYFUNCTION("IFERROR(INDEX(IMPORTRANGE(""1wF8uimz-gnzzmqfjHb8Ua7fudqcoq5SrFyToq2B2IO0"",""💸 Expenses!A5:J200""),16,3),"""")"),"") | D56: =IFERROR(__xludf.DUMMYFUNCTION("IFERROR(INDEX(IMPORTRANGE(""1wF8uimz-gnzzmqfjHb8Ua7fudqcoq5SrFyToq2B2IO0"",""💸 Expenses!A5:J200""),16,4),"""")"),"") | E56: =IFERROR(__xludf.DUMMYFUNCTION("IFERROR(INDEX(IMPORTRANGE(""1wF8uimz-gnzzmqfjHb8Ua7fudqcoq5SrFyToq2B2IO0"",""💸 Expenses!A5:J200""),16,5),"""")"),"") | F56: =IFERROR(__xludf.DUMMYFUNCTION("IFERROR(IFERROR(INDEX(IMPORTRANGE(""1wF8uimz-gnzzmqfjHb8Ua7fudqcoq5SrFyToq2B2IO0"",""💸 Expenses!A5:J200""),16,6)*1,0),0)"),0.0) -> 0 | G56: =IFERROR(__xludf.DUMMYFUNCTION("IFERROR(INDEX(IMPORTRANGE(""1wF8uimz-gnzzmqfjHb8Ua7fudqcoq5SrFyToq2B2IO0"",""💸 Expenses!A5:J200""),16,7),"""")"),"") | H56: =IFERROR(__xludf.DUMMYFUNCTION("IFERROR(INDEX(IMPORTRANGE(""1wF8uimz-gnzzmqfjHb8Ua7fudqcoq5SrFyToq2B2IO0"",""💸 Expenses!A5:J200""),16,8),"""")"),"") | I56: =IFERROR(__xludf.DUMMYFUNCTION("IFERROR(INDEX(IMPORTRANGE(""1wF8uimz-gnzzmqfjHb8Ua7fudqcoq5SrFyToq2B2IO0"",""💸 Expenses!A5:J200""),16,9),"""")"),"") | J56: =IFERROR(__xludf.DUMMYFUNCTION("IFERROR(INDEX(IMPORTRANGE(""1wF8uimz-gnzzmqfjHb8Ua7fudqcoq5SrFyToq2B2IO0"",""💸 Expenses!A5:J200""),16,10),"""")"),"")
A57: =IFERROR(__xludf.DUMMYFUNCTION("IFERROR(INDEX(IMPORTRANGE(""1wF8uimz-gnzzmqfjHb8Ua7fudqcoq5SrFyToq2B2IO0"",""💸 Expenses!A5:J200""),17,1),"""")"),"") | B57: =IFERROR(__xludf.DUMMYFUNCTION("IFERROR(IF(INDEX(IMPORTRANGE(""1wF8uimz-gnzzmqfjHb8Ua7fudqcoq5SrFyToq2B2IO0"",""💸 Expenses!A5:J200""),17,2)="""","""",TEXT(INDEX(IMPORTRANGE(""1wF8uimz-gnzzmqfjHb8Ua7fudqcoq5SrFyToq2B2IO0"",""💸 Expenses!A5:J200""),17,2),""DD-MM-YYYY"")),"""")"),"") | C57: =IFERROR(__xludf.DUMMYFUNCTION("IFERROR(INDEX(IMPORTRANGE(""1wF8uimz-gnzzmqfjHb8Ua7fudqcoq5SrFyToq2B2IO0"",""💸 Expenses!A5:J200""),17,3),"""")"),"") | D57: =IFERROR(__xludf.DUMMYFUNCTION("IFERROR(INDEX(IMPORTRANGE(""1wF8uimz-gnzzmqfjHb8Ua7fudqcoq5SrFyToq2B2IO0"",""💸 Expenses!A5:J200""),17,4),"""")"),"") | E57: =IFERROR(__xludf.DUMMYFUNCTION("IFERROR(INDEX(IMPORTRANGE(""1wF8uimz-gnzzmqfjHb8Ua7fudqcoq5SrFyToq2B2IO0"",""💸 Expenses!A5:J200""),17,5),"""")"),"") | F57: =IFERROR(__xludf.DUMMYFUNCTION("IFERROR(IFERROR(INDEX(IMPORTRANGE(""1wF8uimz-gnzzmqfjHb8Ua7fudqcoq5SrFyToq2B2IO0"",""💸 Expenses!A5:J200""),17,6)*1,0),0)"),0.0) -> 0 | G57: =IFERROR(__xludf.DUMMYFUNCTION("IFERROR(INDEX(IMPORTRANGE(""1wF8uimz-gnzzmqfjHb8Ua7fudqcoq5SrFyToq2B2IO0"",""💸 Expenses!A5:J200""),17,7),"""")"),"") | H57: =IFERROR(__xludf.DUMMYFUNCTION("IFERROR(INDEX(IMPORTRANGE(""1wF8uimz-gnzzmqfjHb8Ua7fudqcoq5SrFyToq2B2IO0"",""💸 Expenses!A5:J200""),17,8),"""")"),"") | I57: =IFERROR(__xludf.DUMMYFUNCTION("IFERROR(INDEX(IMPORTRANGE(""1wF8uimz-gnzzmqfjHb8Ua7fudqcoq5SrFyToq2B2IO0"",""💸 Expenses!A5:J200""),17,9),"""")"),"") | J57: =IFERROR(__xludf.DUMMYFUNCTION("IFERROR(INDEX(IMPORTRANGE(""1wF8uimz-gnzzmqfjHb8Ua7fudqcoq5SrFyToq2B2IO0"",""💸 Expenses!A5:J200""),17,10),"""")"),"")
A58: =IFERROR(__xludf.DUMMYFUNCTION("IFERROR(INDEX(IMPORTRANGE(""1wF8uimz-gnzzmqfjHb8Ua7fudqcoq5SrFyToq2B2IO0"",""💸 Expenses!A5:J200""),18,1),"""")"),"") | B58: =IFERROR(__xludf.DUMMYFUNCTION("IFERROR(IF(INDEX(IMPORTRANGE(""1wF8uimz-gnzzmqfjHb8Ua7fudqcoq5SrFyToq2B2IO0"",""💸 Expenses!A5:J200""),18,2)="""","""",TEXT(INDEX(IMPORTRANGE(""1wF8uimz-gnzzmqfjHb8Ua7fudqcoq5SrFyToq2B2IO0"",""💸 Expenses!A5:J200""),18,2),""DD-MM-YYYY"")),"""")"),"") | C58: =IFERROR(__xludf.DUMMYFUNCTION("IFERROR(INDEX(IMPORTRANGE(""1wF8uimz-gnzzmqfjHb8Ua7fudqcoq5SrFyToq2B2IO0"",""💸 Expenses!A5:J200""),18,3),"""")"),"") | D58: =IFERROR(__xludf.DUMMYFUNCTION("IFERROR(INDEX(IMPORTRANGE(""1wF8uimz-gnzzmqfjHb8Ua7fudqcoq5SrFyToq2B2IO0"",""💸 Expenses!A5:J200""),18,4),"""")"),"") | E58: =IFERROR(__xludf.DUMMYFUNCTION("IFERROR(INDEX(IMPORTRANGE(""1wF8uimz-gnzzmqfjHb8Ua7fudqcoq5SrFyToq2B2IO0"",""💸 Expenses!A5:J200""),18,5),"""")"),"") | F58: =IFERROR(__xludf.DUMMYFUNCTION("IFERROR(IFERROR(INDEX(IMPORTRANGE(""1wF8uimz-gnzzmqfjHb8Ua7fudqcoq5SrFyToq2B2IO0"",""💸 Expenses!A5:J200""),18,6)*1,0),0)"),0.0) -> 0 | G58: =IFERROR(__xludf.DUMMYFUNCTION("IFERROR(INDEX(IMPORTRANGE(""1wF8uimz-gnzzmqfjHb8Ua7fudqcoq5SrFyToq2B2IO0"",""💸 Expenses!A5:J200""),18,7),"""")"),"") | H58: =IFERROR(__xludf.DUMMYFUNCTION("IFERROR(INDEX(IMPORTRANGE(""1wF8uimz-gnzzmqfjHb8Ua7fudqcoq5SrFyToq2B2IO0"",""💸 Expenses!A5:J200""),18,8),"""")"),"") | I58: =IFERROR(__xludf.DUMMYFUNCTION("IFERROR(INDEX(IMPORTRANGE(""1wF8uimz-gnzzmqfjHb8Ua7fudqcoq5SrFyToq2B2IO0"",""💸 Expenses!A5:J200""),18,9),"""")"),"") | J58: =IFERROR(__xludf.DUMMYFUNCTION("IFERROR(INDEX(IMPORTRANGE(""1wF8uimz-gnzzmqfjHb8Ua7fudqcoq5SrFyToq2B2IO0"",""💸 Expenses!A5:J200""),18,10),"""")"),"")
A59: =IFERROR(__xludf.DUMMYFUNCTION("IFERROR(INDEX(IMPORTRANGE(""1wF8uimz-gnzzmqfjHb8Ua7fudqcoq5SrFyToq2B2IO0"",""💸 Expenses!A5:J200""),19,1),"""")"),"") | B59: =IFERROR(__xludf.DUMMYFUNCTION("IFERROR(IF(INDEX(IMPORTRANGE(""1wF8uimz-gnzzmqfjHb8Ua7fudqcoq5SrFyToq2B2IO0"",""💸 Expenses!A5:J200""),19,2)="""","""",TEXT(INDEX(IMPORTRANGE(""1wF8uimz-gnzzmqfjHb8Ua7fudqcoq5SrFyToq2B2IO0"",""💸 Expenses!A5:J200""),19,2),""DD-MM-YYYY"")),"""")"),"") | C59: =IFERROR(__xludf.DUMMYFUNCTION("IFERROR(INDEX(IMPORTRANGE(""1wF8uimz-gnzzmqfjHb8Ua7fudqcoq5SrFyToq2B2IO0"",""💸 Expenses!A5:J200""),19,3),"""")"),"") | D59: =IFERROR(__xludf.DUMMYFUNCTION("IFERROR(INDEX(IMPORTRANGE(""1wF8uimz-gnzzmqfjHb8Ua7fudqcoq5SrFyToq2B2IO0"",""💸 Expenses!A5:J200""),19,4),"""")"),"") | E59: =IFERROR(__xludf.DUMMYFUNCTION("IFERROR(INDEX(IMPORTRANGE(""1wF8uimz-gnzzmqfjHb8Ua7fudqcoq5SrFyToq2B2IO0"",""💸 Expenses!A5:J200""),19,5),"""")"),"") | F59: =IFERROR(__xludf.DUMMYFUNCTION("IFERROR(IFERROR(INDEX(IMPORTRANGE(""1wF8uimz-gnzzmqfjHb8Ua7fudqcoq5SrFyToq2B2IO0"",""💸 Expenses!A5:J200""),19,6)*1,0),0)"),0.0) -> 0 | G59: =IFERROR(__xludf.DUMMYFUNCTION("IFERROR(INDEX(IMPORTRANGE(""1wF8uimz-gnzzmqfjHb8Ua7fudqcoq5SrFyToq2B2IO0"",""💸 Expenses!A5:J200""),19,7),"""")"),"") | H59: =IFERROR(__xludf.DUMMYFUNCTION("IFERROR(INDEX(IMPORTRANGE(""1wF8uimz-gnzzmqfjHb8Ua7fudqcoq5SrFyToq2B2IO0"",""💸 Expenses!A5:J200""),19,8),"""")"),"") | I59: =IFERROR(__xludf.DUMMYFUNCTION("IFERROR(INDEX(IMPORTRANGE(""1wF8uimz-gnzzmqfjHb8Ua7fudqcoq5SrFyToq2B2IO0"",""💸 Expenses!A5:J200""),19,9),"""")"),"") | J59: =IFERROR(__xludf.DUMMYFUNCTION("IFERROR(INDEX(IMPORTRANGE(""1wF8uimz-gnzzmqfjHb8Ua7fudqcoq5SrFyToq2B2IO0"",""💸 Expenses!A5:J200""),19,10),"""")"),"")
A60: =IFERROR(__xludf.DUMMYFUNCTION("IFERROR(INDEX(IMPORTRANGE(""1wF8uimz-gnzzmqfjHb8Ua7fudqcoq5SrFyToq2B2IO0"",""💸 Expenses!A5:J200""),20,1),"""")"),"") | B60: =IFERROR(__xludf.DUMMYFUNCTION("IFERROR(IF(INDEX(IMPORTRANGE(""1wF8uimz-gnzzmqfjHb8Ua7fudqcoq5SrFyToq2B2IO0"",""💸 Expenses!A5:J200""),20,2)="""","""",TEXT(INDEX(IMPORTRANGE(""1wF8uimz-gnzzmqfjHb8Ua7fudqcoq5SrFyToq2B2IO0"",""💸 Expenses!A5:J200""),20,2),""DD-MM-YYYY"")),"""")"),"") | C60: =IFERROR(__xludf.DUMMYFUNCTION("IFERROR(INDEX(IMPORTRANGE(""1wF8uimz-gnzzmqfjHb8Ua7fudqcoq5SrFyToq2B2IO0"",""💸 Expenses!A5:J200""),20,3),"""")"),"") | D60: =IFERROR(__xludf.DUMMYFUNCTION("IFERROR(INDEX(IMPORTRANGE(""1wF8uimz-gnzzmqfjHb8Ua7fudqcoq5SrFyToq2B2IO0"",""💸 Expenses!A5:J200""),20,4),"""")"),"") | E60: =IFERROR(__xludf.DUMMYFUNCTION("IFERROR(INDEX(IMPORTRANGE(""1wF8uimz-gnzzmqfjHb8Ua7fudqcoq5SrFyToq2B2IO0"",""💸 Expenses!A5:J200""),20,5),"""")"),"") | F60: =IFERROR(__xludf.DUMMYFUNCTION("IFERROR(IFERROR(INDEX(IMPORTRANGE(""1wF8uimz-gnzzmqfjHb8Ua7fudqcoq5SrFyToq2B2IO0"",""💸 Expenses!A5:J200""),20,6)*1,0),0)"),0.0) -> 0 | G60: =IFERROR(__xludf.DUMMYFUNCTION("IFERROR(INDEX(IMPORTRANGE(""1wF8uimz-gnzzmqfjHb8Ua7fudqcoq5SrFyToq2B2IO0"",""💸 Expenses!A5:J200""),20,7),"""")"),"") | H60: =IFERROR(__xludf.DUMMYFUNCTION("IFERROR(INDEX(IMPORTRANGE(""1wF8uimz-gnzzmqfjHb8Ua7fudqcoq5SrFyToq2B2IO0"",""💸 Expenses!A5:J200""),20,8),"""")"),"") | I60: =IFERROR(__xludf.DUMMYFUNCTION("IFERROR(INDEX(IMPORTRANGE(""1wF8uimz-gnzzmqfjHb8Ua7fudqcoq5SrFyToq2B2IO0"",""💸 Expenses!A5:J200""),20,9),"""")"),"") | J60: =IFERROR(__xludf.DUMMYFUNCTION("IFERROR(INDEX(IMPORTRANGE(""1wF8uimz-gnzzmqfjHb8Ua7fudqcoq5SrFyToq2B2IO0"",""💸 Expenses!A5:J200""),20,10),"""")"),"")
A61: =IFERROR(__xludf.DUMMYFUNCTION("IFERROR(INDEX(IMPORTRANGE(""1wF8uimz-gnzzmqfjHb8Ua7fudqcoq5SrFyToq2B2IO0"",""💸 Expenses!A5:J200""),21,1),"""")"),"") | B61: =IFERROR(__xludf.DUMMYFUNCTION("IFERROR(IF(INDEX(IMPORTRANGE(""1wF8uimz-gnzzmqfjHb8Ua7fudqcoq5SrFyToq2B2IO0"",""💸 Expenses!A5:J200""),21,2)="""","""",TEXT(INDEX(IMPORTRANGE(""1wF8uimz-gnzzmqfjHb8Ua7fudqcoq5SrFyToq2B2IO0"",""💸 Expenses!A5:J200""),21,2),""DD-MM-YYYY"")),"""")"),"") | C61: =IFERROR(__xludf.DUMMYFUNCTION("IFERROR(INDEX(IMPORTRANGE(""1wF8uimz-gnzzmqfjHb8Ua7fudqcoq5SrFyToq2B2IO0"",""💸 Expenses!A5:J200""),21,3),"""")"),"") | D61: =IFERROR(__xludf.DUMMYFUNCTION("IFERROR(INDEX(IMPORTRANGE(""1wF8uimz-gnzzmqfjHb8Ua7fudqcoq5SrFyToq2B2IO0"",""💸 Expenses!A5:J200""),21,4),"""")"),"") | E61: =IFERROR(__xludf.DUMMYFUNCTION("IFERROR(INDEX(IMPORTRANGE(""1wF8uimz-gnzzmqfjHb8Ua7fudqcoq5SrFyToq2B2IO0"",""💸 Expenses!A5:J200""),21,5),"""")"),"") | F61: =IFERROR(__xludf.DUMMYFUNCTION("IFERROR(IFERROR(INDEX(IMPORTRANGE(""1wF8uimz-gnzzmqfjHb8Ua7fudqcoq5SrFyToq2B2IO0"",""💸 Expenses!A5:J200""),21,6)*1,0),0)"),0.0) -> 0 | G61: =IFERROR(__xludf.DUMMYFUNCTION("IFERROR(INDEX(IMPORTRANGE(""1wF8uimz-gnzzmqfjHb8Ua7fudqcoq5SrFyToq2B2IO0"",""💸 Expenses!A5:J200""),21,7),"""")"),"") | H61: =IFERROR(__xludf.DUMMYFUNCTION("IFERROR(INDEX(IMPORTRANGE(""1wF8uimz-gnzzmqfjHb8Ua7fudqcoq5SrFyToq2B2IO0"",""💸 Expenses!A5:J200""),21,8),"""")"),"") | I61: =IFERROR(__xludf.DUMMYFUNCTION("IFERROR(INDEX(IMPORTRANGE(""1wF8uimz-gnzzmqfjHb8Ua7fudqcoq5SrFyToq2B2IO0"",""💸 Expenses!A5:J200""),21,9),"""")"),"") | J61: =IFERROR(__xludf.DUMMYFUNCTION("IFERROR(INDEX(IMPORTRANGE(""1wF8uimz-gnzzmqfjHb8Ua7fudqcoq5SrFyToq2B2IO0"",""💸 Expenses!A5:J200""),21,10),"""")"),"")
A62: =IFERROR(__xludf.DUMMYFUNCTION("IFERROR(INDEX(IMPORTRANGE(""1wF8uimz-gnzzmqfjHb8Ua7fudqcoq5SrFyToq2B2IO0"",""💸 Expenses!A5:J200""),22,1),"""")"),"") | B62: =IFERROR(__xludf.DUMMYFUNCTION("IFERROR(IF(INDEX(IMPORTRANGE(""1wF8uimz-gnzzmqfjHb8Ua7fudqcoq5SrFyToq2B2IO0"",""💸 Expenses!A5:J200""),22,2)="""","""",TEXT(INDEX(IMPORTRANGE(""1wF8uimz-gnzzmqfjHb8Ua7fudqcoq5SrFyToq2B2IO0"",""💸 Expenses!A5:J200""),22,2),""DD-MM-YYYY"")),"""")"),"") | C62: =IFERROR(__xludf.DUMMYFUNCTION("IFERROR(INDEX(IMPORTRANGE(""1wF8uimz-gnzzmqfjHb8Ua7fudqcoq5SrFyToq2B2IO0"",""💸 Expenses!A5:J200""),22,3),"""")"),"") | D62: =IFERROR(__xludf.DUMMYFUNCTION("IFERROR(INDEX(IMPORTRANGE(""1wF8uimz-gnzzmqfjHb8Ua7fudqcoq5SrFyToq2B2IO0"",""💸 Expenses!A5:J200""),22,4),"""")"),"") | E62: =IFERROR(__xludf.DUMMYFUNCTION("IFERROR(INDEX(IMPORTRANGE(""1wF8uimz-gnzzmqfjHb8Ua7fudqcoq5SrFyToq2B2IO0"",""💸 Expenses!A5:J200""),22,5),"""")"),"") | F62: =IFERROR(__xludf.DUMMYFUNCTION("IFERROR(IFERROR(INDEX(IMPORTRANGE(""1wF8uimz-gnzzmqfjHb8Ua7fudqcoq5SrFyToq2B2IO0"",""💸 Expenses!A5:J200""),22,6)*1,0),0)"),0.0) -> 0 | G62: =IFERROR(__xludf.DUMMYFUNCTION("IFERROR(INDEX(IMPORTRANGE(""1wF8uimz-gnzzmqfjHb8Ua7fudqcoq5SrFyToq2B2IO0"",""💸 Expenses!A5:J200""),22,7),"""")"),"") | H62: =IFERROR(__xludf.DUMMYFUNCTION("IFERROR(INDEX(IMPORTRANGE(""1wF8uimz-gnzzmqfjHb8Ua7fudqcoq5SrFyToq2B2IO0"",""💸 Expenses!A5:J200""),22,8),"""")"),"") | I62: =IFERROR(__xludf.DUMMYFUNCTION("IFERROR(INDEX(IMPORTRANGE(""1wF8uimz-gnzzmqfjHb8Ua7fudqcoq5SrFyToq2B2IO0"",""💸 Expenses!A5:J200""),22,9),"""")"),"") | J62: =IFERROR(__xludf.DUMMYFUNCTION("IFERROR(INDEX(IMPORTRANGE(""1wF8uimz-gnzzmqfjHb8Ua7fudqcoq5SrFyToq2B2IO0"",""💸 Expenses!A5:J200""),22,10),"""")"),"")
A63: =IFERROR(__xludf.DUMMYFUNCTION("IFERROR(INDEX(IMPORTRANGE(""1wF8uimz-gnzzmqfjHb8Ua7fudqcoq5SrFyToq2B2IO0"",""💸 Expenses!A5:J200""),23,1),"""")"),"") | B63: =IFERROR(__xludf.DUMMYFUNCTION("IFERROR(IF(INDEX(IMPORTRANGE(""1wF8uimz-gnzzmqfjHb8Ua7fudqcoq5SrFyToq2B2IO0"",""💸 Expenses!A5:J200""),23,2)="""","""",TEXT(INDEX(IMPORTRANGE(""1wF8uimz-gnzzmqfjHb8Ua7fudqcoq5SrFyToq2B2IO0"",""💸 Expenses!A5:J200""),23,2),""DD-MM-YYYY"")),"""")"),"") | C63: =IFERROR(__xludf.DUMMYFUNCTION("IFERROR(INDEX(IMPORTRANGE(""1wF8uimz-gnzzmqfjHb8Ua7fudqcoq5SrFyToq2B2IO0"",""💸 Expenses!A5:J200""),23,3),"""")"),"") | D63: =IFERROR(__xludf.DUMMYFUNCTION("IFERROR(INDEX(IMPORTRANGE(""1wF8uimz-gnzzmqfjHb8Ua7fudqcoq5SrFyToq2B2IO0"",""💸 Expenses!A5:J200""),23,4),"""")"),"") | E63: =IFERROR(__xludf.DUMMYFUNCTION("IFERROR(INDEX(IMPORTRANGE(""1wF8uimz-gnzzmqfjHb8Ua7fudqcoq5SrFyToq2B2IO0"",""💸 Expenses!A5:J200""),23,5),"""")"),"") | F63: =IFERROR(__xludf.DUMMYFUNCTION("IFERROR(IFERROR(INDEX(IMPORTRANGE(""1wF8uimz-gnzzmqfjHb8Ua7fudqcoq5SrFyToq2B2IO0"",""💸 Expenses!A5:J200""),23,6)*1,0),0)"),0.0) -> 0 | G63: =IFERROR(__xludf.DUMMYFUNCTION("IFERROR(INDEX(IMPORTRANGE(""1wF8uimz-gnzzmqfjHb8Ua7fudqcoq5SrFyToq2B2IO0"",""💸 Expenses!A5:J200""),23,7),"""")"),"") | H63: =IFERROR(__xludf.DUMMYFUNCTION("IFERROR(INDEX(IMPORTRANGE(""1wF8uimz-gnzzmqfjHb8Ua7fudqcoq5SrFyToq2B2IO0"",""💸 Expenses!A5:J200""),23,8),"""")"),"") | I63: =IFERROR(__xludf.DUMMYFUNCTION("IFERROR(INDEX(IMPORTRANGE(""1wF8uimz-gnzzmqfjHb8Ua7fudqcoq5SrFyToq2B2IO0"",""💸 Expenses!A5:J200""),23,9),"""")"),"") | J63: =IFERROR(__xludf.DUMMYFUNCTION("IFERROR(INDEX(IMPORTRANGE(""1wF8uimz-gnzzmqfjHb8Ua7fudqcoq5SrFyToq2B2IO0"",""💸 Expenses!A5:J200""),23,10),"""")"),"")
A64: =IFERROR(__xludf.DUMMYFUNCTION("IFERROR(INDEX(IMPORTRANGE(""1wF8uimz-gnzzmqfjHb8Ua7fudqcoq5SrFyToq2B2IO0"",""💸 Expenses!A5:J200""),24,1),"""")"),"") | B64: =IFERROR(__xludf.DUMMYFUNCTION("IFERROR(IF(INDEX(IMPORTRANGE(""1wF8uimz-gnzzmqfjHb8Ua7fudqcoq5SrFyToq2B2IO0"",""💸 Expenses!A5:J200""),24,2)="""","""",TEXT(INDEX(IMPORTRANGE(""1wF8uimz-gnzzmqfjHb8Ua7fudqcoq5SrFyToq2B2IO0"",""💸 Expenses!A5:J200""),24,2),""DD-MM-YYYY"")),"""")"),"") | C64: =IFERROR(__xludf.DUMMYFUNCTION("IFERROR(INDEX(IMPORTRANGE(""1wF8uimz-gnzzmqfjHb8Ua7fudqcoq5SrFyToq2B2IO0"",""💸 Expenses!A5:J200""),24,3),"""")"),"") | D64: =IFERROR(__xludf.DUMMYFUNCTION("IFERROR(INDEX(IMPORTRANGE(""1wF8uimz-gnzzmqfjHb8Ua7fudqcoq5SrFyToq2B2IO0"",""💸 Expenses!A5:J200""),24,4),"""")"),"") | E64: =IFERROR(__xludf.DUMMYFUNCTION("IFERROR(INDEX(IMPORTRANGE(""1wF8uimz-gnzzmqfjHb8Ua7fudqcoq5SrFyToq2B2IO0"",""💸 Expenses!A5:J200""),24,5),"""")"),"") | F64: =IFERROR(__xludf.DUMMYFUNCTION("IFERROR(IFERROR(INDEX(IMPORTRANGE(""1wF8uimz-gnzzmqfjHb8Ua7fudqcoq5SrFyToq2B2IO0"",""💸 Expenses!A5:J200""),24,6)*1,0),0)"),0.0) -> 0 | G64: =IFERROR(__xludf.DUMMYFUNCTION("IFERROR(INDEX(IMPORTRANGE(""1wF8uimz-gnzzmqfjHb8Ua7fudqcoq5SrFyToq2B2IO0"",""💸 Expenses!A5:J200""),24,7),"""")"),"") | H64: =IFERROR(__xludf.DUMMYFUNCTION("IFERROR(INDEX(IMPORTRANGE(""1wF8uimz-gnzzmqfjHb8Ua7fudqcoq5SrFyToq2B2IO0"",""💸 Expenses!A5:J200""),24,8),"""")"),"") | I64: =IFERROR(__xludf.DUMMYFUNCTION("IFERROR(INDEX(IMPORTRANGE(""1wF8uimz-gnzzmqfjHb8Ua7fudqcoq5SrFyToq2B2IO0"",""💸 Expenses!A5:J200""),24,9),"""")"),"") | J64: =IFERROR(__xludf.DUMMYFUNCTION("IFERROR(INDEX(IMPORTRANGE(""1wF8uimz-gnzzmqfjHb8Ua7fudqcoq5SrFyToq2B2IO0"",""💸 Expenses!A5:J200""),24,10),"""")"),"")
A65: =IFERROR(__xludf.DUMMYFUNCTION("IFERROR(INDEX(IMPORTRANGE(""1wF8uimz-gnzzmqfjHb8Ua7fudqcoq5SrFyToq2B2IO0"",""💸 Expenses!A5:J200""),25,1),"""")"),"") | B65: =IFERROR(__xludf.DUMMYFUNCTION("IFERROR(IF(INDEX(IMPORTRANGE(""1wF8uimz-gnzzmqfjHb8Ua7fudqcoq5SrFyToq2B2IO0"",""💸 Expenses!A5:J200""),25,2)="""","""",TEXT(INDEX(IMPORTRANGE(""1wF8uimz-gnzzmqfjHb8Ua7fudqcoq5SrFyToq2B2IO0"",""💸 Expenses!A5:J200""),25,2),""DD-MM-YYYY"")),"""")"),"") | C65: =IFERROR(__xludf.DUMMYFUNCTION("IFERROR(INDEX(IMPORTRANGE(""1wF8uimz-gnzzmqfjHb8Ua7fudqcoq5SrFyToq2B2IO0"",""💸 Expenses!A5:J200""),25,3),"""")"),"") | D65: =IFERROR(__xludf.DUMMYFUNCTION("IFERROR(INDEX(IMPORTRANGE(""1wF8uimz-gnzzmqfjHb8Ua7fudqcoq5SrFyToq2B2IO0"",""💸 Expenses!A5:J200""),25,4),"""")"),"") | E65: =IFERROR(__xludf.DUMMYFUNCTION("IFERROR(INDEX(IMPORTRANGE(""1wF8uimz-gnzzmqfjHb8Ua7fudqcoq5SrFyToq2B2IO0"",""💸 Expenses!A5:J200""),25,5),"""")"),"") | F65: =IFERROR(__xludf.DUMMYFUNCTION("IFERROR(IFERROR(INDEX(IMPORTRANGE(""1wF8uimz-gnzzmqfjHb8Ua7fudqcoq5SrFyToq2B2IO0"",""💸 Expenses!A5:J200""),25,6)*1,0),0)"),0.0) -> 0 | G65: =IFERROR(__xludf.DUMMYFUNCTION("IFERROR(INDEX(IMPORTRANGE(""1wF8uimz-gnzzmqfjHb8Ua7fudqcoq5SrFyToq2B2IO0"",""💸 Expenses!A5:J200""),25,7),"""")"),"") | H65: =IFERROR(__xludf.DUMMYFUNCTION("IFERROR(INDEX(IMPORTRANGE(""1wF8uimz-gnzzmqfjHb8Ua7fudqcoq5SrFyToq2B2IO0"",""💸 Expenses!A5:J200""),25,8),"""")"),"") | I65: =IFERROR(__xludf.DUMMYFUNCTION("IFERROR(INDEX(IMPORTRANGE(""1wF8uimz-gnzzmqfjHb8Ua7fudqcoq5SrFyToq2B2IO0"",""💸 Expenses!A5:J200""),25,9),"""")"),"") | J65: =IFERROR(__xludf.DUMMYFUNCTION("IFERROR(INDEX(IMPORTRANGE(""1wF8uimz-gnzzmqfjHb8Ua7fudqcoq5SrFyToq2B2IO0"",""💸 Expenses!A5:J200""),25,10),"""")"),"")
A66: =IFERROR(__xludf.DUMMYFUNCTION("IFERROR(INDEX(IMPORTRANGE(""1wF8uimz-gnzzmqfjHb8Ua7fudqcoq5SrFyToq2B2IO0"",""💸 Expenses!A5:J200""),26,1),"""")"),"") | B66: =IFERROR(__xludf.DUMMYFUNCTION("IFERROR(IF(INDEX(IMPORTRANGE(""1wF8uimz-gnzzmqfjHb8Ua7fudqcoq5SrFyToq2B2IO0"",""💸 Expenses!A5:J200""),26,2)="""","""",TEXT(INDEX(IMPORTRANGE(""1wF8uimz-gnzzmqfjHb8Ua7fudqcoq5SrFyToq2B2IO0"",""💸 Expenses!A5:J200""),26,2),""DD-MM-YYYY"")),"""")"),"") | C66: =IFERROR(__xludf.DUMMYFUNCTION("IFERROR(INDEX(IMPORTRANGE(""1wF8uimz-gnzzmqfjHb8Ua7fudqcoq5SrFyToq2B2IO0"",""💸 Expenses!A5:J200""),26,3),"""")"),"") | D66: =IFERROR(__xludf.DUMMYFUNCTION("IFERROR(INDEX(IMPORTRANGE(""1wF8uimz-gnzzmqfjHb8Ua7fudqcoq5SrFyToq2B2IO0"",""💸 Expenses!A5:J200""),26,4),"""")"),"") | E66: =IFERROR(__xludf.DUMMYFUNCTION("IFERROR(INDEX(IMPORTRANGE(""1wF8uimz-gnzzmqfjHb8Ua7fudqcoq5SrFyToq2B2IO0"",""💸 Expenses!A5:J200""),26,5),"""")"),"") | F66: =IFERROR(__xludf.DUMMYFUNCTION("IFERROR(IFERROR(INDEX(IMPORTRANGE(""1wF8uimz-gnzzmqfjHb8Ua7fudqcoq5SrFyToq2B2IO0"",""💸 Expenses!A5:J200""),26,6)*1,0),0)"),0.0) -> 0 | G66: =IFERROR(__xludf.DUMMYFUNCTION("IFERROR(INDEX(IMPORTRANGE(""1wF8uimz-gnzzmqfjHb8Ua7fudqcoq5SrFyToq2B2IO0"",""💸 Expenses!A5:J200""),26,7),"""")"),"") | H66: =IFERROR(__xludf.DUMMYFUNCTION("IFERROR(INDEX(IMPORTRANGE(""1wF8uimz-gnzzmqfjHb8Ua7fudqcoq5SrFyToq2B2IO0"",""💸 Expenses!A5:J200""),26,8),"""")"),"") | I66: =IFERROR(__xludf.DUMMYFUNCTION("IFERROR(INDEX(IMPORTRANGE(""1wF8uimz-gnzzmqfjHb8Ua7fudqcoq5SrFyToq2B2IO0"",""💸 Expenses!A5:J200""),26,9),"""")"),"") | J66: =IFERROR(__xludf.DUMMYFUNCTION("IFERROR(INDEX(IMPORTRANGE(""1wF8uimz-gnzzmqfjHb8Ua7fudqcoq5SrFyToq2B2IO0"",""💸 Expenses!A5:J200""),26,10),"""")"),"")
A67: =IFERROR(__xludf.DUMMYFUNCTION("IFERROR(INDEX(IMPORTRANGE(""1wF8uimz-gnzzmqfjHb8Ua7fudqcoq5SrFyToq2B2IO0"",""💸 Expenses!A5:J200""),27,1),"""")"),"") | B67: =IFERROR(__xludf.DUMMYFUNCTION("IFERROR(IF(INDEX(IMPORTRANGE(""1wF8uimz-gnzzmqfjHb8Ua7fudqcoq5SrFyToq2B2IO0"",""💸 Expenses!A5:J200""),27,2)="""","""",TEXT(INDEX(IMPORTRANGE(""1wF8uimz-gnzzmqfjHb8Ua7fudqcoq5SrFyToq2B2IO0"",""💸 Expenses!A5:J200""),27,2),""DD-MM-YYYY"")),"""")"),"") | C67: =IFERROR(__xludf.DUMMYFUNCTION("IFERROR(INDEX(IMPORTRANGE(""1wF8uimz-gnzzmqfjHb8Ua7fudqcoq5SrFyToq2B2IO0"",""💸 Expenses!A5:J200""),27,3),"""")"),"") | D67: =IFERROR(__xludf.DUMMYFUNCTION("IFERROR(INDEX(IMPORTRANGE(""1wF8uimz-gnzzmqfjHb8Ua7fudqcoq5SrFyToq2B2IO0"",""💸 Expenses!A5:J200""),27,4),"""")"),"") | E67: =IFERROR(__xludf.DUMMYFUNCTION("IFERROR(INDEX(IMPORTRANGE(""1wF8uimz-gnzzmqfjHb8Ua7fudqcoq5SrFyToq2B2IO0"",""💸 Expenses!A5:J200""),27,5),"""")"),"") | F67: =IFERROR(__xludf.DUMMYFUNCTION("IFERROR(IFERROR(INDEX(IMPORTRANGE(""1wF8uimz-gnzzmqfjHb8Ua7fudqcoq5SrFyToq2B2IO0"",""💸 Expenses!A5:J200""),27,6)*1,0),0)"),0.0) -> 0 | G67: =IFERROR(__xludf.DUMMYFUNCTION("IFERROR(INDEX(IMPORTRANGE(""1wF8uimz-gnzzmqfjHb8Ua7fudqcoq5SrFyToq2B2IO0"",""💸 Expenses!A5:J200""),27,7),"""")"),"") | H67: =IFERROR(__xludf.DUMMYFUNCTION("IFERROR(INDEX(IMPORTRANGE(""1wF8uimz-gnzzmqfjHb8Ua7fudqcoq5SrFyToq2B2IO0"",""💸 Expenses!A5:J200""),27,8),"""")"),"") | I67: =IFERROR(__xludf.DUMMYFUNCTION("IFERROR(INDEX(IMPORTRANGE(""1wF8uimz-gnzzmqfjHb8Ua7fudqcoq5SrFyToq2B2IO0"",""💸 Expenses!A5:J200""),27,9),"""")"),"") | J67: =IFERROR(__xludf.DUMMYFUNCTION("IFERROR(INDEX(IMPORTRANGE(""1wF8uimz-gnzzmqfjHb8Ua7fudqcoq5SrFyToq2B2IO0"",""💸 Expenses!A5:J200""),27,10),"""")"),"")
A68: =IFERROR(__xludf.DUMMYFUNCTION("IFERROR(INDEX(IMPORTRANGE(""1wF8uimz-gnzzmqfjHb8Ua7fudqcoq5SrFyToq2B2IO0"",""💸 Expenses!A5:J200""),28,1),"""")"),"") | B68: =IFERROR(__xludf.DUMMYFUNCTION("IFERROR(IF(INDEX(IMPORTRANGE(""1wF8uimz-gnzzmqfjHb8Ua7fudqcoq5SrFyToq2B2IO0"",""💸 Expenses!A5:J200""),28,2)="""","""",TEXT(INDEX(IMPORTRANGE(""1wF8uimz-gnzzmqfjHb8Ua7fudqcoq5SrFyToq2B2IO0"",""💸 Expenses!A5:J200""),28,2),""DD-MM-YYYY"")),"""")"),"") | C68: =IFERROR(__xludf.DUMMYFUNCTION("IFERROR(INDEX(IMPORTRANGE(""1wF8uimz-gnzzmqfjHb8Ua7fudqcoq5SrFyToq2B2IO0"",""💸 Expenses!A5:J200""),28,3),"""")"),"") | D68: =IFERROR(__xludf.DUMMYFUNCTION("IFERROR(INDEX(IMPORTRANGE(""1wF8uimz-gnzzmqfjHb8Ua7fudqcoq5SrFyToq2B2IO0"",""💸 Expenses!A5:J200""),28,4),"""")"),"") | E68: =IFERROR(__xludf.DUMMYFUNCTION("IFERROR(INDEX(IMPORTRANGE(""1wF8uimz-gnzzmqfjHb8Ua7fudqcoq5SrFyToq2B2IO0"",""💸 Expenses!A5:J200""),28,5),"""")"),"") | F68: =IFERROR(__xludf.DUMMYFUNCTION("IFERROR(IFERROR(INDEX(IMPORTRANGE(""1wF8uimz-gnzzmqfjHb8Ua7fudqcoq5SrFyToq2B2IO0"",""💸 Expenses!A5:J200""),28,6)*1,0),0)"),0.0) -> 0 | G68: =IFERROR(__xludf.DUMMYFUNCTION("IFERROR(INDEX(IMPORTRANGE(""1wF8uimz-gnzzmqfjHb8Ua7fudqcoq5SrFyToq2B2IO0"",""💸 Expenses!A5:J200""),28,7),"""")"),"") | H68: =IFERROR(__xludf.DUMMYFUNCTION("IFERROR(INDEX(IMPORTRANGE(""1wF8uimz-gnzzmqfjHb8Ua7fudqcoq5SrFyToq2B2IO0"",""💸 Expenses!A5:J200""),28,8),"""")"),"") | I68: =IFERROR(__xludf.DUMMYFUNCTION("IFERROR(INDEX(IMPORTRANGE(""1wF8uimz-gnzzmqfjHb8Ua7fudqcoq5SrFyToq2B2IO0"",""💸 Expenses!A5:J200""),28,9),"""")"),"") | J68: =IFERROR(__xludf.DUMMYFUNCTION("IFERROR(INDEX(IMPORTRANGE(""1wF8uimz-gnzzmqfjHb8Ua7fudqcoq5SrFyToq2B2IO0"",""💸 Expenses!A5:J200""),28,10),"""")"),"")
A69: =IFERROR(__xludf.DUMMYFUNCTION("IFERROR(INDEX(IMPORTRANGE(""1wF8uimz-gnzzmqfjHb8Ua7fudqcoq5SrFyToq2B2IO0"",""💸 Expenses!A5:J200""),29,1),"""")"),"") | B69: =IFERROR(__xludf.DUMMYFUNCTION("IFERROR(IF(INDEX(IMPORTRANGE(""1wF8uimz-gnzzmqfjHb8Ua7fudqcoq5SrFyToq2B2IO0"",""💸 Expenses!A5:J200""),29,2)="""","""",TEXT(INDEX(IMPORTRANGE(""1wF8uimz-gnzzmqfjHb8Ua7fudqcoq5SrFyToq2B2IO0"",""💸 Expenses!A5:J200""),29,2),""DD-MM-YYYY"")),"""")"),"") | C69: =IFERROR(__xludf.DUMMYFUNCTION("IFERROR(INDEX(IMPORTRANGE(""1wF8uimz-gnzzmqfjHb8Ua7fudqcoq5SrFyToq2B2IO0"",""💸 Expenses!A5:J200""),29,3),"""")"),"") | D69: =IFERROR(__xludf.DUMMYFUNCTION("IFERROR(INDEX(IMPORTRANGE(""1wF8uimz-gnzzmqfjHb8Ua7fudqcoq5SrFyToq2B2IO0"",""💸 Expenses!A5:J200""),29,4),"""")"),"") | E69: =IFERROR(__xludf.DUMMYFUNCTION("IFERROR(INDEX(IMPORTRANGE(""1wF8uimz-gnzzmqfjHb8Ua7fudqcoq5SrFyToq2B2IO0"",""💸 Expenses!A5:J200""),29,5),"""")"),"") | F69: =IFERROR(__xludf.DUMMYFUNCTION("IFERROR(IFERROR(INDEX(IMPORTRANGE(""1wF8uimz-gnzzmqfjHb8Ua7fudqcoq5SrFyToq2B2IO0"",""💸 Expenses!A5:J200""),29,6)*1,0),0)"),0.0) -> 0 | G69: =IFERROR(__xludf.DUMMYFUNCTION("IFERROR(INDEX(IMPORTRANGE(""1wF8uimz-gnzzmqfjHb8Ua7fudqcoq5SrFyToq2B2IO0"",""💸 Expenses!A5:J200""),29,7),"""")"),"") | H69: =IFERROR(__xludf.DUMMYFUNCTION("IFERROR(INDEX(IMPORTRANGE(""1wF8uimz-gnzzmqfjHb8Ua7fudqcoq5SrFyToq2B2IO0"",""💸 Expenses!A5:J200""),29,8),"""")"),"") | I69: =IFERROR(__xludf.DUMMYFUNCTION("IFERROR(INDEX(IMPORTRANGE(""1wF8uimz-gnzzmqfjHb8Ua7fudqcoq5SrFyToq2B2IO0"",""💸 Expenses!A5:J200""),29,9),"""")"),"") | J69: =IFERROR(__xludf.DUMMYFUNCTION("IFERROR(INDEX(IMPORTRANGE(""1wF8uimz-gnzzmqfjHb8Ua7fudqcoq5SrFyToq2B2IO0"",""💸 Expenses!A5:J200""),29,10),"""")"),"")
A70: =IFERROR(__xludf.DUMMYFUNCTION("IFERROR(INDEX(IMPORTRANGE(""1wF8uimz-gnzzmqfjHb8Ua7fudqcoq5SrFyToq2B2IO0"",""💸 Expenses!A5:J200""),30,1),"""")"),"") | B70: =IFERROR(__xludf.DUMMYFUNCTION("IFERROR(IF(INDEX(IMPORTRANGE(""1wF8uimz-gnzzmqfjHb8Ua7fudqcoq5SrFyToq2B2IO0"",""💸 Expenses!A5:J200""),30,2)="""","""",TEXT(INDEX(IMPORTRANGE(""1wF8uimz-gnzzmqfjHb8Ua7fudqcoq5SrFyToq2B2IO0"",""💸 Expenses!A5:J200""),30,2),""DD-MM-YYYY"")),"""")"),"") | C70: =IFERROR(__xludf.DUMMYFUNCTION("IFERROR(INDEX(IMPORTRANGE(""1wF8uimz-gnzzmqfjHb8Ua7fudqcoq5SrFyToq2B2IO0"",""💸 Expenses!A5:J200""),30,3),"""")"),"") | D70: =IFERROR(__xludf.DUMMYFUNCTION("IFERROR(INDEX(IMPORTRANGE(""1wF8uimz-gnzzmqfjHb8Ua7fudqcoq5SrFyToq2B2IO0"",""💸 Expenses!A5:J200""),30,4),"""")"),"") | E70: =IFERROR(__xludf.DUMMYFUNCTION("IFERROR(INDEX(IMPORTRANGE(""1wF8uimz-gnzzmqfjHb8Ua7fudqcoq5SrFyToq2B2IO0"",""💸 Expenses!A5:J200""),30,5),"""")"),"") | F70: =IFERROR(__xludf.DUMMYFUNCTION("IFERROR(IFERROR(INDEX(IMPORTRANGE(""1wF8uimz-gnzzmqfjHb8Ua7fudqcoq5SrFyToq2B2IO0"",""💸 Expenses!A5:J200""),30,6)*1,0),0)"),0.0) -> 0 | G70: =IFERROR(__xludf.DUMMYFUNCTION("IFERROR(INDEX(IMPORTRANGE(""1wF8uimz-gnzzmqfjHb8Ua7fudqcoq5SrFyToq2B2IO0"",""💸 Expenses!A5:J200""),30,7),"""")"),"") | H70: =IFERROR(__xludf.DUMMYFUNCTION("IFERROR(INDEX(IMPORTRANGE(""1wF8uimz-gnzzmqfjHb8Ua7fudqcoq5SrFyToq2B2IO0"",""💸 Expenses!A5:J200""),30,8),"""")"),"") | I70: =IFERROR(__xludf.DUMMYFUNCTION("IFERROR(INDEX(IMPORTRANGE(""1wF8uimz-gnzzmqfjHb8Ua7fudqcoq5SrFyToq2B2IO0"",""💸 Expenses!A5:J200""),30,9),"""")"),"") | J70: =IFERROR(__xludf.DUMMYFUNCTION("IFERROR(INDEX(IMPORTRANGE(""1wF8uimz-gnzzmqfjHb8Ua7fudqcoq5SrFyToq2B2IO0"",""💸 Expenses!A5:J200""),30,10),"""")"),"")
A71: TOTAL EXPENSES | F71: =SUMPRODUCT((A41:A70<>"")*F41:F70) -> 0
A73: 💝 DONATION TYPE SUMMARY
A74: # | B74: Donation Type | D74: Pledged (₹) | E74: Received (₹) | F74: Pending (₹)
A75: 1 | B75: Aadi Festival | D75: =IFERROR(__xludf.DUMMYFUNCTION("IFERROR(INDEX(QUERY(IMPORTRANGE(""1wF8uimz-gnzzmqfjHb8Ua7fudqcoq5SrFyToq2B2IO0"",""💰 Donations!C4:M200""),""SELECT SUM(Col1) WHERE Col11='Aadi Festival' LABEL SUM(Col1) ''""),1),0)"),0.0) -> 0 | E75: =IFERROR(__xludf.DUMMYFUNCTION("IFERROR(INDEX(QUERY(IMPORTRANGE(""1wF8uimz-gnzzmqfjHb8Ua7fudqcoq5SrFyToq2B2IO0"",""💰 Donations!C4:M200""),""SELECT SUM(Col2) WHERE Col11='Aadi Festival' LABEL SUM(Col2) ''""),1),0)"),0.0) -> 0 | F75: =D75-E75 -> 0
A76: 2 | B76: Temple Development | D76: =IFERROR(__xludf.DUMMYFUNCTION("IFERROR(INDEX(QUERY(IMPORTRANGE(""1wF8uimz-gnzzmqfjHb8Ua7fudqcoq5SrFyToq2B2IO0"",""💰 Donations!C4:M200""),""SELECT SUM(Col1) WHERE Col11='Temple Development' LABEL SUM(Col1) ''""),1),0)"),0.0) -> 0 | E76: =IFERROR(__xludf.DUMMYFUNCTION("IFERROR(INDEX(QUERY(IMPORTRANGE(""1wF8uimz-gnzzmqfjHb8Ua7fudqcoq5SrFyToq2B2IO0"",""💰 Donations!C4:M200""),""SELECT SUM(Col2) WHERE Col11='Temple Development' LABEL SUM(Col2) ''""),1),0)"),0.0) -> 0 | F76: =D76-E76 -> 0
A77: 3 | B77: Birthday Pooja | D77: =IFERROR(__xludf.DUMMYFUNCTION("IFERROR(INDEX(QUERY(IMPORTRANGE(""1wF8uimz-gnzzmqfjHb8Ua7fudqcoq5SrFyToq2B2IO0"",""💰 Donations!C4:M200""),""SELECT SUM(Col1) WHERE Col11='Birthday Pooja' LABEL SUM(Col1) ''""),1),0)"),0.0) -> 0 | E77: =IFERROR(__xludf.DUMMYFUNCTION("IFERROR(INDEX(QUERY(IMPORTRANGE(""1wF8uimz-gnzzmqfjHb8Ua7fudqcoq5SrFyToq2B2IO0"",""💰 Donations!C4:M200""),""SELECT SUM(Col2) WHERE Col11='Birthday Pooja' LABEL SUM(Col2) ''""),1),0)"),0.0) -> 0 | F77: =D77-E77 -> 0
A78: 4 | B78: Anniversary Pooja | D78: =IFERROR(__xludf.DUMMYFUNCTION("IFERROR(INDEX(QUERY(IMPORTRANGE(""1wF8uimz-gnzzmqfjHb8Ua7fudqcoq5SrFyToq2B2IO0"",""💰 Donations!C4:M200""),""SELECT SUM(Col1) WHERE Col11='Anniversary Pooja' LABEL SUM(Col1) ''""),1),0)"),0.0) -> 0 | E78: =IFERROR(__xludf.DUMMYFUNCTION("IFERROR(INDEX(QUERY(IMPORTRANGE(""1wF8uimz-gnzzmqfjHb8Ua7fudqcoq5SrFyToq2B2IO0"",""💰 Donations!C4:M200""),""SELECT SUM(Col2) WHERE Col11='Anniversary Pooja' LABEL SUM(Col2) ''""),1),0)"),0.0) -> 0 | F78: =D78-E78 -> 0
A79: 5 | B79: Pournami Pooja | D79: =IFERROR(__xludf.DUMMYFUNCTION("IFERROR(INDEX(QUERY(IMPORTRANGE(""1wF8uimz-gnzzmqfjHb8Ua7fudqcoq5SrFyToq2B2IO0"",""💰 Donations!C4:M200""),""SELECT SUM(Col1) WHERE Col11='Pournami Pooja' LABEL SUM(Col1) ''""),1),0)"),0.0) -> 0 | E79: =IFERROR(__xludf.DUMMYFUNCTION("IFERROR(INDEX(QUERY(IMPORTRANGE(""1wF8uimz-gnzzmqfjHb8Ua7fudqcoq5SrFyToq2B2IO0"",""💰 Donations!C4:M200""),""SELECT SUM(Col2) WHERE Col11='Pournami Pooja' LABEL SUM(Col2) ''""),1),0)"),0.0) -> 0 | F79: =D79-E79 -> 0
A80: 6 | B80: Amavasai Pooja | D80: =IFERROR(__xludf.DUMMYFUNCTION("IFERROR(INDEX(QUERY(IMPORTRANGE(""1wF8uimz-gnzzmqfjHb8Ua7fudqcoq5SrFyToq2B2IO0"",""💰 Donations!C4:M200""),""SELECT SUM(Col1) WHERE Col11='Amavasai Pooja' LABEL SUM(Col1) ''""),1),0)"),0.0) -> 0 | E80: =IFERROR(__xludf.DUMMYFUNCTION("IFERROR(INDEX(QUERY(IMPORTRANGE(""1wF8uimz-gnzzmqfjHb8Ua7fudqcoq5SrFyToq2B2IO0"",""💰 Donations!C4:M200""),""SELECT SUM(Col2) WHERE Col11='Amavasai Pooja' LABEL SUM(Col2) ''""),1),0)"),0.0) -> 0 | F80: =D80-E80 -> 0
A81: 7 | B81: Weekly Pooja | D81: =IFERROR(__xludf.DUMMYFUNCTION("IFERROR(INDEX(QUERY(IMPORTRANGE(""1wF8uimz-gnzzmqfjHb8Ua7fudqcoq5SrFyToq2B2IO0"",""💰 Donations!C4:M200""),""SELECT SUM(Col1) WHERE Col11='Weekly Pooja' LABEL SUM(Col1) ''""),1),0)"),0.0) -> 0 | E81: =IFERROR(__xludf.DUMMYFUNCTION("IFERROR(INDEX(QUERY(IMPORTRANGE(""1wF8uimz-gnzzmqfjHb8Ua7fudqcoq5SrFyToq2B2IO0"",""💰 Donations!C4:M200""),""SELECT SUM(Col2) WHERE Col11='Weekly Pooja' LABEL SUM(Col2) ''""),1),0)"),0.0) -> 0 | F81: =D81-E81 -> 0
A82: 8 | B82: Others | D82: =IFERROR(__xludf.DUMMYFUNCTION("IFERROR(INDEX(QUERY(IMPORTRANGE(""1wF8uimz-gnzzmqfjHb8Ua7fudqcoq5SrFyToq2B2IO0"",""💰 Donations!C4:M200""),""SELECT SUM(Col1) WHERE Col11='Others' LABEL SUM(Col1) ''""),1),0)"),0.0) -> 0 | E82: =IFERROR(__xludf.DUMMYFUNCTION("IFERROR(INDEX(QUERY(IMPORTRANGE(""1wF8uimz-gnzzmqfjHb8Ua7fudqcoq5SrFyToq2B2IO0"",""💰 Donations!C4:M200""),""SELECT SUM(Col2) WHERE Col11='Others' LABEL SUM(Col2) ''""),1),0)"),0.0) -> 0 | F82: =D82-E82 -> 0
A83: TOTAL | D83: =SUM(D75:D82) -> 0 | E83: =SUM(E75:E82) -> 0 | F83: =D83-E83 -> 0
A85: 🙏 DONOR LIST
A86: # | B86: Donor Name | D86: Pledged (₹) | E86: Received (₹) | F86: Balance (₹) | G86: Status | H86: Pay Mode | I86: Date Rcvd | J86: Received By | K86: Purpose / Notes | L86: Type | M86: Person Name | N86: Exp. Pay Date
A87: =IFERROR(__xludf.DUMMYFUNCTION("IFERROR(INDEX(IMPORTRANGE(""1wF8uimz-gnzzmqfjHb8Ua7fudqcoq5SrFyToq2B2IO0"",""💰 Donations!A4:N200""),1,1),"""")"),"2027/D/1") -> 2027/D/1 | B87: =IFERROR(__xludf.DUMMYFUNCTION("IFERROR(INDEX(IMPORTRANGE(""1wF8uimz-gnzzmqfjHb8Ua7fudqcoq5SrFyToq2B2IO0"",""💰 Donations!A4:N200""),1,2),"""")"),"S Shekar") -> S Shekar | D87: =IFERROR(__xludf.DUMMYFUNCTION("IFERROR(IFERROR(INDEX(IMPORTRANGE(""1wF8uimz-gnzzmqfjHb8Ua7fudqcoq5SrFyToq2B2IO0"",""💰 Donations!A4:N200""),1,3)*1,0),0)"),0.0) -> 0 | E87: =IFERROR(__xludf.DUMMYFUNCTION("IFERROR(IFERROR(INDEX(IMPORTRANGE(""1wF8uimz-gnzzmqfjHb8Ua7fudqcoq5SrFyToq2B2IO0"",""💰 Donations!A4:N200""),1,4)*1,0),0)"),0.0) -> 0 | F87: =IFERROR(D87-E87,0) -> 0 | G87: =IF(A87="","",IF(OR(E87=0,E87=""),"Pending",IF(E87>=D87,"Received","Partially Received"))) -> Pending | H87: =IFERROR(__xludf.DUMMYFUNCTION("IFERROR(INDEX(IMPORTRANGE(""1wF8uimz-gnzzmqfjHb8Ua7fudqcoq5SrFyToq2B2IO0"",""💰 Donations!A4:N200""),1,6),"""")"),"") | I87: =IFERROR(__xludf.DUMMYFUNCTION("IFERROR(IF(INDEX(IMPORTRANGE(""1wF8uimz-gnzzmqfjHb8Ua7fudqcoq5SrFyToq2B2IO0"",""💰 Donations!A4:N200""),1,7)="""","""",TEXT(INDEX(IMPORTRANGE(""1wF8uimz-gnzzmqfjHb8Ua7fudqcoq5SrFyToq2B2IO0"",""💰 Donations!A4:N200""),1,7),""DD-MM-YYYY"")),"""")"),"") | J87: =IFERROR(__xludf.DUMMYFUNCTION("IFERROR(INDEX(IMPORTRANGE(""1wF8uimz-gnzzmqfjHb8Ua7fudqcoq5SrFyToq2B2IO0"",""💰 Donations!A4:N200""),1,8),"""")"),"") | K87: =IFERROR(__xludf.DUMMYFUNCTION("IFERROR(INDEX(IMPORTRANGE(""1wF8uimz-gnzzmqfjHb8Ua7fudqcoq5SrFyToq2B2IO0"",""💰 Donations!A4:N200""),1,11),"""")"),"Towards Iyer") -> Towards Iyer | L87: =IFERROR(__xludf.DUMMYFUNCTION("IFERROR(INDEX(IMPORTRANGE(""1wF8uimz-gnzzmqfjHb8Ua7fudqcoq5SrFyToq2B2IO0"",""💰 Donations!A4:N200""),1,13),"""")"),"Aadi Festival") -> Aadi Festival | M87: =IFERROR(__xludf.DUMMYFUNCTION("IFERROR(INDEX(IMPORTRANGE(""1wF8uimz-gnzzmqfjHb8Ua7fudqcoq5SrFyToq2B2IO0"",""💰 Donations!A4:N200""),1,14),"""")"),"") | N87: =IFERROR(__xludf.DUMMYFUNCTION("IFERROR(IF(INDEX(IMPORTRANGE(""1wF8uimz-gnzzmqfjHb8Ua7fudqcoq5SrFyToq2B2IO0"",""💰 Donations!A4:N200""),1,10)="""","""",TEXT(INDEX(IMPORTRANGE(""1wF8uimz-gnzzmqfjHb8Ua7fudqcoq5SrFyToq2B2IO0"",""💰 Donations!A4:N200""),1,10),""DD-MM-YYYY"")),"""")"),"10-08-2026") -> 10-08-2026
A88: =IFERROR(__xludf.DUMMYFUNCTION("IFERROR(INDEX(IMPORTRANGE(""1wF8uimz-gnzzmqfjHb8Ua7fudqcoq5SrFyToq2B2IO0"",""💰 Donations!A4:N200""),2,1),"""")"),"") | B88: =IFERROR(__xludf.DUMMYFUNCTION("IFERROR(INDEX(IMPORTRANGE(""1wF8uimz-gnzzmqfjHb8Ua7fudqcoq5SrFyToq2B2IO0"",""💰 Donations!A4:N200""),2,2),"""")"),"") | D88: =IFERROR(__xludf.DUMMYFUNCTION("IFERROR(IFERROR(INDEX(IMPORTRANGE(""1wF8uimz-gnzzmqfjHb8Ua7fudqcoq5SrFyToq2B2IO0"",""💰 Donations!A4:N200""),2,3)*1,0),0)"),0.0) -> 0 | E88: =IFERROR(__xludf.DUMMYFUNCTION("IFERROR(IFERROR(INDEX(IMPORTRANGE(""1wF8uimz-gnzzmqfjHb8Ua7fudqcoq5SrFyToq2B2IO0"",""💰 Donations!A4:N200""),2,4)*1,0),0)"),0.0) -> 0 | F88: =IFERROR(D88-E88,0) -> 0 | G88: =IF(A88="","",IF(OR(E88=0,E88=""),"Pending",IF(E88>=D88,"Received","Partially Received"))) | H88: =IFERROR(__xludf.DUMMYFUNCTION("IFERROR(INDEX(IMPORTRANGE(""1wF8uimz-gnzzmqfjHb8Ua7fudqcoq5SrFyToq2B2IO0"",""💰 Donations!A4:N200""),2,6),"""")"),"") | I88: =IFERROR(__xludf.DUMMYFUNCTION("IFERROR(IF(INDEX(IMPORTRANGE(""1wF8uimz-gnzzmqfjHb8Ua7fudqcoq5SrFyToq2B2IO0"",""💰 Donations!A4:N200""),2,7)="""","""",TEXT(INDEX(IMPORTRANGE(""1wF8uimz-gnzzmqfjHb8Ua7fudqcoq5SrFyToq2B2IO0"",""💰 Donations!A4:N200""),2,7),""DD-MM-YYYY"")),"""")"),"") | J88: =IFERROR(__xludf.DUMMYFUNCTION("IFERROR(INDEX(IMPORTRANGE(""1wF8uimz-gnzzmqfjHb8Ua7fudqcoq5SrFyToq2B2IO0"",""💰 Donations!A4:N200""),2,8),"""")"),"") | K88: =IFERROR(__xludf.DUMMYFUNCTION("IFERROR(INDEX(IMPORTRANGE(""1wF8uimz-gnzzmqfjHb8Ua7fudqcoq5SrFyToq2B2IO0"",""💰 Donations!A4:N200""),2,11),"""")"),"") | L88: =IFERROR(__xludf.DUMMYFUNCTION("IFERROR(INDEX(IMPORTRANGE(""1wF8uimz-gnzzmqfjHb8Ua7fudqcoq5SrFyToq2B2IO0"",""💰 Donations!A4:N200""),2,13),"""")"),"") | M88: =IFERROR(__xludf.DUMMYFUNCTION("IFERROR(INDEX(IMPORTRANGE(""1wF8uimz-gnzzmqfjHb8Ua7fudqcoq5SrFyToq2B2IO0"",""💰 Donations!A4:N200""),2,14),"""")"),"") | N88: =IFERROR(__xludf.DUMMYFUNCTION("IFERROR(IF(INDEX(IMPORTRANGE(""1wF8uimz-gnzzmqfjHb8Ua7fudqcoq5SrFyToq2B2IO0"",""💰 Donations!A4:N200""),2,10)="""","""",TEXT(INDEX(IMPORTRANGE(""1wF8uimz-gnzzmqfjHb8Ua7fudqcoq5SrFyToq2B2IO0"",""💰 Donations!A4:N200""),2,10),""DD-MM-YYYY"")),"""")"),"")
A89: =IFERROR(__xludf.DUMMYFUNCTION("IFERROR(INDEX(IMPORTRANGE(""1wF8uimz-gnzzmqfjHb8Ua7fudqcoq5SrFyToq2B2IO0"",""💰 Donations!A4:N200""),3,1),"""")"),"") | B89: =IFERROR(__xludf.DUMMYFUNCTION("IFERROR(INDEX(IMPORTRANGE(""1wF8uimz-gnzzmqfjHb8Ua7fudqcoq5SrFyToq2B2IO0"",""💰 Donations!A4:N200""),3,2),"""")"),"") | D89: =IFERROR(__xludf.DUMMYFUNCTION("IFERROR(IFERROR(INDEX(IMPORTRANGE(""1wF8uimz-gnzzmqfjHb8Ua7fudqcoq5SrFyToq2B2IO0"",""💰 Donations!A4:N200""),3,3)*1,0),0)"),0.0) -> 0 | E89: =IFERROR(__xludf.DUMMYFUNCTION("IFERROR(IFERROR(INDEX(IMPORTRANGE(""1wF8uimz-gnzzmqfjHb8Ua7fudqcoq5SrFyToq2B2IO0"",""💰 Donations!A4:N200""),3,4)*1,0),0)"),0.0) -> 0 | F89: =IFERROR(D89-E89,0) -> 0 | G89: =IF(A89="","",IF(OR(E89=0,E89=""),"Pending",IF(E89>=D89,"Received","Partially Received"))) | H89: =IFERROR(__xludf.DUMMYFUNCTION("IFERROR(INDEX(IMPORTRANGE(""1wF8uimz-gnzzmqfjHb8Ua7fudqcoq5SrFyToq2B2IO0"",""💰 Donations!A4:N200""),3,6),"""")"),"") | I89: =IFERROR(__xludf.DUMMYFUNCTION("IFERROR(IF(INDEX(IMPORTRANGE(""1wF8uimz-gnzzmqfjHb8Ua7fudqcoq5SrFyToq2B2IO0"",""💰 Donations!A4:N200""),3,7)="""","""",TEXT(INDEX(IMPORTRANGE(""1wF8uimz-gnzzmqfjHb8Ua7fudqcoq5SrFyToq2B2IO0"",""💰 Donations!A4:N200""),3,7),""DD-MM-YYYY"")),"""")"),"") | J89: =IFERROR(__xludf.DUMMYFUNCTION("IFERROR(INDEX(IMPORTRANGE(""1wF8uimz-gnzzmqfjHb8Ua7fudqcoq5SrFyToq2B2IO0"",""💰 Donations!A4:N200""),3,8),"""")"),"") | K89: =IFERROR(__xludf.DUMMYFUNCTION("IFERROR(INDEX(IMPORTRANGE(""1wF8uimz-gnzzmqfjHb8Ua7fudqcoq5SrFyToq2B2IO0"",""💰 Donations!A4:N200""),3,11),"""")"),"") | L89: =IFERROR(__xludf.DUMMYFUNCTION("IFERROR(INDEX(IMPORTRANGE(""1wF8uimz-gnzzmqfjHb8Ua7fudqcoq5SrFyToq2B2IO0"",""💰 Donations!A4:N200""),3,13),"""")"),"") | M89: =IFERROR(__xludf.DUMMYFUNCTION("IFERROR(INDEX(IMPORTRANGE(""1wF8uimz-gnzzmqfjHb8Ua7fudqcoq5SrFyToq2B2IO0"",""💰 Donations!A4:N200""),3,14),"""")"),"") | N89: =IFERROR(__xludf.DUMMYFUNCTION("IFERROR(IF(INDEX(IMPORTRANGE(""1wF8uimz-gnzzmqfjHb8Ua7fudqcoq5SrFyToq2B2IO0"",""💰 Donations!A4:N200""),3,10)="""","""",TEXT(INDEX(IMPORTRANGE(""1wF8uimz-gnzzmqfjHb8Ua7fudqcoq5SrFyToq2B2IO0"",""💰 Donations!A4:N200""),3,10),""DD-MM-YYYY"")),"""")"),"")
A90: =IFERROR(__xludf.DUMMYFUNCTION("IFERROR(INDEX(IMPORTRANGE(""1wF8uimz-gnzzmqfjHb8Ua7fudqcoq5SrFyToq2B2IO0"",""💰 Donations!A4:N200""),4,1),"""")"),"") | B90: =IFERROR(__xludf.DUMMYFUNCTION("IFERROR(INDEX(IMPORTRANGE(""1wF8uimz-gnzzmqfjHb8Ua7fudqcoq5SrFyToq2B2IO0"",""💰 Donations!A4:N200""),4,2),"""")"),"") | D90: =IFERROR(__xludf.DUMMYFUNCTION("IFERROR(IFERROR(INDEX(IMPORTRANGE(""1wF8uimz-gnzzmqfjHb8Ua7fudqcoq5SrFyToq2B2IO0"",""💰 Donations!A4:N200""),4,3)*1,0),0)"),0.0) -> 0 | E90: =IFERROR(__xludf.DUMMYFUNCTION("IFERROR(IFERROR(INDEX(IMPORTRANGE(""1wF8uimz-gnzzmqfjHb8Ua7fudqcoq5SrFyToq2B2IO0"",""💰 Donations!A4:N200""),4,4)*1,0),0)"),0.0) -> 0 | F90: =IFERROR(D90-E90,0) -> 0 | G90: =IF(A90="","",IF(OR(E90=0,E90=""),"Pending",IF(E90>=D90,"Received","Partially Received"))) | H90: =IFERROR(__xludf.DUMMYFUNCTION("IFERROR(INDEX(IMPORTRANGE(""1wF8uimz-gnzzmqfjHb8Ua7fudqcoq5SrFyToq2B2IO0"",""💰 Donations!A4:N200""),4,6),"""")"),"") | I90: =IFERROR(__xludf.DUMMYFUNCTION("IFERROR(IF(INDEX(IMPORTRANGE(""1wF8uimz-gnzzmqfjHb8Ua7fudqcoq5SrFyToq2B2IO0"",""💰 Donations!A4:N200""),4,7)="""","""",TEXT(INDEX(IMPORTRANGE(""1wF8uimz-gnzzmqfjHb8Ua7fudqcoq5SrFyToq2B2IO0"",""💰 Donations!A4:N200""),4,7),""DD-MM-YYYY"")),"""")"),"") | J90: =IFERROR(__xludf.DUMMYFUNCTION("IFERROR(INDEX(IMPORTRANGE(""1wF8uimz-gnzzmqfjHb8Ua7fudqcoq5SrFyToq2B2IO0"",""💰 Donations!A4:N200""),4,8),"""")"),"") | K90: =IFERROR(__xludf.DUMMYFUNCTION("IFERROR(INDEX(IMPORTRANGE(""1wF8uimz-gnzzmqfjHb8Ua7fudqcoq5SrFyToq2B2IO0"",""💰 Donations!A4:N200""),4,11),"""")"),"") | L90: =IFERROR(__xludf.DUMMYFUNCTION("IFERROR(INDEX(IMPORTRANGE(""1wF8uimz-gnzzmqfjHb8Ua7fudqcoq5SrFyToq2B2IO0"",""💰 Donations!A4:N200""),4,13),"""")"),"") | M90: =IFERROR(__xludf.DUMMYFUNCTION("IFERROR(INDEX(IMPORTRANGE(""1wF8uimz-gnzzmqfjHb8Ua7fudqcoq5SrFyToq2B2IO0"",""💰 Donations!A4:N200""),4,14),"""")"),"") | N90: =IFERROR(__xludf.DUMMYFUNCTION("IFERROR(IF(INDEX(IMPORTRANGE(""1wF8uimz-gnzzmqfjHb8Ua7fudqcoq5SrFyToq2B2IO0"",""💰 Donations!A4:N200""),4,10)="""","""",TEXT(INDEX(IMPORTRANGE(""1wF8uimz-gnzzmqfjHb8Ua7fudqcoq5SrFyToq2B2IO0"",""💰 Donations!A4:N200""),4,10),""DD-MM-YYYY"")),"""")"),"")
